Workbook

Sheet TOC
A1: File | B1: Translator | C1: Status | D1: Note
A2: AccessoryItemMessage.csv | C2: =SUMPRODUCT(--(LEN(AccessoryItemMessage!C2:C247)>1))/SUMPRODUCT(--(LEN(AccessoryItemMessage!B2:B247)>1)) | D2: Thảo luận tại forum: https://viethoagame.com/threads/i-am-setsuna.90/ Hoặc discord #set: https://discord.gg/YE59VVK
A3: AutoSetsunaSystemDataMessage.csv | C3: =SUMPRODUCT(--(LEN(AutoSetsunaSystemDataMessage!C2:C21)>1))/SUMPRODUCT(--(LEN(AutoSetsunaSystemDataMessage!B2:B21)>1))
A4: BraveStoryCategoryMessage.csv | C4: =SUMPRODUCT(--(LEN(BraveStoryCategoryMessage!C2:C120)>1))/SUMPRODUCT(--(LEN(BraveStoryCategoryMessage!B2:B120)>1))
A5: BraveStoryCoopMessage.csv | C5: =SUMPRODUCT(--(LEN(BraveStoryCoopMessage!C2:C138)>1))/SUMPRODUCT(--(LEN(BraveStoryCoopMessage!B2:B138)>1))
A6: BraveStoryGeographyMessage.csv | C6: =SUMPRODUCT(--(LEN(BraveStoryGeographyMessage!C2:C185)>1))/SUMPRODUCT(--(LEN(BraveStoryGeographyMessage!B2:B185)>1))
A7: BraveStoryItemMessage.csv | C7: =SUMPRODUCT(--(LEN(BraveStoryItemMessage!C2:C356)>1))/SUMPRODUCT(--(LEN(BraveStoryItemMessage!B2:B356)>1))
A8: BraveStoryMateriaMessage.csv | C8: =SUMPRODUCT(--(LEN(BraveStoryMateriaMessage!C2:C223)>1))/SUMPRODUCT(--(LEN(BraveStoryMateriaMessage!B2:B223)>1))
A9: BraveStoryMemoMessage.csv | C9: =SUMPRODUCT(--(LEN(BraveStoryMemoMessage!C2:C77)>1))/SUMPRODUCT(--(LEN(BraveStoryMemoMessage!B2:B77)>1))
A10: BraveStoryMonsterMessage.csv | C10: =SUMPRODUCT(--(LEN(BraveStoryMonsterMessage!C2:C207)>1))/SUMPRODUCT(--(LEN(BraveStoryMonsterMessage!B2:B207)>1))
A11: BraveStoryNoteMessage.csv | C11: =SUMPRODUCT(--(LEN(BraveStoryNoteMessage!C2:C75)>1))/SUMPRODUCT(--(LEN(BraveStoryNoteMessage!B2:B75)>1))
A12: BraveStoryPersonMessage.csv | C12: =SUMPRODUCT(--(LEN(BraveStoryPersonMessage!C2:C101)>1))/SUMPRODUCT(--(LEN(BraveStoryPersonMessage!B2:B101)>1))
A13: BraveStorySetsunaMessage.csv | C13: =SUMPRODUCT(--(LEN(BraveStorySetsunaMessage!C2:C36)>1))/SUMPRODUCT(--(LEN(BraveStorySetsunaMessage!B2:B36)>1))
A14: BraveStorySublimationMessage.csv | C14: =SUMPRODUCT(--(LEN(BraveStorySublimationMessage!C2:C24)>1))/SUMPRODUCT(--(LEN(BraveStorySublimationMessage!B2:B24)>1))
A15: BraveStoryWeaponMessage.csv | C15: =SUMPRODUCT(--(LEN(BraveStoryWeaponMessage!C2:C84)>1))/SUMPRODUCT(--(LEN(BraveStoryWeaponMessage!B2:B84)>1))
A16: ConsumptionItemMessage.csv | C16: =SUMPRODUCT(--(LEN(ConsumptionItemMessage!C2:C37)>1))/SUMPRODUCT(--(LEN(ConsumptionItemMessage!B2:B37)>1))
A17: CookingItemMessage.csv | C17: =SUMPRODUCT(--(LEN(CookingItemMessage!C2:C45)>1))/SUMPRODUCT(--(LEN(CookingItemMessage!B2:B45)>1))
A18: EnemyBossSkillDataMessage.csv | C18: =SUMPRODUCT(--(LEN(EnemyBossSkillDataMessage!C2:C549)>1))/SUMPRODUCT(--(LEN(EnemyBossSkillDataMessage!B2:B549)>1))
A19: EnemyCoopSkillDataMessage.csv | C19: =SUMPRODUCT(--(LEN(EnemyCoopSkillDataMessage!C2:C81)>1))/SUMPRODUCT(--(LEN(EnemyCoopSkillDataMessage!B2:B81)>1))
A20: EnemySetParameterMessage.csv | C20: =SUMPRODUCT(--(LEN(EnemySetParameterMessage!C2:C209)>1))/SUMPRODUCT(--(LEN(EnemySetParameterMessage!B2:B209)>1))
A21: EnemySkillDataMessage.csv | C21: =SUMPRODUCT(--(LEN(EnemySkillDataMessage!C2:C181)>1))/SUMPRODUCT(--(LEN(EnemySkillDataMessage!B2:B181)>1))
A22: EventItemMessage.csv | C22: =SUMPRODUCT(--(LEN(EventItemMessage!C2:C65)>1))/SUMPRODUCT(--(LEN(EventItemMessage!B2:B65)>1))
A23: GrimreaperSkillDataMessage.csv | C23: =SUMPRODUCT(--(LEN(GrimreaperSkillDataMessage!C2:C39)>1))/SUMPRODUCT(--(LEN(GrimreaperSkillDataMessage!B2:B39)>1))
A24: IntensifyMessage.csv | C24: =SUMPRODUCT(--(LEN(IntensifyMessage!C2:C13)>1))/SUMPRODUCT(--(LEN(IntensifyMessage!B2:B13)>1))
A25: ItemSkillDataMessage.csv | C25: =SUMPRODUCT(--(LEN(ItemSkillDataMessage!C2:C11)>1))/SUMPRODUCT(--(LEN(ItemSkillDataMessage!B2:B11)>1))
A26: KishilSkillDataMessage.csv | C26: =SUMPRODUCT(--(LEN(KishilSkillDataMessage!C2:C39)>1))/SUMPRODUCT(--(LEN(KishilSkillDataMessage!B2:B39)>1))
A27: MaterialItemMessage.csv | C27: =SUMPRODUCT(--(LEN(MaterialItemMessage!C2:C819)>1))/SUMPRODUCT(--(LEN(MaterialItemMessage!B2:B819)>1))
A28: MateriaMessage.csv | C28: =SUMPRODUCT(--(LEN(MateriaMessage!C2:C877)>1))/SUMPRODUCT(--(LEN(MateriaMessage!B2:B877)>1))
A29: NPCSetParameterMessage.csv | C29: =SUMPRODUCT(--(LEN(NPCSetParameterMessage!C2:C667)>1))/SUMPRODUCT(--(LEN(NPCSetParameterMessage!B2:B667)>1))
A30: PlayerSetParameterMessage.csv | C30: =SUMPRODUCT(--(LEN(PlayerSetParameterMessage!C2:C19)>1))/SUMPRODUCT(--(LEN(PlayerSetParameterMessage!B2:B19)>1))
A31: PlayerSkillDataMessage.csv | C31: =SUMPRODUCT(--(LEN(PlayerSkillDataMessage!C2:C39)>1))/SUMPRODUCT(--(LEN(PlayerSkillDataMessage!B2:B39)>1))
A32: ScenarioMessageData_Chapter_1.csv | C32: =SUMPRODUCT(--(LEN(ScenarioMessageData_Chapter_1!C2:C1405)>1))/SUMPRODUCT(--(LEN(ScenarioMessageData_Chapter_1!B2:B1405)>1))
A33: ScenarioMessageData_Chapter_2.csv | C33: =SUMPRODUCT(--(LEN(ScenarioMessageData_Chapter_2!C2:C1715)>1))/SUMPRODUCT(--(LEN(ScenarioMessageData_Chapter_2!B2:B1715)>1))
A34: ScenarioMessageData_Chapter_3.csv | C34: =SUMPRODUCT(--(LEN(ScenarioMessageData_Chapter_3!C2:C1346)>1))/SUMPRODUCT(--(LEN(ScenarioMessageData_Chapter_3!B2:B1346)>1))
A35: ScenarioMessageData_Chapter_4.csv | C35: =SUMPRODUCT(--(LEN(ScenarioMessageData_Chapter_4!C2:C807)>1))/SUMPRODUCT(--(LEN(ScenarioMessageData_Chapter_4!B2:B807)>1))
A36: ScenarioMessageData_NormalConversation.csv | C36: =SUMPRODUCT(--(LEN(ScenarioMessageData_NormalConv!C2:C3)>1))/SUMPRODUCT(--(LEN(ScenarioMessageData_NormalConv!B2:B3)>1))
A37: SetsunaSkillDataMessage.csv | C37: =SUMPRODUCT(--(LEN(SetsunaSkillDataMessage!C2:C39)>1))/SUMPRODUCT(--(LEN(SetsunaSkillDataMessage!B2:B39)>1))
A38: SetsunaSystemDataMessage.csv | C38: =SUMPRODUCT(--(LEN(SetsunaSystemDataMessage!C2:C493)>1))/SUMPRODUCT(--(LEN(SetsunaSystemDataMessage!B2:B493)>1))
A39: SionSkillDataMessage.csv | C39: =SUMPRODUCT(--(LEN(SionSkillDataMessage!C2:C39)>1))/SUMPRODUCT(--(LEN(SionSkillDataMessage!B2:B39)>1))
A40: SublimationDataMessage.csv | C40: =SUMPRODUCT(--(LEN(SublimationDataMessage!C2:C45)>1))/SUMPRODUCT(--(LEN(SublimationDataMessage!B2:B45)>1))
A41: SubQuestMessageData.csv | C41: =SUMPRODUCT(--(LEN(SubQuestMessageData!C2:C23)>1))/SUMPRODUCT(--(LEN(SubQuestMessageData!B2:B23)>1))
A42: ThreePlayerCoopSkillDataMessage.csv | C42: =SUMPRODUCT(--(LEN(ThreePlayerCoopSkillDataMessag!C2:C145)>1))/SUMPRODUCT(--(LEN(ThreePlayerCoopSkillDataMessag!B2:B145)>1))
A43: TsukushiSkillDataMessage.csv | C43: =SUMPRODUCT(--(LEN(TsukushiSkillDataMessage!C2:C39)>1))/SUMPRODUCT(--(LEN(TsukushiSkillDataMessage!B2:B39)>1))
A44: TwoPlayerCoopSkillDataMessage.csv | C44: =SUMPRODUCT(--(LEN(TwoPlayerCoopSkillDataMessage!C2:C131)>1))/SUMPRODUCT(--(LEN(TwoPlayerCoopSkillDataMessage!B2:B131)>1))
A45: WeaponItemMessage.csv | C45: =SUMPRODUCT(--(LEN(WeaponItemMessage!C2:C163)>1))/SUMPRODUCT(--(LEN(WeaponItemMessage!B2:B163)>1))
A46: YomiSkillDataMessage.csv | C46: =SUMPRODUCT(--(LEN(YomiSkillDataMessage!C2:C39)>1))/SUMPRODUCT(--(LEN(YomiSkillDataMessage!B2:B39)>1))

Sheet AccessoryItemMessage
A1: ID | B1: English | C1: Vietnamese | D1: Note
A2: 0.001_ | B2: 2 | D2: 2
A3: 1_ | B3: True | D3: True
A4: 1.001_ | B4: 0 | D4: 0
A5: 2_ | B5: 121 | D5: 121
A6: 3_ | B6: Mark of the Masked Tribe | C6: Dấu hiệu của bộ tộc Mặt Nạ | D6: 仮面族の証
A7: 4_ | B7: A mark carried by adult members of the masked tribe. It is given to them by the chieftain to signify their coming of age. | C7: Là dấu hiệu ở người trưởng thành của bộ tộc Mặt nạ. Họ được mang dấu hiệu này sau lễ trưởng thành, được cấp bởi tộc trưởng. | D7: 成人した仮面の一族が持つ証。 族長に一人前と認められた時に渡される法器。
A8: 5_ | B8: Dawn Amulet | C8: Bùa Bình Minh | D8: 暁の守り
A9: 6_ | B9: This amulet is adorned with a rising sun motif. It is imbued with a magic spell that has been passed down in the village for many years. | C9: Một tấm mề đay khắc hình mặt trời mọc. Được ếm 1 câu thần chú được truyền lại trong làng từ rất lâu. | D9: 太陽が昇る意匠がほどこされたお守り。 集落に伝わるまじないが込められている。
A10: 7_ | B10: Frog Doll | C10: Búp Bê Ếch | D10: カエルの人形
A11: 8_ | B11: A doll depicting a mysterious creature with green skin and bulging eyes. Some say it is a proto- creature that conquered land and sea long ago. | C11: Một con búp bê có hình dáng 1 sinh vật kì quái với làn da xanh và mắt trố. Nó được cho là 1 sinh vật cổ đại từng thống trị thế giới. | D11: 表面が緑色で目が大きい謎の生き物を象った人形。 一説によると古代、海と陸を制覇した 生物の原型とも言われているが定かではない。
A12: 9_ | B12: Ancient Charm | C12: Trang Sức Cổ Đại | D12: オールドチャーム
A13: 10_ | B13: A metal charm fashioned in the shape of a wing. It is old and worn, but carefully maintained, and it is clear that its former owner took great care of it. | C13: Một đồ trang sức có hình đôi cánh. Dù cũ và sắp hỏng nhưng nó được bảo quản cẩn thận. Rõ ràng chủ trước rất trân trọng món đồ này. | D13: 羽の形をした金属製の装飾品。 古ぼけてはいるが、手入れが行き届いており 前の持ち主が大事にしていたことがわかる。
A14: 11_ | B14: Firestone | C14: Đá Lửa | D14: ファイアストーン
A15: 12_ | B15: When held to the light, the fissures inside this stone resemble flickering flames. | C15: Dưới ánh sáng, họa tiết bên trong viên đá có hình ngọn lửa. | D15: 見る角度によって 内部の亀裂が炎のゆらぎにもみえる紅玉。
A16: 13_ | B16: Ancient Crest | C16: Huy Hiệu Cổ Đại | D16: 古の紋章
A17: 14_ | B17: This pendant bears the crest of an ancient royal family that fell long ago. | C17: Chiếc huân chương có khắc huy hiệu của 1 Hoàng tộc cổ đại. | D17: 今はなき、古代王家の紋章が刻まれたペンダント。
... A247: 244_ | B247: This talisman is said to grant happiness to its bearer. It becomes more powerful with each successive owner, granting even greater happiness. | C247: Phù chú này sẽ mang đến hạnh phúc cho người dùng. Nó trở nên mạnh hơn khi ở trong tay người giàu, mang lại nhiều hạnh phúc hơn/ | D247: 持つ物に幸せを与えるとされている法器。 さまざまな人に受け継がれてきた想いが 持ち主に更なる幸福をもたらす。

Sheet AutoSetsunaSystemDataMessage
A1: ID | B1: English | C1: Vietnamese | D1: Note
A2: 244.001_ | B2: 2 | D2: 2
A3: 245_ | B3: True | D3: True
A4: 245.001_ | B4: 0 | D4: 0
A5: 245.002_ | B5: 8 | D5: 8
A6: 246_ | B6: Chrono Burst | C6: Bùng Nổ | D6: クロノバースト
A7: 247_ | B7: ATB speed is greatly increased. However, combos can no longer be used. | C7: Tốc độ hồi ATB tăng mạnh. Tuy nhiên, không thể dùng combo được nữa. | D7: ATBが高速でたまり、連続行動ができる。 その代わり、連携が使えなくなる。
A8: 248_ | B8: Momentum Control | C8: Điều Khiển Momentum | D8: 刹那の極意
A9: 249_ | B9: SP speed is greatly increased. The power of Momentum mode effects is also increased. | C9: Tốc độ hồi SP tăng mạnh. Hiệu quả khi sử dụng chế độ Momentum tăng. | D9: SPがたまりやすくなる。 刹那システムの発動効果も強くなる。
A10: 250_ | B10: Elemental Inflation | C10: Điều Khiển Nguyên Tố | D10: 属性インフレ
A11: 251_ | B11: All attacks cause all-elemental damage, and all resistances match the highest resistance. | C11: Đòn tấn công chứa đựng tấn cả thuộc tính, khả năng kháng được đẩy toàn bộ bằng khả năng kháng cao nhất. | D11: 攻撃属性が強制的に全属性になる。 耐性も全ての耐性が一番高い数値になる。
A12: 252_ | B12: Probability Change | C12: Thay Đổi Xác Suất | D12: 確率変動
A13: 253_ | B13: Critical hits are generated more easily, and status ailments are inflicted more easily. | C13: Tăng khả năng tung đòn chí mạng, đồng thời tăng khả năng gây ra hiệu ứng. | D13: クリティカルが発生しやすくなる。 状態異常も発生しやすくなる。
A14: 254_ | B14: Timelight | C14: Ánh Sáng Thời Gian | D14: 創刻の光
A15: 255_ | B15: Damage adjustment counters will no longer be reset, even by enemy attacks. | C15: Sát thương gây ra sẽ không bị ảnh hưởng. | D15: 特殊な威力補正用カウントがリセットしない。 敵の行動によるリセットも起きなくなる。
A16: 256_ | B16: Guardian Goddess | C16: Kẻ Bảo Vệ Nữ Thần | D16: 聖女の加護
A17: 257_ | B17: HP of allies will no longer be reduced below 1, except due to Death. | C17: Lượng HP của đồng minh không bao giờ xuống dưới 1, kể cả bị Thần Chết tấn công. | D17: 味方のHPが1以下にならなくなる。 ただし、即死で戦闘不能になることはある。
... A21: 261_ | B21: Fluxation occurs more easily, and tech power rises based on no. of Fluxes. | C21: Sự đột biến năng lượng xảy ra thường xuyên, sát thương chiêu thức tăng. | D21: 昇華が発生しやすくなる。 魔法の昇華数が多いほど、威力が強くなる。

Sheet BraveStoryCategoryMessage
A1: ID | B1: English | C1: Vietnamese | D1: Note
A2: 261.001_ | B2: 2 | D2: 2
A3: 262_ | B3: True | D3: True
A4: 262.001_ | B4: 0 | D4: 0
A5: 263_ | B5: 115 | D5: 115
A6: 264_ | B6: Nive Island | C6: Đảo Nive | D6: モル島
A7: 265_ | B7: Floneian Territories | C7: Lãnh thổ người Floneian | D7: ウカテイナ領
A8: 266_ | B8: Northern Frontier | C8: Biên giới phía Bắc | D8: 北方辺境
A9: 267_ | B9: Fridging Mountain Range | C9: Dãy Băng Sơn | D9: オッカオッカ山岳地帯
A10: 268_ | B10: Remote Islands | C10: Hòn đảo hẻo lánh | D10: 絶海群島
A11: 269_ | B11: F Area | C11: Khu vực F | D11: F地方
A12: 270_ | B12: G Area | C12: Khu vực G | D12: G地方
A13: 271_ | B13: H Area | C13: Khu vực H | D13: H地方
A14: 272_ | B14: I Area | C14: Khu vực I | D14: I地方
A15: 273_ | B15: J Area | C15: Khu vực J | D15: J地方
A16: 274_ | B16: Items | C16: Vật Phẩm | D16: 道具
A17: 275_ | B17: Tempering Items | C17: Vật Phẩm Tạm Thời | D17: 武器強化道具
... A120: 378_ | B120: Extra | C120: Thêm | D120: 番外

Sheet BraveStoryCoopMessage
A1: ID | B1: English | C1: Vietnamese | D1: Note
A2: 378.001_ | B2: 2 | D2: 2
A3: 379_ | B3: True | D3: True
A4: 379.001_ | B4: 0 | D4: 0
A5: 380_ | B5: 133 | D5: 133
A6: 381_ | B6: Synchronizes the healing power of the users, recovering the HP of all allies and healing all status ailments. When used in Momentum mode, it will also recover MP. | C6: Đồng bộ hóa sức mạnh chữa bệnh của người dùng, phục hồi HP của tất cả các đồng minh và chữa lành tất cả các trạng thái bệnh. Khi được sử dụng ở chế độ Momentum, nó cũng sẽ phục hồi MP. | D6: 癒しの魔力を同調させて、HP回復と全ての状態異常を解除する効果が全体に発生する。 刹那システムを発動すると、MP回復することもできる。
A7: 382_ | B7: One user imbues the other's sword with the power of lightning, producing a powerful strike. Causes increased damage when striking a foe's weakness. When used in Momentum mode, damage will be even further increased when striking a weakness. | C7: "Một người sử dụng thấm nhuần thanh kiếm của người kia với sức mạnh của tia sét, tạo ra một đòn tấn công mạnh mẽ. Gây sát thương tăng lên khi tấn công điểm yếu của kẻ thù. | D7: 雷の力を剣にのせて、叩きつける攻撃である。弱点属性に攻撃したときに威力が大きくなるという特性がある。 刹那システムを発動すると、弱点属性を攻撃したときに威力が大きくなる攻撃がさらに発生する。
A8: 383_ | B8: This combo can only be used by two people with an unshakable bond. It creates harmony among the party, raising the stats of all allies to the same value as that of the ally with the highest stat. When used in Momentum mode, its duration will be increased. | C8: Khi sử dụng ở chế độ Momentum, sát thương sẽ còn tăng hơn nữa khi chạm vào một điểm yếu. " | D8: 揺るぎのない深いつながりがあるからこそできる連携であり、パーティの波長を同調させることで、全員の能力値がパーティの中で一番高い数値になる。 刹那システムを発動すると、発生時間が長くなる。
A9: 384_ | B9: The users' strikes cross each other, creating an X-shaped trail that causes damage to enemies. It inflicts more damage the sooner the two strikes cross. When used in Momentum mode, this combo will also cause additional physical damage to a single enemy. | C9: Đòn đánh của hai người dùng giao nhau, tạo thành vệt chém hình chữ X gây sát thương lên kẻ địch. Càng tung đòn giao kiếm sớm sát thương càng cao. Khi sử dụng ở chế độ Xung Lực, liên chiêu này sẽ gây thêm sát thương vật lý phụ lên một mục tiêu. | D9: エックスの軌跡ができるように2人で交差するように斬り抜ける連携である。斬撃の交差点が近いほど威力が大きくなる。 刹那システムを発動すると、敵単体に物理攻撃が発生する。
A10: 385_ | B10: This combo uses the combined magical energy of the two users to manipulate space-time, causing effects to be generated twice when Momentum mode is triggered. When used in Momentum mode, its duration will be increased. | C10: Liên chiêu này kết hợp ma lực của hai người dùng để thao túng không-thời gian, giúp kích hoạt hiệu ứng hai lần khi ở chế độ Xung Lực. Khi sử dụng ở chế độ Xung Lực, thời gian hiệu lực của kỹ năng sẽ được gia tăng. | D10: 2人で集束した膨大な魔力によって時空を操作する連携である。刹那システムを発動したときに連続して同じ効果が発生するようになる。 刹那システムを発動すると、発生時間が長くなる。
A11: 386_ | B11: This combo uses Momentum power to create a barrier, then destroys it, triggering a blast that causes damage to enemies. It also raises the SP gauges of all allies. When used in Momentum mode, it will also cause physical damage that increases in power according to how high SP is. | C11: Liên chiêu này sử dụng sức mạnh Xung Lực tạo ra lá chắn rồi phá hủy nó, giải phóng vụ nổ gây sát thương lên kẻ địch. Đồng thời làm tăng thanh SP của toàn đội. Khi dùng ở chế độ Xung Lực, nó sẽ gây thêm sát thương vật lý tăng theo lượng SP. | D11: 刹那の力によって発生した結界を破壊した衝撃で攻撃する。攻撃するだけでなく、味方のSPもたまるという汎用性の高い連携である。 刹那システムを発動すると、SPが高いほど威力が大きくなる物理攻撃が発生する。
A12: 387_ | B12: Energy blades fired by the two users create a cross-shaped slash. When used in Momentum mode, this combo will also cause additional physical damage to all enemies. | C12: Lưỡi kiếm năng lượng được phóng ra bởi hai người dùng tạo thành một nhát chém chữ thập hình dấu X. Khi sử dụng ở chế độ Xung Lực, liên chiêu này sẽ gây thêm sát thương vật lý phụ lên toàn bộ kẻ địch. | D12: 闘気の刃で生みだす十字斬りが発生する。 刹那システムを発動すると、敵全体に物理攻撃が発生する。
A13: 388_ | B13: Hits all enemies with a powerful pressure attack that can sometimes also inflict Paralysis, Confusion, and Stun. When used in Momentum mode, this combo will also reduce Attack and Defense. | C13: Tấn công toàn bộ kẻ địch bằng áp lực kiếm khí cực mạnh, có tỉ lệ gây trạng thái Tê Liệt, Hỗn Loạn và Choáng. Khi sử dụng ở chế độ Xung Lực, liên chiêu này cũng sẽ làm giảm chỉ số Tấn Công và Phòng Thủ của địch. | D13: 敵を威圧して攻撃しながら、麻痺と混乱とスタンを発生させる。 刹那システムを発動すると、さらに攻撃力と防御力も低下させる攻撃が発生する。
A14: 389_ | B14: Launches enemies into the air before sending them hurtling down again. Has a high critical hit rate, and also ignores 30% of Defense. When used in Momentum mode, this combo will also boost evasion rate, making it effective in terms of both attack and defense. | C14: Hất tung kẻ địch lên không trung trước khi giáng mạnh chúng xuống đất. Đòn đánh có tỉ lệ chí mạng cao và bỏ qua 30% Phòng Thủ. Khi sử dụng ở chế độ Xung Lực, liên chiêu này sẽ tăng tỉ lệ né tránh, hiệu quả trong cả tấn công lẫn phòng ngự. | D14: 敵を打ち上げて叩き落とす攻撃である。クリティカル率が高く、防御を30%を無視する特性がある。 刹那システムを発動すれば、回避率が上昇するため、攻防一体の連携となる。
A15: 390_ | B15: Charges the blade with absorptive magical energy and slashes at surrounding foes. 40% of the damage inflicted is absorbed by all allies as HP. When used in Momentum mode, HP will also be recovered. An excellent combo that combines both attack and recovery. | C15: Truyền ma lực hấp thụ vào lưỡi kiếm và chém quét mọi kẻ thù xung quanh. 40% lượng sát thương gây ra được toàn đội hấp thụ thành HP. Khi sử dụng ở chế độ Xung Lực, lượng HP hồi phục sẽ được gia tăng, tạo nên đòn đánh hoàn hảo cả công lẫn thủ. | D15: 吸収の魔力を剣にこめて、周囲を斬りつける攻撃である。与えたダメージの40%を味方全体でHP吸収する。 刹那システムを発動すると、HPを回復することもできる。攻撃以上に回復として優秀な連携である。
A16: 391_ | B16: One user imbues the other's sword with the power of fire, producing a powerful strike. Causes increased damage when striking a foe's weakness. When used in Momentum mode, damage will be even further increased when striking a weakness. | C16: Một người truyền hỏa lực vào kiếm của người kia,|giáng đòn công kích dũng mãnh. Gây thêm sát thương|khi đánh trúng điểm yếu của kẻ địch. Khi dùng ở chế độ|Momentum, sát thương trúng điểm yếu sẽ tăng mạnh hơn|nữa. | D16: 炎の力を剣にのせて、叩きつける攻撃である。弱点属性に攻撃したときに威力が大きくなるという特性がある。 刹那システムを発動すると、弱点属性を攻撃したときに威力が大きくなる攻撃がさらに発生する。
A17: 392_ | B17: Attacks by summoning a meteor storm from the skies above, causing damage that ignores 50% of Defense. When used in Momentum mode, this combo will also cause additional magical damage to a single enemy. The single-user tech "Meteo" was originally adapted from this combo. | C17: Tấn công bằng cách triệu hồi một cơn bão thiên thạch từ bầu trời, gây sát thương bỏ qua 50% Phòng Thủ. Khi sử dụng ở chế độ Xung Lực, chiêu thức gây thêm sát thương ma thuật phụ lên một kẻ địch. Kỹ năng đơn lẻ 'Thiên Thạch' vốn được phỏng theo liên chiêu này. | D17: 天から膨大な流星が降り注ぐ攻撃である。防御を50%無視する効果がある。 刹那システムを発動すると、魔法攻撃が敵単体に発生する。 連携として編み出されたメテオの本来の形であり、後に1人でも使えるようにしたのが現在のメテオである。
... A138: 513_ | B138: This combo is a variation of Omega Drive, and its appearance is the same. It is less powerful, but when used in Momentum mode will cause additional special damage to all enemies that becomes more powerful according to the number of status boosts in effect. | C138: This combo is a variation of Omega Drive, and its appearance is the same. It is less powerful, but when used in Momentum mode will cause additional special damage lên toàn bộ kẻ địch that becomes more powerful according to the number of status boosts in effect. | D138: オメガドライブの特異版であり、見た目は同じである。 威力は控えめだが、刹那システムを発動すると、発生中の状態強化数が多いほど威力が大きくなる特殊攻撃が敵全体に発生する。

Sheet BraveStoryItemMessage
A1: ID | B1: English | C1: Vietnamese | D1: Note
A2: 561.001_ | B2: 2 | D2: 2
A3: 562_ | B3: True | D3: True
A4: 562.001_ | B4: 0 | D4: 0
A5: 563_ | B5: 351 | D5: 351
A6: 564_ | B6: Potion | C6: Thuốc Hồi Máu | D6: ポーション
A7: 565_ | B7: Mid-Potion | C7: Thuốc Hồi Máu - Trung | D7: ミドルポーション
A8: 566_ | B8: Hi-Potion | C8: Thuốc Hồi Máu - Cao | D8: ハイポーション
A9: 567_ | B9: Ether | C9: Thuốc Hồi MP | D9: エーテル
A10: 568_ | B10: Mid-Ether | C10: Thuốc Hồi MP - Trung | D10: ミドルエーテル
A11: 569_ | B11: Hi-Ether | C11: Thuốc Hồi MP - Cao | D11: ハイエーテル
A12: 570_ | B12: Elixir | C12: Elixir | D12: エリクサー
A13: 571_ | B13: Megalixir | C13: WOW Elixir | D13: ラストエリクサー
A14: 572_ | B14: Antidote | C14: Thuốc Giải Độc | D14: 毒消し
A15: 573_ | B15: Crescent Grass | C15: Cỏ Mặt Trăng | D15: 三日月草
A16: 574_ | B16: Smelling Salts | C16: Muối Bốc Mùi | D16: 気付け薬
A17: 575_ | B17: Panacea | C17: Panacea | D17: 万能薬
... A356: 914_ | B356: Lost Wallet | C356: Cái Ví Bị Thất Lạc | D356: だれかのさいふ

Sheet BraveStoryMateriaMessage
A1: ID | B1: English | C1: Vietnamese | D1: Note
A2: 914.001_ | B2: 2 | D2: 2
A3: 915_ | B3: True | D3: True
A4: 915.001_ | B4: 0 | D4: 0
A5: 916_ | B5: 218 | D5: 218
A6: 917_ | B6: The user channels magical energy into the blade, then swings it around, sending foes flying. Offers a wide attack range, and is also able to knock back enemies. When used in Momentum mode, it will also cause additional physical damage to all enemies. The channeling of magical energy is not hard to pull off, making it a simple and useful tech that is a favorite among those who make their living as mercenaries. | C6: Người dùng truyền năng lượng vào lưỡi kiếm rồi vung kiếm, hất tung kẻ địch. Là chiêu thức tấn công diện rộng, đồng thời có khả năng làm ngã choáng kẻ địch. Khi sử dụng chiêu ở chế độ Momentum sẽ gây thêm sát thương đối với toàn bộ kẻ địch. Việc truyền năng lượng có thể dễ dàng dừng lại, khiến cho chiêu thức trở nên đơn giản và hữu dụng, là chiêu thức yêu thích của lính đánh thuê. | D6: 魔力を剣に込めて、回転しながら斬り払う攻撃である。広い範囲に攻撃ができる上に、敵を吹っ飛ばすこともできる。刹那システムを発動すると、敵全体に物理攻撃が発生する。 魔力運用も難しいわけではなく、扱いやすい上に利便性も高く、傭兵稼業を生業にする者たちに愛用されている。
A7: 918_ | B7: Uses healing energy to aid the body's recovery from damage. As well as recovering HP, the ATB gauge will already be partially full after use, allowing another action to be performed in quick succession. When used in Momentum mode, it will also heal any status ailments, making it a popular tech among those who often fight alone. | C7: Sử dụng năng lực trị thương tự điều trị cho bản thân. Ngoài việc hồi phục HP, thanh ATB cũng sẽ đầy 1 phần sau khi sử dụng, cho phép người chơi thực hiện hành động khác nhanh chóng. Khi dùng ở chế độ Momentum, mọi hiệu ứng bất lợi bị giải trừ, đây là một chiêu thức phổ biến với người chơi đơn lẻ. | D7: 癒しの魔力をもって、身体の再生を促す魔法である。HPを回復することができるわけだが、使用後にATBがたまっている状態になるので、すぐに他の行動に移れるという利点がある。 刹那システムを発動すると、発生している状態異常を解除することができるため、一人で戦う機会が多い人から評価が高い。
A8: 919_ | B8: Releases a blast of magical energy next to the enemy. Out of the many magical attacks available, this is one of the few non-elemental ones, making it very valuable. When used in Momentum mode, it will also cause additional magical damage to a single enemy. Although a simple tech, its uses are wide-ranging, and its ease of use makes it one that is definitely worth learning. | C8: Giải phóng một vụ nổ pháp thuật ở gần kẻ địch. Trong số rất nhiều phép thuật tấn công, đây là một trong số ít những phép thuật phi nguyên tố, điều khiến nó trở nên giá trị. Khi dùng ở chế độ Momentum, nó sẽ gây thêm sát thương cho 1 kẻ địch. Dù đơn giản, chiêu thức này có cách sử dụng rất đa dạng và dễ sử dụng, là một chiêu thức đáng học. | D8: 圧縮した魔力を敵の懐で解放して、暴発させて攻撃する。魔法攻撃はたくさんあるが、無属性のものは少ないために、貴重な攻撃である。刹那システムを発動すると、敵単体に魔法攻撃が発生する。 単純な攻撃ではあるものの、工夫することで使い勝手も広く、何より扱いやすいため、使えるようにしておいて損がない魔法である。
A9: 920_ | B9: Creates a wall of magical energy that bears the brunt of attacks. It deploys shields that protect against both physical and magical damage. Each of these shields has HP, and will disappear once it reaches zero. When used in Momentum mode, the tech's effect will be applied to all allies. Not only can this tech be used to protect the user, it can also grant protection to one's charge, and is often used by those who work as mercenaries and bodyguards. | C9: Tạo ra một lớp lá chắn ma thuật có thể chịu được nhiều đòn tấn công. Triệu hồi các khiên ma thuật có thể đỡ các đòn tấn côn pháp thuật và vật lí. Các khiên có HP riêng, khi hết sẽ lập tức biến mất. Khi sử dụng ở chế độ Momentum, hiệu ứng của chiêu thức đồng thời áp dụng lên đồng minh. Không chỉ bảo vệ người sử dụng, có thể chọn người khác để cùng bảo vệ, hợp với lính đánh thuê hoặc bảo vệ. | D9: 魔力の障壁により、ダメージを肩代わりしてくれる壁を作る。物理攻撃には物理盾が、魔法攻撃には魔法盾が受けてくれる。盾には、ともにHPが設定されており、0になると消滅する。刹那を発動すると、効果が味方全体に発生するようになる。 使用者を護るというのは当然として、護衛対象を護るのにも便利であり、傭兵稼業を生業とする者たちがよく使っている。
A10: 921_ | B10: Fires a blade of energy. This tech is useful for attacking from a distance, and can also pierce through multiple enemies in a straight line, although damage is reduced with each successive hit. When used in Momentum mode it will also recover the HP of all allies. When used effectively, this tech can therefore provide both powerful attack and defense simultaneously. | C10: Bắn ra 1 tia năng lượng. Chiêu thức phù hợp với lối tấn công tầm trung-xa, gây sát thương đa mục tiêu trên 1 đường thẳng, sát thương giảm dần sau mỗi lần trúng thành công kẻ địch. Khi sử dụng ở chế độ Momentum sẽ hồi phục HP cho toàn bộ đồng minh. Khi sử dụng hiệu quả có thể đồng thời vừa là chiêu thức tấn công, vừa là chiêu thức phòng thủ. | D10: 闘気で作られた刃を飛ばすことで攻撃する。敵との間合いを取るのに便利であり、さらに刃は敵を貫通する効果を持つ。貫通するたびに威力は下がってしまう欠点はあるが、直線上にいる敵に一気に攻撃できるのが優秀である。 刹那を発動すると、味方全体のHPを回復することができるため、上手く使えば、攻防一体の非常に扱いやすい魔法となる。
A11: 922_ | B11: The user uses magical energy to sense enemy movements, then seizes a momentary gap in their defense to move behind them in a split second and strike. Although the damage caused is not that great, when used in Momentum mode, this tech will also cause extremely powerful additional damage. It is said to have been created for use in assassinations, though this is uncertain. | C11: Người dùng sử dụng năng lượng pháp thuật thăm dò hành động kẻ địch, sau đó chọn 1 điểm mù của kẻ địch, di chuyển ra đó trong chớp mắt và đột kích. Dù sát thương không quá lớn, khi sử dụng ở chế độ Momentum, chiêu thức có thể gây thêm 1 lượng sát thương cực lớn. Dù không chắc chắn, chiêu thức này có thể được tạo ra vì class sát thủ. | D11: 敵から放たれる気配を魔力によって察知し、隙ができた一瞬に敵の背後に回り込んで斬りつける攻撃である。 威力自体は控えめではあるものの、刹那を発動すると、非常に威力の高い攻撃を追撃することができる。暗殺をするために作られたものと言われるが、本当かは定かではない。
A12: 923_ | B12: Attacks using a blast created by combining physical and magical energy. Damage is calculated according to the lower of the enemy's physical defense or magical defense, making this a very useful tech. When used in Momentum mode, multiple hits with a high critical hit rate will also be inflicted. This tech gets its name from its divine appearance, and boasts equally magnificent power. | C12: Tấn công bằng 1 vụ nổ tạo ra bằng việc kết hợp năng lượng vật lí và pháp thuật. Sát thương gây ra dựa trên chỉ số phòng ngự vật lí hoặc ma pháp của đối phương, khiến cho chiêu thức cực kì hữu dụng. Khi sử dụng ở chế độ Momentum có đi kèm liên kích và khả năng chí mạng cao. Chiêu thức lấy tên từ vẻ ngoài thần thánh của nó, đồng thời có sức sát thương cao. Đẹp mà chất. | D12: 闘気と魔力を練り合わせて作りあげた破壊の衝撃で攻撃する。敵の物理防御と魔法防御の低い方がダメージ算出に使われるため、使い勝手がいい。刹那システムを発動すると、クリティカル率が高い連続攻撃が発生する。 神々しい見た目から名づけられた魔法であるが、名前に負けていない威力を誇っている。
A13: 924_ | B13: This tech creates a magical energy source that emanates spiritual power. It casts Concentration on all allies, automatically recovering MP. When used in Momentum mode, its duration will be increased. Developed in order to enable continued combat during long missions, this is an extremely useful tech, and a very popular one. | C13: Chiêu thức tạo ra 1 nguồn pháp thuật tỏa ra sức mạnh linh hồn. Buff hiệu ứng Tập Trung đối với toàn bộ đồng minh, tự động hồi toàn bộ MP. Khi sử dụng ở chế độ Momentum sẽ giảm thời gian chờ. Để hỗ trợ các cuộc chiến, nhiệm vụ dài hơi, chiêu thức được phát triển và rất hữu dụng, phổ biến. | D13: 精神力が湧きでる魔力源を生み出す魔法である。集中状態となり、MPが自動で回復するようになる。刹那システムを発動すると、発生時間が長くなる。 長時間の任務遂行を可能とするために、継戦能力を高めるために作られたものである。扱いやすい魔法であり、利便性も極めて高いため、愛用する者が多い。
A14: 925_ | B14: Purifies the spirit, recovering knocked-out allies. It will also recover the HP of those who are not knocked out. When used in Momentum mode, it will cast Auto-Revive status on allies for a set period of time. Although a useful tech that can be employed in a variety of situations, it requires its user to possess plentiful magical energy reserves, and so is not often seen in use. | C14: Thanh lọc linh hồn, hồi sinh các đồng minh đã bị knock-out, đồng thời hồi phục HP cho những đồng minh còn lại. Khi sử dụng ở chế độ Momentum sẽ tự động buff hiệu ứng Auto-Revive (tự động hồi sinh) cho đồng minh trong 1 khoảng thời gian cố định. Dù là 1 kĩ nẵng hữu ích và có tác dụng trong rất nhiều thời điểm, nó tiêu tốn của người dùng rất lượng lớn MP, vì vậy Thường không bắt gặp | D14: 魂を浄化することで、戦闘不能者ですら復活させることができる。戦闘不能ではない者に対してもHP回復できるという特性がある。刹那システムを発動すると、自動復活がしばらくの間発生するため、有用性が高い。 いろんな状況に対応できる便利な魔法ではあるが、高い魔力資質を持つ者にしか使えないため、なかなかお目にかかれない魔法でもある。
A15: 926_ | B15: The user channels power into the sword, jumps up, and then swings down with their full weight behind the weapon, releasing all the channeled energy upon impact. When used in Momentum mode, it will also cause additional physical damage to all enemies. Although the principle behind this attack is simple, it takes a huge toll on the user's body, and so is not a tech that can be used by just anyone. | C15: Người dùng truyền năng lượng vào thanh kiếm, nhảy lên, dồn toàn bộ trọng lượng cơ thể vào thanh kiếm và vung xuống, giải phóng năng lượng trong thanh kiếm. Khi sử dụng ở chế độ Momentum sẽ gây thêm sát thương cho toàn bộ kẻ địch. Dù nguyên lí của chiêu thức rất đơn giản, cơ thể người dùng sẽ phải chịu áp lực rất lớn, vậy nên không phải ai cũng có thể dùng được chiêu thức này. | D15: 持てる闘気を剣に流し込み、ジャンプしてから全体重をかけて、剣を振りおろした瞬間に、闘気を一気に爆発させる攻撃である。刹那システムを発動すると、敵全体に物理攻撃が発生する。 やっていることはシンプルながら、身体にかかる負荷は大きく、使い手を選ぶ魔法であると言えよう。
A16: 927_ | B16: Awakens dormant power, instantly filling the SP gauge and increasing the rate at which it fills up for a set period. When wanting to make full use of Momentum mode during battle, this tech is ideal. When used in Momentum mode, its duration will be increased. Although an extremely useful tech for mercenaries who must overcome any adverse situation, it requires a high level of ability from its user, and so is not often seen in use. | C16: Thức tỉnh năng lượng tiềm ẩn, ngay lập tức hồi đầy SP và tăng tốc độ hồi SP trong 1 khoảng thời gian. Chiêu thức rất hữu dụng khi muốn sử dụng chế độ Momentum đạt hiệu quả cao nhất. Ở chế độ Momentum, thời gian sử dụng tăng lên. Mặc dù chiêu thức rất hữu dụng đối với lính đánh thuê khi chống lại kẻ địch, nó yêu cầu người dùng có năng lực cao, vì vậy không thường xuyên bắt gặp chiêu thức này. | D16: 人間の眠る力を引き出すことができる。SPが一気にたまり、さらにSPがしばらくの間はたまりやすくなる。刹那システムを使いたいときにはうってつけの魔法と言える。刹那システムを発動すると、発生時間が長くなる。 どんな状況であっても任務遂行を求められる傭兵にとって、便利なものではあるが、使用に高い能力が求められるのか、使い手はあまり見ない。
A17: 928_ | B17: Stimulates the magical energy inside the body, creating an attack that uses Momentum power to maximum efficiency. The SP accumulated when using this tech is higher than usual, and the damage inflicted also increases according to the user's SP. When used in Momentum mode it will also recover HP, and if used effectively, battles can easily be won using this tech alone. It is said to have been invented by a legendary mercenary during a sacrificial pilgrimage. | C17: Kích thích năng lượng pháp thuật trong cơ thể, tạo ra 1 vụ tấn công sử dụng năng lượng Momentum để đạt hiệu quả cao nhất. SP tích lũy khi sử dụng chiêu thức nàycao hơn bình thường. Khi sử dụng ở chế độ Momentum còn hồi phục HP, và nếu được sử dụng hiệu quả, chỉ riêng chiêu thức này có thể kết thúc cả trận đấu. Tác giả của chiêu thức được đồn đại là 1 lính đánh thuê huyền thoại, sáng tạo khi đi hành hương. | D17: 体内にある魔力を活性化して、刹那の力を最大限活用する攻撃を行う。攻撃したときにより多くSPがたまり、SPが高いほど威力が大きくなる。刹那システムを発動すると、HP回復もできるので、上手く使えば、この魔法だけでも戦い抜ける。 伝説の傭兵がいけにえの旅路の最中で生みだした攻撃と言われている。
... A223: 1134_ | B223: Triggering Momentum mode when being attacked while HP is below 20% will generate a counterattack with an available combo. This spritnite stone has existed since before the Momentum system was completed, and when first discovered, its purpose was unknown. After many years of research, its power can now be used. | C223: Triggering Momentum mode when being attacked while HP is below 20% will generate a counterattack with an available combo. This spritnite stone has existed since before the Momentum system was completed, and when first discovered, its purpose was unknown. After many years of research, its power can now be used. | D223: HPが20%以下のときに攻撃を受けて、刹那システムを発動すると、使用可能な連携で攻撃した敵に反撃することができる。 刹那システムが完成する前から存在していた法石であり、発見された当初は使い方がわからないものであったが、研究を続けた結果、使いこなせるまでに至っている。

Sheet BraveStoryGeographyMessage
A1: ID | B1: English | C1: Vietnamese | D1: Note
A2: 513.001_ | B2: 2 | D2: 2
A3: 514_ | B3: True | D3: True
A4: 514.001_ | B4: 0 | D4: 0
A5: 515_ | B5: 45 | D5: 45
A6: 516_ | B6: A picturesque harbor on the coast of Nive Island. The ferries that sail to and from it serve as the only route between Nive and the mainland, so it has been built to accommodate ships of any size. All the sacrifices depart from here when beginning their pilgrimages, and it is referred to by some local people as "Farewell Harbor." The sea breeze means that snow does not settle as readily as on other parts of the island, but on windy days, powdered snow can often be seen dancing in the air. | C6: Một cảng biển thơ mộng trên bờ biển đảo Nive. Là cảng biển duy nhất trên đảo, nó được xây dựng để phù hợp với thuyền ở mọi kích cỡ di chuyển từ đảo ra Lục địa và ngược lại. Mọi vật tế bắt đầu cuộc hành hương của mình ở đây, vì vậy cảng này còn có tên là "Cảng Biệt Ly". Gió biển nhè nhẹ, tuyết ở đây rơi cũng không dày như ở các khu khác của đảo. Nhưng vào ngày gió mạnh, nơi này cũng có thể xuất hiện tuyết rơi. | D6: モル島にある美しい港。 本島と行き来できる唯一の手段が船による航路だけなので、大型船も停泊できるように設計されている。 いけにえが旅立つときは必ずこの港からなので「別れの港」と呼ぶ者もいる。 潮風の影響でそれほど深く雪は積もらないが、風の強い日は粉雪が舞うことも多い。
A7: 516.001_
A8: 516.002_
A9: 516.003_
A10: 517_ | B10: The village from which all the sacrifices are sent forth. The sacrificial tradition began here, and so it is known across the land as the "village of sacrifice." The sacrifices, who protect everyone from the monsters, are the only hope of people everywhere, and so Nive carries a grave responsibility. The people of the village therefore have a strong sense of duty and pride. | C10: Ngôi làng của tất cả các vật tế. Phong tục hiến tế cũng từ đây mà sinh ra, vì vậy ngôi làng được cả thế giới gọi là "Làng Hiến Tế". Những vật tế, những người bảo vệ mọi người khỏi quái vật, là niềm hi vọng duy nhất của tất cả, vì vậy ngôi làng có trách nhiệm rất lớn. Cũng chính vì thế, người dân trong làng có tinh thần trách nhiệm cùng danh dự rất lớn. | D10: いけにえを送り出せる唯一無二の村。 モルとは古代語で「雪深い」という意味である。 いけにえの歴史はこの村から始まったもので、そのため「はじまりの村」と言えば、知らない者はいない。 人々を魔物から守れる存在であるいけにえは、かけがえのない希望であるため、それを送り出せるモルの責任は重く、村人たちは使命感と誇りに支えられて、生活を営んでいる。
A11: 517.001_
A12: 517.002_
A13: 517.003_
A14: 518_ | B14: A forest situated to the northeast of <NAME=MA_0003_01>. Anyone who visits the woods for the first time and sees the sunlight filtering through the boughs of the trees, and the stunning red of the deciduous tree leaves against the brilliant white snow, will instantly understand the reason for this name. | C14: Một khu rừng ở phía Đông Bắc của <NAME=CP_0003_01>. Lữ khách tới đây sẽ ngay lập tức hiểu về cái tên của nó. Mặt trời xuyên qua từng tán cây, màu lá nhuộm đỏ rực cả một vùng trời đối lập với màu tuyết trắng xóa... | D14: <NAME=MA_0003_01>の北東に位置している森。 ヨーデとは古代語で「美しい」という意味で、ここを初めて訪れた者は、木々のあいだから差しこむ木漏れ日や冬期でも色づいている落葉樹の紅い葉が雪の白さに映えていて、まさしくヨーデと名づけられた理由に納得するという。
A15: 518.001_
A16: 518.002_
A17: 518.003_
A18: 519_ | B18: A monument engraved with the names of all the past sacrifices. The souls of the sacrifices are thought to return as the snow that falls across the land, and this monument was built in honor of them. The cliff on which it stands is considered a holy ground by the people of Nive, and it is time-honored tradition that all women chosen as sacrifices offer up a prayer to the monument before departing on their journeys. | C18: Bia mộ có khắc tên của tất cả những vật tế. Linh hồn của các vật tế sẽ trở về mỗi khi tuyết đầu mùa rơi, và bia mộ này được xây để tưởng nhớ họ. Vách đá nơi đặt bia mộ là vùng đất thiêng của đảo Nive, và trước khi bắt đầu cuộc hành hương, mọi vật tế sẽ đến đây cầu nguyện. | D18: 歴代のいけにえたちの名前が刻まれている石碑。 名残雪とは、春になっても残っている雪という意味であり、この村から旅立ってなお、いけにえの魂は名残雪のように世界を優しく包んでいるという想いをこめて建てられた。 村人たちにとっては聖域とも言える場所である。 いけにえに選ばれた女性は一度はこの石碑に祈りを捧げることが古くからの習わしとなっている。
A19: 519.001_
A20: 519.002_
A21: 519.003_
A22: 520_ | B22: An inlet beach on the coast of the Floneian Territories. Although it is not immediately apparent, the tide here is fierce, and if one is careless, it is easy to be swept out to sea by its current. There were once plans to build a harbor here, but they were abandoned due to the aquatic monsters that frequent the beach's sands. As the years passed, the beach became forgotten, and its shore lies empty, save for the rocks. | C22: Một bờ vịnh trên lãnh thổ Floneian. Mặc dù không rõ ràng nhưng thủy triều nơi này rất mạnh, dòng biển có thể cuốn trôi người ta ra biển nếu bất cẩn. Đã từng có kế hoạch cho xây dựng cảng biển ở nơi này nhưng đã bị dừng lại bởi lũ quái vật thường xuyên hoạt động quanh đây. Rất nhiều năm trôi qua, vùng vịnh đã bị quên lãng. Chẳng còn gì ở đây ngoài cát, gió, biển, sỏi đá và quái vật. | D22: 湾状になっている浜辺。 海面からはわからないが複雑な潮の流れになっており、ヘタに海流に飲みこまれるとそのまま、外洋へと流されてしまう。 かつてはここに港を作る計画もあったが、頻繁に水棲の魔物が出没するため断念。時代とともに忘れ去られてしまった。 今はただ岩礁のみが残っている。
A23: 520.001_
A24: 520.002_
A25: 520.003_
A26: 521_ | B26: A town situated to the north of the Forgotten Shore. The view of the rising sun to be found here is the most unbroken of any on the mainland. It once thrived as a port town, but one year, when the sacrificial pilgrimage ended in failure, it was ravaged by monsters and left in ruins. It is said that figures can sometimes be seen wandering through the town, and it is possible that these are the lingering souls of its former inhabitants who refuse to leave. | C26: Một thị trấn nằm phía Bắc của Bờ Biển Bị Lãng Quên. Bình minh ở nơi này đẹp và trọn vẹn hơn so với bất cứ đâu trên Lục địa. Đã từng là một thị trấn cảng tấp nập, vì một lần lễ hiến tế thất bại, thị trấn đã bị tàn phá bởi quái vật và cuối cùng bị bỏ hoang. Vẫn có người nhìn thấy vài bóng hình đi quanh quẩn trong thị trấn. Có lẽ đó là linh hồn của những người gắn bó với thị trấn, quyến luyến không rời. | D26: 忘れられた浜辺の北に位置する村。 ゴザとは古代語で「朝日」という意味であり、本島で最も早く夜明けが見えるところからその名がついた。 かつては港町として繁栄したが、その年のいけにえの旅が失敗に終わり、増殖した魔物たちに滅ぼされ、廃墟となってしまった。 時折、うろついている人影を見かけるという。 いまだ死を受け入れられぬ村人たちが、魂となってさまよっているのかもしれない。
A27: 521.001_
A28: 521.002_
A29: 521.003_
A30: 522_ | B30: A small village situated near the mountains. Due to its mild climate, its soils provide relatively plentiful harvests. Because of its ample crops, it once served as a garrison for the knights of the ancient kingdom. The stalwart gates erected at that time can still be seen today, and a watchtower also remains in the center of the village. The village has no official leader, but <NAME=NPC_10050>, the captain of the local resistance, essentially fulfills this role. | C30: Một ngôi làng nhỏ nằm gần núi. Bởi vì khí hậu ôn hòa nên nơi đây trồng trọt rất khá. Bởi vì mùa màng bội thu, nơi đây từng là nơi đóng quân của đội kị sĩ vương quốc cổ đại. Đến bây giờ vẫn còn dấu tích của cổng doanh trại khi ấy, và một tháp canh gác ở trung tâm làng. Ở đây không có trưởng làng nhưng <NAME=NPC_10050>, thủ lĩnh dân làng, đang tạm thời đảm nhiệm chức vụ này. | D30: 山間に位置している小さな村。 気候が穏やかで比較的農作物が収穫しやすいため、古代語で「恵み」という意味をもつ、ユラルという名をつけられた。 その豊富な作物を理由に、いにしえの王国の騎士団が駐留するため駐屯地としての役割も持っていた。 そのため、今でも門の造りは頑丈で、村の中央には物見台が設置されている。村長という役職は置かれず、自警団の団長<NAME=NPC_10050>が実質、まとめ役である。
A31: 522.001_
A32: 522.002_
A33: 522.003_
A34: 523_ | B34: Settlements were once dotted around these plains, but no trace of them remains today. There are no landmarks to speak of, and when strong winds cause the snow to blow up into the air in thick clouds, it is easy to become stranded. | C34: Dân du mục thường sinh sống quanh những vùng đồng bằng này, nhưng đã không còn vết tích con người sinh sống ở đây ngày nay. Không có địa điểm nào nổi bật, và khi gió mạnh, tuyết rơi nhiều, khu vực này có nguy cơ bị cô lập. | D34: かつては複数の集落が点在していた場所だが、今は見る影もない。 目印もなく、ひとたび地吹雪が起こると、遭難の危険性がある。
A35: 523.001_
A36: 523.002_
A37: 523.003_
A38: 524_ | B38: A series of caves leading between <NAME=MA_0010_01> and <NAME=MA_0014_01>. The pillars of ice found in its caverns give off a luminous blue hue. Although perilous, these caves serve as the only route between Purikka and Floneia, and it is said that many travelers have lost their lives to the monsters that dwell within them. | C38: Một hệ thống hang động nằm giữa <NAME=MA_0010_01> và <NAME=MA_0014_01> Những tảng băng tìm thấy trong hang động mang sắc xanh rực rỡ. Mặc dù nguy hiểm, những cái hang này là con đường duy nhất đi từ Purikka đến Floneia, đã có rất nhiều khách lữ hành mất mạng vì những con quái vật sống trong này. | D38: <NAME=MA_0010_01>と、<NAME=MA_0014_01>の間にある洞窟。 カッチは古代語で「青」という意味があり、洞窟内部に点在する氷柱などが青白く光って見えることからこの名がついた。 ユラルとウカテイナを行き来するためには必ず通らなければならない難所で、ここに生息している魔物に襲われて命を落とす者も少なくないという。
A39: 524.001_
A40: 524.002_
A41: 524.003_
A42: 525_ | B42: When the ancient kingdom still reigned, the town was turned into a citadel as part of plans to strengthen the kingdom's defenses. It is extremely secure, and invasion is difficult, even for monsters. | C42: Vào thời kì Vương quốc cổ đại, thị trấn này đã được biến thành một pháo đài để tăng khả năng bảo vệ vương quốc. Rất khó để xâm nhập, ngay cả quái vật còn phải chật vật. | D42: ウカテイナという名称は、古代語で「大勢の人」を意味するウカと、「水辺」を意味するテイナが語源となっている。 いにしえの王国が健在だったころ、防衛力強化政策のひとつとして城塞化が進められた。 全体的に堅固な造りで、魔物ですら侵入は困難である。
A43: 525.001_
A44: 525.002_
A45: 525.003_
A46: 526_ | B46: The snowfall in this area is extremely heavy, and its former inhabitants would generally stay inside. Steam baths were also once very popular in this area. | C46: Tuyết rơi rất nhiều ở khu vực này, và những người dân cũ nơi đây thường xuyên phải ở trong nhà. Dịch vụ tắm hơi đã từng rất nổi tiếng ở đây. | D46: 積雪量が非常に多い土地で、かつての住人たちも家にこもることが多かった。 またこの地では蒸し風呂が盛んだった。
A47: 526.001_
A48: 526.002_
A49: 526.003_
A50: 527_ | B50: A lonely forest with a river running through it leading to a lake. No one knows the reason behind the name "Mysleigh," but the woods are said to hold some sort of secret. Mysteriously, the river that runs through them stays warm all year round, and never freezes over, even in the dead of winter. | C50: Một khu rừng cô đơn với duy nhất 1 con sông chạy qua, chảy vào 1 cái hồ. Không ai biết ý nghĩa cái tên của nó, "Mysleigh", nhưng có vẻ cánh rừng này sở hữu một bí mật. Kì quái thay, nước của con sông duy nhất nơi đây luôn luôn ấm, ngay cả giữa mùa đông lạnh giá. | D50: 悄然とした森で、湖とは川でつながっている。 ニレイとは古代語で「未知の存在」という意味を指すが なぜそう名づけられたのかは誰も知らない。 この森を流れている川は不思議と真冬でも温かく、とうとうと流れている。
A51: 527.001_
A52: 527.002_
A53: 527.003_
A54: 528_ | B54: A small settlement built near the northeastern coast of the mainland. It was originally constructed by <NAME=NPC_10060>, the lord of Floneia, as a safe haven for those whose homes were destroyed by monsters, or for whatever other reason had no place left to go. Its gates are always open, and anyone is free to come and go at any time. Its buildings are modest and uniform, but for a temporary shelter it offers ample accommodation, and it is very popular with residents. | C54: Khu tái định cư xây dựng ở bờ biển phía Đông Bắc Lục địa. Khu này được xay dưng bởi lãnh chúa Floneia, <NAME=NPC_10060>, dành cho những người vì lũ quái vật mà mất nhà, hoặc chỉ đơn giản họ không có nơi để trở về. Cánh cổng nơi này luôn rộng mở, chào đón những ai ghé thăm và tạm biệt những người rời đi. Mặc dù những tòa nhà còn có phần đơn sơ, so với một khu tái định cư, nơi này rất tuyệt vời. | D54: 本島の北東の端にある小さな集落。 もともとはウカテイナの城主・<NAME=NPC_10060>が作ったもので 魔物に住んでいる所を奪われた者や、何らかの事情で行き場を失った者たちを保護するための施設である。 入所も出所も自由で、いつでも門戸が開かれている。 建物こそ簡素で画一的だが、一時的な保護施設としては充分な設備であり、入居者からの評判も上々である。
A55: 528.001_
A56: 528.002_
A57: 528.003_
A58: 529_ | B58: One of the remaining ruins of an ancient and highly advanced civilization. "Laniff" is apparently an ancient word meaning "demise." The ruins of Apparth, Moolbeld, and Laniff all have very similar internal structures. As one historian comments: "The similarities between the three ancient ruins is by no means a coincidence, and undoubtedly holds the key to their significance." | C58: Một trong những tàn tích của cộng đồng dân cư cổ đại, người sở hữu kĩ thuật tân tiến. "Laniff" là một từ cổ mang nghĩa "truyền lại". Bên trong tàn tích ở Apparth, Moolbeld và Laniff có những nét kiến trúc tương tự nhau. Một nhà Sử học từng nói rằng: "Nét tương đồng này hoàn toàn không phải là sự trùng hợp, nó, không thể nghi ngờ, là chìa khóa dẫn chúng ta tới nền văn minh cổ đại". | D58: 超古代文明が残したという遺跡のひとつで、ルマとは古代語で「終焉」という意味である。 アピ、ティキナキ、ルマの３つの遺跡はどれも内部構造が似通っているが、それに関してとある歴史学者は「３つの古代遺跡が同じような構造をしているのは決して偶然ではなく、何らかの意味が隠されているのは間違いない」と断言している。
A59: 529.001_
A60: 529.002_
A61: 529.003_
A62: 530_ | B62: A craggy mountain that lies beyond the <NAME=MA_0013_01>. It is said that many would once gather here to worship the sun, due to its beautiful, dreamlike appearance as it rises to the east of the mountain. However, because of the many fierce monsters that now roam its cliffs, very few people ever choose to come here. | C62: Vùng đồi núi nằm trên <NAME=MA_0013_01>.Rất nhiều người sẽ tụ họp lại đây 1 lần trong năm để ca ngợi thần Mặt Trời, bởi lẽ bình minh nơi đây quá đẹp và thơ mộng. Tuy nhiên, bởi vì lũ quái vật dữ tợn mà ngày một ít người đến thăm nơi này. | D62: <NAME=MA_0013_01>を抜けた先にある険しい山。 イパイとは古代語で「太陽」という意味であり、この山の東側から昇る太陽の姿は幻影的なまでに美しく、その太陽を拝むことが一種の信仰として流行した時代もあったらしい。 しかし、現在では魔物に襲われる者が後を絶たないため 好きこのんでこの山に入る者は少ない。
A63: 530.001_
A64: 530.002_
A65: 530.003_
A66: 531_ | B66: A settlement surrounded by a thick forest of giant trees. The only way to get to it is by crossing over rugged mountains, making it an extremely difficult place to reach. Regardless, few even know of its existence; a special race of people live hidden away here, and only a select few humans - members of the Magic Consortium, merchants, and so forth - are permitted entry. The village is unique in that its residents are all young, and there is not a single elderly person to be found. | C66: Khu tái định cư nằm ở giữa một khu rừng nguyên sinh rộng lớn. Cách duy nhất để đến được đây là băng qua những dãy núi hiểm trở, khó khăn. Cũng vì vậy mà rất ít người biết đến nơi này. Có 1 tộc người đặc biệt ẩn cư tại nơi này. Chỉ một số người đặc biệt - thành viên Thương Hội, thương nhân, hoặc tương tự - được phép vào nơi này. Một ngôi làng kì quái khi người trong làng đều là người trẻ tuổi, không có một ai già. | D66: 巨木がつらなる深い森に囲まれた集落。 イルは古代語で「険しい」という意味だが、イルに入るためには、文字通り険しい山々を抜けなければいけないため、訪れることすら容易ではない。 そもそも特別な種族が隠れ住んでいるので、その存在すら知る者は少なく、魔導商会や行商人など、ごくわずかな人間だけが訪問を許可されている。 住人はみな年若く、老人はひとりもいない、変わった村である。
A67: 531.001_
A68: 531.002_
A69: 531.003_
A70: 532_ | B70: A giant chunk of spritnite embedded in a cliff wall behind <NAME=MA_0022_01>. It possesses a mysterious power, and is able to extract and store magical energy from people's bodies. The people of <NAME=CP_0005>'s tribe transfer their magical energy into the pillar, in order to reduce its burden on their bodies and increase their life spans as much as possible. It is uncertain who made it, or when, but as it is able to store such a vast amount of magical energy, some theorize that it was once used as a power source of some kind. | C70: Một cột pháp thạch trên vách núi đằng sau <NAME=MA_0022_01>. Nó có năng lượng bí ẩn, có khả năng hút và dự trữ năng lượng từ cơ thể người. Người dân trong làng truyền pháp lực vào trong cột pháp thạch nhằm giảm áp lực của nó lên cơ thể họ và kéo dài mạng sống. Chảng ai biết cây cột này từ đâu mà ra, nhưng dựa trên lượng năng lượng nó có thể dự trữ, có giả thiết đặt ra rằng nó từng là một nguồn cung cấp năng lượng | D70: <NAME=MA_0022_01>の奥にある巨大な法石。 不思議な力があり、肉体から魔力を分離させ、温存しておくことができるというものである。 イルに住む人々は、この法石柱に魔力を移し替え、少しでも肉体の負担を減らして長生きに努めるのが習わしである。 このような巨大な法石をいつ、誰が作ったかは不明だが 膨大な魔力を蓄積できるところから、かつては何かの動力源に使われたのでは、という説もある。
A71: 532.001_
A72: 532.002_
A73: 532.003_
A74: 533_ | B74: A mountain that lies to the west of <NAME=MA_0022_01>. It is even more precipitous than <NAME=MA_0021_01>, and the monsters that inhabit its peaks are even more ferocious. Therefore only the most seasoned of travelers - or those with the strength to eliminate the monsters - are ever able to cross it. | C74: Một ngọn núi nằm về phía Tây <NAME=MA_0022_01>. Nó thậm chí còn nguy hiểm hơn cả <NAME=MA_0021_01>, và lũ quái vật sống trên đỉnh núi cũng hung ác hơn nhiều. Vì vậy chỉ có những tay leo núi kì cựu nhất, hay những kẻ đủ mạnh để tiêu diệt lũ quái vật, mới dám đi qua đây. | D74: <NAME=MA_0022_01>の西にある山。 古代語でルッツは「落日」を意味するが、その点では東にある<NAME=MA_0021_01>と対を成している。 だが、その険しさは<NAME=MA_0021_01>以上で、棲み着いている魔物たちも凶暴さを増しているため、<NAME=MA_0024_01>を越えるのはよほど旅慣れているか、あるいは実力で魔物を排除できる強者に限られている。
A75: 533.001_
A76: 533.002_
A77: 533.003_
A78: 534_ | B78: One of the remaining ruins of a highly advanced civilization that dates back to before even the ancient kingdom. Its appearance is otherworldly, as if existing in an interval in space-time. It has long been feared by the people, and today none even dare set foot inside. "Apparth" is apparently an ancient word meaning "birth," but no one knows why these ruins were given such a name. Some suggest that the mystery behind this name holds the secret to the ruins themselves. | C78: Một trong những tàn tích của cộng đồng văn minh cổ đại, thời kì thậm chí còn sớm hơn các vương quốc cổ đại. Vẻ ngoài của nó dường như không thuộc về thế giới này, thậm chí có vài phần như tồn tại giữa không - thời gian. Con người vẫn luôn sợ hãi nơi này và ngày nay thậm chí không ai dám đi vào. "Apparth" còn có nghĩa là "sinh thành", nhưng không ai hiểu tại sao tàn tích này lại có tên như vậy. Một số đoán rằng có lẽ bản thân cái tên cũng đang ẩn chứa bí mật nào đó. | D78: いにしえの王国よりさらに遡った超古代文明が残したという遺跡。 まるで時空の狭間に隔絶されたような、異常な光景に人々は恐れをなし、現在では訪れる者すら皆無である。 アピとは古代語で「誕生」の意味だがなぜ、この遺跡にそのような名前がつけられているのかは誰も知らない。 ただ、一説によると「誕生」という言葉に隠された謎が 遺跡のどこかに埋まっているのでは、と言われている。
A79: 534.001_
A80: 534.002_
A81: 534.003_
A82: 535_ | B82: A sea that lies to the northwest of the mainland. Its waters are covered with ice floes, meaning that no ships can sail across. Although the ice is thick, the current beneath it is strong and fast, meaning that if one were to fall into the sea, chances of survival would be extremely slim. Due to its perilousness, local law dictates that all those wishing to cross the <NAME=MA_0025_01> must be accompanied by a guide. | C82: Vùng biển nằm ở phía Tây Bắc Lục địa. Trên mặt biển có rất nhiều những tảng băng trôi, vậy nên tàu biển không thể nào đi qua. Mặc dù lớp băng rất dày, dòng hải lưu bên dưới rất nhanh và mạnh, vậy nên khi một người rơi xuống biển, cơ hội còn sống của họ là rất mong manh. Cũng bởi sự nguy hiểm của nó, những ai muốn băng qua <NAME=MA_0025_01> cần có hướng dẫn viên đi cùng. | D82: 本島の北西にある海。 ロラとは古代語で「流氷」という意味だが、まさしく流氷に覆われた海であり、ここを船で通過することはできない。 流氷は分厚いものの、その下の海流は複雑で流れも速く 万が一、足を踏み外して海に落ちた場合は、死亡する可能性がきわめて高い。 そのため、地元の人に先導してもらうのが<NAME=MA_0025_01>を渡るときの鉄則である。
A83: 535.001_
A84: 535.002_
A85: 535.003_
A86: 536_ | B86: A village that, unusually, faces onto a lake. Although relatively small in scale, it was founded by the descendants of the ancient kingdom. The mighty knighthood, led by <NAME=CP_0006>, are well known in the surrounding area, and the village's residents are a strong-spirited people, all proud of their ties to the ancient kingdom. | C86: Một ngôi làng, kì quái thay, hướng về phía hồ. Mặc dù khá nhỏ nhưng ngôi làng này được thành lập bởi hậu duệ của vương quốc cổ đại. Đội Kị Sĩ hùng mạnh, dẫn đầu bởi <NAME=CP_0006>, rất nổi tiếng ở những vùng lân cận. Người dân trong làng rất mạnh mẽ, tất cả đều tự hào vì họ mang dòng máu của vương quốc cổ đại. | D86: 珍しく湖に面した村で、規模としてはさほど大きくはないものの、いにしえの王国の末裔が築いた村である。 <NAME=CP_0006>を主とした強力な騎士団が周辺地域で名をはせており、住民たちもみな、王国の末裔であるという誇りと気概に満ちている。 ちなみに村の由来となったヤーガは古代語で「正統」という意味である。
A87: 536.001_
A88: 536.002_
A89: 536.003_
A90: 537_ | B90: A series of caves that lie to the east of the village of <NAME=MA_0026_01>. Their name comes from the local legends that say that even if one enters the mazelike caverns with a torch in hand, its flame will soon flicker out, leaving everything enveloped in total darkness. Many fearsome monsters dwell inside, and even the people of Royburg seldom dare to enter. | C90: Một hệ thống hang động nằm về phía Đông làng <NAME=MA_0026_01>. Cái tên đến từ một truyền thuyết địa phương rằng bất kì ai vào trong hệ thống hang động tựa mê cung này với một cây đuốc trên tay, cấy đuốc sẽ chóng tàn, để lại mọi thứ trong bóng đêm thiên trường địa cửu. Rất nhiều quái vật ẩn nấp bên trong, thậm chí đến cả những người của Royburg cũng hiếm khi vào đây. | D90: <NAME=MA_0026_01>の東に位置する洞窟。 ネルは古代語で「暗闇」という意味だが、たとえ松明を持って入っても、複雑な洞窟内をさまよっているうちに火も消え、最後は暗闇に閉ざされるということから名づけられた。 恐ろしい魔物が棲みつくことも多く、ヤーガの人々でさえ、めったに近づくことはない。
A91: 537.001_
A92: 537.002_
A93: 537.003_
A94: 538_ | B94: It is said that a rare tribe of people who spoke a unique language lived here long ago. These people seem to somehow be strongly tied to the <NAME=MA_0028_01>, but the details of this remain shrouded in mystery. | C94: Một tộc người với thứ tiếng kì lạ được cho là đã từng sống ở đây. Họ có vẻ có mối quan hệ mật thiết với <NAME=MA_0028_01>, nhưng những gì còn lại về họ vẫn còn là một ẩn số. | D94: はるか昔、特殊な言語を話す少数民族が住んでいたと伝えられている。 <NAME=MA_0028_01>と関係の深い民族だったようだが真相は謎に包まれたままである。
A95: 538.001_
A96: 538.002_
A97: 538.003_
A98: 539_ | B98: An ancient ruin that lies across the <NAME=MA_0025_01> from Royburg. The layout of the ruins is extremely complex, with an unusual, mazelike structure, and includes devices that allow for instantaneous transportation between one area and another. As a result, this can distort the perception of time and space of those who enter, leaving them wandering inside the ruins forever. Indeed, countless people who have strayed inside the ruins have never been seen again. | C98: Tàn tích cổ đại nằm qua <NAME=MA_0025_01> từ Royburg. Bố cục của tàn tích cực kì phức tạp, cấu trúc giống mê cung kì lạ, với những thiết bị cho phép di chuyển ngay lập tức từ nơi này đếm nơi khác. vì vậy, khái niệm về không - thời gian của những người bước vào nơi này sẽ bị xáo trộn, khiến họ có thể lạc trôi ở nơi này tới vĩnh hằng. Tất nhiên, rất nhiều người bước vào đây đã không thể trở ra được nữa. | D98: <NAME=MA_0025_01>を渡った先にある古代遺跡。 ワッカとは古代語で「時間」という意味だが、それはこの遺跡の独特な構造に関係している。 ワッカの内部構造は複雑で、瞬時にして別の場所に移動させられる仕掛けが施されているため、侵入した者は時間と空間の認識が乱され、永遠にさまよいかねないという恐ろしさを秘めている。 事実、このワッカに入りこみ、そのまま行方不明となった者は数知れない。
A99: 539.001_
A100: 539.002_
...

Sheet BraveStoryMemoMessage
A1: ID | B1: English | C1: Vietnamese | D1: Note
A2: 1134.001_ | B2: 2 | D2: 2
A3: 1135_ | B3: True | D3: True
A4: 1135.001_ | B4: 0 | D4: 0
A5: 1136_ | B5: 36 | D5: 36
A6: 1137_ | B6: The Sacrifice | C6: Vật Hiến Tế | D6: いけにえ
A7: 1138_ | B7: A custom that has been carried out in Nive Village for many years. In order to appease the savage monsters, the chosen sacrifice travels to the Last Lands to perform the sacrificial rites. It is customary for females to be chosen, as they generally possess greater magical energy than males. Up until now these rites have been carried out once every ten years, but because the monsters are now increasing in number more rapidly, the time between pilgrimages has been shortened. | C7: Có 1 phong tục tồn tại ở làng Nive đã rất nhiều năm. Để khiến cho những con quái vật nguôi giận, vật tế được chọn phải đi tới vùng đất Tận Cùng để thực hiện nghi thức hi sinh. Thường thường, người được chọn là nữ giới, bởi họ có năng lượng pháp thuật cao hơn nam. Nghi lễ này diễn ra 10 năm 1 lần, nhưng vì càng ngày quái vật xuất hiện càng nhiều, thời gian giữa 2 lần tế lễ bị rút ngắn lại. | D7: モルの村が長年に渡り行ってきた慣習。 いけにえとなった者は荒ぶる魔物を鎮めるため、最果ての地へと赴きその身を捧げる。いけにえとして選ばれるのは魔力の観点から女性が通例となっている。 これまで十年に一度行われてきた儀式だが、昨今の魔物増加の影響により、その周期は短くなっている。
A8: 1139_ | B8: The Sacrifice's Protection | C8: Sự Bảo Vệ Của Vật Hiến Tế | D8: いけにえの守護
A9: 1140_ | B9: It is said that once the sacrifice fulfills her duty, the threat of the monsters will disappear, bringing peace to the mainland and the surrounding islands. The vast majority of people therefore regard the sacrifices with great esteem, and will do their best to aid them on their journeys. However, few people today know the reason why the sacrificial rites appease the monsters, and as a result, there are also those who doubt the effectiveness of the sacrifices. | C9: Sự hi sinh của 1 vật tế có thể đổi lấy 1 khoảng thời gian yên bình cho Lục địa cũng như các đảo lân cận. Hầu hết mọi người rất tôn sùng vật tế, và làm tất cả những gì để giúp vật tế trên chuyến hành trình của họ. Tuy nhiên, số người biết về nghi lễ này ngày một ít, cũng như tại sao lễ tế có thể làm ổn định lũ quái vật. Vì vậy, có cơ số người nghi ngờ tính hiệu quả của lễ tế này. | D9: いけにえがその役目を果たすことで、魔物の脅威は去り、本島やその周辺の島々の平穏は守られると伝えられている。そのため、ほとんどの人々はいけにえを尊重し、協力してくれる。 だが、なぜいけにえが魔物を鎮めることができるのか、その理由を知る者は今ではほとんどいない。その結果、いけにえの価値を認めない者も中には存在する。
A10: 1141_ | B10: The Pilgrimage's Route | C10: Hành Trình Hành Hương Của Vật Tế | D10: いけにえの旅路
A11: 1142_ | B11: The route and means of transport for the sacrificial pilgrimage is determined based on a variety of factors, such as weather conditions and environmental changes. In most cases, after departing from Nive Village, the sacrifice and her guard will first travel to the town of Floneia to gather information. From there, they will choose how to continue their journey - for example, by land, or by sea. | C11: Lộ trình và phương tiện di chuyển của vật tế trên đường tới Vùng đất Tận Cùng được quyết định dựa trên rất nhiều yếu tố, như là điều kiện thời tiết hay sự thay đổi môi trường. Hầu hết, sau khi khởi hành từ làng Nive, vật tế cùng những người bảo vệ cô sẽ đến Thị trấn Floneia để thu thập thông tin. Từ đó, họ sẽ chọn cách để tiếp tục cuộc hành trình - đi bằng đường biển, đường bộ,... | D11: その時の気象状況や環境変化などさまざまな要素を判断し、いけにえの交通手段や道順が決定されている。 モルの村を出発したいけにえは大抵の場合、本島の情報を得るためウカテイナの町に立ち寄り、進路を決定する。そこで陸路や海路など、その時々の状況に応じていくつかの旅路を選択して進んでいくのが常套手段となっている。
A12: 1143_ | B12: The Sacrifice's Guard | C12: Người Bảo Vệ Của Vật Tế | D12: 護衛隊
A13: 1144_ | B13: A special guard formed in order to see the sacrifice safely to the Last Lands. The guard is absolutely essential to the pilgrimage's success. It is not made up of a set number of people; its number is decided based on the ability of its members. However, the Last Lands are a perilous place, and can only be crossed by those who possess extremely high magical energy. As a result, no sacrifice's guard is ever thought to have reached the pilgrimage's final destination intact. | C13: 1 đội bảo vệ đặc biệt sẽ được cử đi bảo vệ vật tế cho tới khi cô đến Vùng đất Tận Cùng an toàn. Đội bảo vệ đóng vai trò quan trọng trong sự thành công của lễ tế. Đội không xác định số người, số người trong đội dựa trên năng lực của từng cá nhân. Tuy nhiên, Vùng đất Tận Cùng là 1 nơi nguy hiểm, chỉ những người có pháp lực cực cao mới có thể đi vào. Vì vậy, không người bảo vệ nào có thể đi cùng vật tế đến cuối cùng. | D13: いけにえを無事に最果ての地まで送り届けるために編成される特別な集団。 事実上、いけにえの旅を成功させるために欠かせない存在である。個人の能力が判断材料となるため、その人数は一定ではない。 ただ、護衛隊として真の終着点までたどり着けた者は過去に存在しない。これは、最果ての地が、高い魔力を持つ者でないと進むことすら適わない過酷な環境になっているためである。
A14: 1145_ | B14: Monsters | C14: Quái Vật | D14: 魔物
A15: 1146_ | B15: Beasts that feed on magical energy. Many monsters will often attack humans and their settlements, and they are feared and hated across the land. Their numbers and ferocity begin to increase every ten years or so, and if the sacrificial pilgrimage fails, their attacks on towns and villages will grow more intense. When this happens, they will sometimes destroy some villages completely. It is said that long ago monsters did not exist, but the validity of these claims is uncertain. | C15: Quái vật sống nhờ vào năng lượng ma pháp. Rất nhiều quái vật sẽ thường tấn công con người và thành trì của họ, vì vậy mọi người đều sợ và thù ghét quái vật. Số lượng và sự tàn ác của chúng tăng dần đều mỗi 10 năm, và nếu lễ tế thất bại, cuộc tấn công của chúng vào thành trì của con người sẽ càng thêm dữ dội. Khi điều này xảy ra, rất nhiều nơi sẽ bị phá hủy. Nghe nói trước đây, quái vật không hề tồn tại, nhưng chẳng có ai có thể khẳng định tính chính xác của nhận định này. | D15: 魔力を糧として生息している獣。 多くの魔物が人や集落を襲うため、人々からは恐れられ、忌み嫌われる存在である。 十年周期で数の増加や凶暴化が進むため、いけにえの旅が失敗した場合には、多くの町や村が襲われることになり、結果として滅ぼされた村もある。 太古の昔には存在していなかったという言い伝えもあるが、真相はいまだ不明である。
A16: 1147_ | B16: Magical Energy | C16: Năng Lượng Pháp Thuật (Pháp Lực) | D16: 魔力
A17: 1148_ | B17: An inert source of spiritual power that is said to flow within all living things. Magic, or "techs," are performed by releasing focused magical energy from the body. The power and properties of each being's magical energy vary greatly. However, the days when the majority of humans were able to make use of their magical energy have long passed, and today most have lost this ability. As a result, magic users are now extremely rare. | C17: Một lực lượng năng lượng tâm linh chảy trong tất cả vật sống. Pháp thuật, hay chiêu thức, được thực hiện bằng việc giải phóng pháp lực tích tụ trong cơ thể. Lượng pháp lực trong mỗi sinh vật rất khác nhau. Tuy nhiên, con người ngày nay hầu hết đã đánh mất khả năng sử dụng pháp thuật. Vì vậy số pháp sư còn lại là cực kì ít. | D17: 命あるもの全てに備わっているとされる、精神を具現化する根源的な力（具現化されたものが魔法となって体外へ放出される）。 その強さや性質は個体ごとに異なる。ただし、大部分の人間が魔力を持っていた時代は遙か彼方に消え去り、今ではほとんどの人間が魔力を失っている。そのため、現在では魔法を使える者は希少である。
... A77: 1208_ | B77: Monsters that have mutated due to the effects of spritnite. It is unknown exactly why such creatures came to be, but they seem to contradict the laws of nature. All spritnite-eaten monsters possess powerful abilities, and defeating them is said to be a very difficult task. | C77: Quái vật đột biến nhờ năng lực của đá spritnite. Không ai hiểu tại sao lại vậy, nhưng điều này dường như đi trái với quy luật của tự nhiên. Pháp thạch thực quái rất mạnh, rất khó để đánh bại. | D77: 法石の力に影響を受けて、変異してしまった魔物のことである。 どうして、そのような魔物が生まれるのかは謎ではあるが、自然の法則からは外れている存在のようではある。蝕まれた魔物たちは例外なく、際立った能力を持っており、倒すのが困難であると言われている。

Sheet BraveStoryMonsterMessage
A1: ID | B1: English | C1: Vietnamese | D1: Note
A2: 1208.001_ | B2: 2 | D2: 2
A3: 1209_ | B3: True | D3: True
A4: 1209.001_ | B4: 0 | D4: 0
A5: 1210_ | B5: 101 | D5: 101
A6: 1211_ | B6: Pengy | C6: Pengy | D6: ペンギィ
A7: 1212_ | B7: The most well-known of all monsters. It is found across the land, and there is also a high degree of intraspecific variation. Its wings have evolved to make them suited to delivering powerful "Slap" attacks, and in exchange have lost the ability of flight. Its large crest acts like a tail fin, stabilizing acceleration during its "Dive" attack. It can also use "Focus" to increase its own tension, boosting attack power, so be sure to defeat it before it does! Will drop a "Thawdrop" if defeated while afflicted with a status ailment. | C7: Loài quái vật được biết đến nhiều nhất. Chúng được tìm thấy ở khắp nơi và có lượng phân loài cực kì lớn. Cánh của chúng tiến hóa để phù hợp với đòn "Vả" của chúng, bù lại, chúng mất đi khả năng bay lượn. Bộ mào lớn đóng vai trò như một chiếc đuôi, giúp chúng giữ thăng bằng sau khi dùng chiêu "Lượn". Chúng còn có thể sử dụng "Tập Trung" để tăng độ căng thẳng của bản thân, dẫn đến việc tăng sức mạnh tấn công. Hãy tiêu diệt nó trước khi đó nhé! Có thể rớt ra "Tuyết Tan" nếu bị tiêu diệt khi đang bị ảnh hưởng bởi trạng thái tiêu cực. | D7: この世界で最もよく見かける、代表的な魔物。場所を問わず至る所に分布し、また種族内のバリエーションも非常に多い。 羽根は高威力の「ビンタ」に適した骨格に進化したため、その代償に飛行能力は失われた。 大きなトサカは「ダイブ」の加速を安定させるための垂直尾翼の役割を持つ。 自らのストレスを「ためる」ことで攻撃力を上昇するので、その前に倒そう！ 状態異常の最中に倒すと「雪解けドロップ」を落とす。
A8: 1213_ | B8: Hoppy | C8: Hoppy | D8: イワトビィ
A9: 1214_ | B9: A more powerful relative of the Pengy. It is mainly found in rocky areas, and gets its name from the hopping motion it makes when moving. Its crest is even larger than that of the Pengy, and as well as acting as a tail fin, also serves as an antenna for communication with other Hoppies. Hoppies use this ability to perform a synchronized "Rocket Rush" attack in pairs, and caution is thus advised when encountering more than one of the creatures. Will drop a "Round Stone" if defeated with Over Kill. | C9: Họ hàng của Pengy, mà mạnh hơn. Chúng thường được tìm thấy ở những vùng sỏi đá, và cái tên của chúng đến từ việc chúng nhảy để di chuyển. Bộ mào của chúng còn lớn hơn của Pengy, không chỉ là chiếc vây đuôi, chúng còn là chiếc ăng ten để các Hoppy giao tiếp với nhau. Các Hoppy sử dụng khả năng này để thực hiện đòn "Tên Lửa Vụt Bay" theo cặp, vì vậy cần phải cẩn thận khi đối đầu với nhiều Hoppy. Sẽ rớt ra "Đá Tròn" nếu bị tiêu diệt trong trạng thái Bá Đạo | D9: ペンギィの上位種。主に岩場に生息し、ピョンピョン飛び跳ねる動きをすることからこう呼ばれるようになった。 ペンギィよりもさらに大型化したトサカは、垂直尾翼としての機能に加えて、イワトビィ同士で意思疎通を行うためのアンテナとしての機能を併せ持つ。 その能力により、２体のイワトビィでタイミングを合わせて放つ「ロケットラッシュ」にはくれぐれも気をつけよう。 オーバーキルで倒すと「まるい石」を落とす。
A10: 1215_ | B10: Empy | C10: Empy | D10: コウティ
A11: 1216_ | B11: The most powerful member of the Pengy species. Although its genetic makeup differs from that of the Pengy by a mere 0.01%, its appearance is strikingly different. Its crown-like crest has evolved into a more powerful antenna than that of the Hoppy, and it is even able to control other Empies remotely. This ability is used to unleash an extremely powerful "Rocket Rush" attack in which three Empies move in perfect synchronization. Will sometimes drop an "Emperor's Crown Gem." | C11: Phân loài mạnh nhất của Pengy. Mặc dù gen của chúng và Pengy chỉ khác nhau chưa đến 0.01%, ngoại hình của chúng lại khác nhau hoàn toàn. Lông mao hình vương miện tiến hóa trở thành chiếc ăng ten còn mạnh hơn của Hoppy, thậm chí còn có thể điều khiển các Empy từ xa. Khả năng này giúp Empy thực hiện đòn "Tên Lửa Vụt Bay" với 3 Empy cùng sự đồng điệu hoàn hảo. Thỉnh thoảng sẽ rớt ra "Ngọc Thạch Ngai Vàng Của Hoàng Đế". | D11: ペンギィの最上位種。ペンギィとはわずか0.01％しか遺伝子構造に差がないのにも関わらず、その外見はまったくと言って良いほど異なる。 王冠のような形状をしたトサカは、イワトビィのものよりもさらに高精度のアンテナと化しており、他のコウティをリモート操作することさえ可能。 その能力により、コウティ３体の動きを完全にシンクロさせて放つ「ロケットラッシュ」は超強力！ 時々「王冠石」が手に入ることがある。
A12: 1217_ | B12: Scarly | C12: Scarly | D12: ベスィ
A13: 1218_ | B13: This unfortunate Pengy has been afflicted by a disease of unknown cause. Its body fluids have solidified and formed a stone inside its body, causing intense pain and fever. As a result, its eyes are constantly teary from pain, and its skin red from fever. When the creature is defeated, the stone inside it will occasionally remain intact. This stone, which bears a speckled pattern and emits a characteristic glow, is a highly valuable item known as the "Madara Spritnite." | C13: Loài Pengy tội nghiệp này đã bị lây nhiễm một căn bệnh kì quái. Chất lỏng trong cơ thể chúng dần dần đông cứng lại tạo thành đá, gây ra những trận đau và sốt dữ dội. Mắt chúng nhòa lệ vì đau, da chúng đỏ ửng lên vì sốt. Khi chúng bị tiêu diệt, những viên đá thỉnh thoảng sẽ còn ở lại. Những viên đá này, với những vệt lốm đốm và ánh sáng đặc trưng, là một trong những vật phẩm có giá trị cao, Pháp Thạch Madara. | D13: 魔物なのに原因不明の病魔に冒されてしまった可哀そうなペンギィ。体内の分泌物が固まって石を形成し、それにより疼痛・発熱などの症状を伴っている。疼痛のせいで瞳はいつも涙目、また発熱のせいで表皮も赤く染まっている。 倒すと、まれにその石がそのまま残ることがあり、その石は綺麗な斑模様、そして独特の輝きを放つ法石「マダラ法石」として珍重される。
A14: 1219_ | B14: King Pengy | C14: Pengy Vua | D14: スーパーペンギィ
A15: 1220_ | B15: A form of mutated Pengy. Although far larger in stature than a regular Pengy, the creature itself appears to be entirely unaware of this fact. It can be found mingling and living with Pengy colonies, seemingly under the impression that it is no different from the others. In combat it utilizes a diverse range of attacks, using "Royal Bite" with its giant beak, firing "Pengy Missiles" in all directions, and using "Power Dives" to rock the earth with its full body weight. | C15: Một loài Pengy đột biến. Mặc dù kích thước của chúng lớn hơn Pengy thông thường, loài sinh vật này có vẻ như hoàn toàn không biết điều ấy. Chúng thường sống cùng với Pengy thông thường, có lẽ vì trong mắt chúng, chúng không khác gì các Pengy. Chúng sử dụng rất nhiều đòn chiến đấu, sử dụng "Đớp" với cái mỏ của mình, bắn "Đạn Pengy" tứ tung, làm rung chuyển mặt đất với toàn bộ trọng lượng cơ thể mình bằng "Lượn Sức Mạnh". | D15: ペンギィが突然変異した魔物。ペンギィに比べてはるかに大きな体躯を持つものの、自身ではその自覚はまるで無し。自分をごくごく普通のペンギィと信じて疑わず、ペンギィの群れに紛れ込んで生活を共にする。 巨大な口を大きく開き敵を「かじりつくす」、自身のまわりにまんべんなく「ペンギィミサイル」発射、全体重を乗せて大地を揺るがす「パワーダイブ」などの多彩な攻撃を繰り出す。
A16: 1221_ | B16: King Hoppy | C16: Hoppy Vua | D16: スーパーイワトビィ
A17: 1222_ | B17: An unidentified monster that suddenly appeared in a Hoppy colony on the ice floes of the Floeberg Waters. It is an extremely rare monster, and only one specimen has so far been spotted. Although it usually lives peacefully together with the other Hoppies, when it detects the presence of humans it uses "Hoppy Fusion" to intake the other creatures like sacrifices, drastically increasing its own power. As such, it is a fearsome threat to both humans and monsters alike. | C17: Một loài quái vật chưa được nhận dạng, đột ngột xuất hiện lẫn vào các Hoppy trên những tảng băng trôi dạt tại Floeberg Waters. Là loài quái vật cực kì hiếm, chỉ có 1 cá thể duy nhất từng được phát hiện. Mặc dù chung sống hòa bình cùng các Hoppy, khi cảm nhận được sự tồn tại của con người, chúng sẽ ăn thịt đồng loại để gia tăng sức mạnh. Chúng đe dọa tới cả sự tồn tại của quái vật cũng như con người. | D17: イワトビィの群れの中に突如として現れた正体不明の魔物。他のイワトビィと共にロラの海の流氷の上で暮らしており、未だこの一匹以外は発見されていない希少な魔物。 普段は他のイワトビィと仲良く暮らしているものの、人間の気配を察知すると他のイワトビィを「イワトビィ合体」によりいけにえのように取り込んで大幅にパワーアップする。他のイワトビィにとってもある意味で恐ろしい魔物である。
... A207: 1412_ | B207: A Hoot-Hoot that has been eaten away at by spritnite, enhancing its motor nerves and reflexes to their utmost limits. This enables it to fly away at light-speed when spotted by humans, allowing it to disappear from sight each and every time. Will sometimes drop a "Crystallized Teardrop." | C207: A Hoot-Hoot that has been eaten away at by spritnite, enhancing its motor nerves and reflexes to their utmost limits. This enables it to fly away at light-speed when spotted by humans, allowing it to disappear from sight each and every time. Will sometimes drop a "Crystallized Teardrop." | D207: 法石に蝕まれたことで、運動神経・反射神経が極限まで研ぎ澄まされたハクホウ。 その異常なまでの運動神経・反射神経により、人間に気付くと超光速で飛び去り、確実に人間の前から姿を消す能力を獲得した。 時々「結晶化した涙」を落とすことがある。

Sheet BraveStoryNoteMessage
A1: ID | B1: English | C1: Vietnamese | D1: Note
A2: 1412.001_ | B2: 2 | D2: 2
A3: 1413_ | B3: True | D3: True
A4: 1413.001_ | B4: 0 | D4: 0
A5: 1414_ | B5: 14 | D5: 14
A6: 1415_ | B6: The Masked Mercenaries | C6: Lính Đánh Thuê Và Mặt Nạ | D6: 異端の傭兵たち
A7: 1416_ | B7: <NAME=CP_0001> receives a mission to rescue a girl who has been kidnapped by monsters. He joins up with fellow mercenary <NAME=NPC_10020> in order to carry out this mission. <NAME=CP_0001> and <NAME=NPC_10020> successfully defeat the monsters and rescue the girl. After <NAME=NPC_10020> leaves to take the girl back to her parents, a mysterious man appears before <NAME=CP_0001> with a new mission for him: the assassination of a young girl. | C7: <NAME=CP_0001> | D7: 魔物にさらわれた少女の救出。 という依頼を受けた<NAME=CP_0001>は、 傭兵の<NAME=NPC_10020>と合流し、任務を遂行する。 首尾よく魔物たちを倒し、 少女を解放する<NAME=CP_0001>と<NAME=NPC_10020>。 少女を親元に帰すために<NAME=NPC_10020>が 去っていったあと、謎の人物が<NAME=CP_0001>の前に現れ、 新たな依頼を提示する。 それはとある小さな村にいるひとりの少女を、 暗殺してほしいという依頼だった。
A8: 1416.001_
A9: 1416.002_
A10: 1416.003_
A11: 1417_ | B11: The Journey Begins | C11: Hành Trình Bắt Đầu | D11: はじまりの旅路
A12: 1418_ | B12: Arriving in <NAME=MA_0003_01>, <NAME=CP_0001> finds his target, <NAME=CP_0002>, who turns out to be the latest girl to be chosen as sacrifice. However, her guard, <NAME=CP_0003>, appears, and <NAME=CP_0001> is captured. Even though he tried to take her life, <NAME=CP_0002> sticks up for <NAME=CP_0001>. He is intrigued by her, and abandoning his mission for the moment, he agrees to join her guard. The party set sail on a ferry to the mainland, but the ferry is attacked by a giant monster, and sinks. | C12: Đến <NAME=MA_0003_01>, <NAME=CP_0001> tìm thấy mục tiêu của mình, <NAME=CP_0002>, người vừa được chọn làm vật hiến tế tiếp theo. Tuy nhiên, cận vệ của cô, <NAME=CP_0003>, xuất hiện và <NAME=CP_0001> bị bắt giữ. Dù anh từng có ý định lấy mạng cô, <NAME=CP_0002> vẫn đứng ra bảo vệ <NAME=CP_0001>. Cảm kích trước tấm lòng của cô, anh tạm gác nhiệm vụ và đồng ý gia nhập đội cận vệ. Cả nhóm lên tàu sang lục địa, nhưng con tàu bị quái vật khổng lồ tấn công và chìm xuống biển. | D12: <NAME=MA_0003_01>にやってきた<NAME=CP_0001>は、 標的である少女<NAME=CP_0002>と出会う。 彼女こそは今年のいけにえだった。 だが、そこに駆けつけた護衛隊の<NAME=CP_0003>らによって <NAME=CP_0001>は取り押さえられる。 命を狙われながらも<NAME=CP_0001>をかばう<NAME=CP_0002>。 彼女に興味を持った<NAME=CP_0001>は、 暗殺をいったん思いとどまり、護衛隊に参加する。 しかし、一行を乗せた船は巨大な魔物の襲撃を受けて、 沈められてしまう。
A13: 1418.001_
A14: 1418.002_
A15: 1418.003_
A16: 1419_ | B16: The Lone Swordsman | C16: Kiếm Sĩ Đơn Độc | D16: 許されざる孤剣
A17: 1420_ | B17: After being washed ashore to the mainland, the party meet <NAME=CP_0004>, a man who lives in <NAME=MA_0010_01>. He turns out to be a hero who served on the guard of a previous pilgrimage. The party ask <NAME=CP_0004> to join them, but he refuses. Shortly afterwards, the village is attacked by a mysterious man wielding a scythe. With <NAME=CP_0004>'s help, the party manage to drive the man away. <NAME=CP_0004> is able to overcome his past, and joins the party. Together, they head for <NAME=MA_0014_01>. | C17: Sau khi dạt vào bờ lục địa, nhóm gặp <NAME=CP_0004>, người đàn ông sống tại <NAME=MA_0010_01>. Ông là một người hùng từng tham gia đội cận vệ trong chuyến hành hương trước đây. Nhóm ngỏ lời mời <NAME=CP_0004> tham gia nhưng ông từ chối. Ngay sau đó, ngôi làng bị tấn công bởi một người đàn ông bí ẩn cầm lưỡi hái. Nhờ sự trợ giúp của <NAME=CP_0004>, nhóm đẩy lùi được kẻ địch. Vượt qua được quá khứ u tối, <NAME=CP_0004> quyết định gia nhập đội ngũ. Cùng nhau, họ tiến về <NAME=MA_0014_01>. | D17: 本島に漂着した一行は道中、<NAME=MA_0010_01>に住む、 <NAME=CP_0004>という男と出会う。 彼こそは過去にいけにえの旅を成功させた英雄であった。 一行は<NAME=CP_0004>の協力を仰ごうとするが、 <NAME=CP_0004>はこれを拒絶する。 そんななか、大鎌を持った謎の男の襲撃で村は揺れる。 いけにえの護衛隊を狙う大鎌の男に対し、 <NAME=CP_0004>の協力で、一行はどうにか撃退に成功する。 過去のわだかまりを払拭した<NAME=CP_0004>が新たに加わり、 いけにえの護衛隊は<NAME=MA_0014_01>を めざすのだった。
A18: 1420.001_
A19: 1420.002_
A20: 1420.003_
A21: 1421_ | B21: Good and Evil | C21: Thiện Và Ác | D21: 善悪の境界線
A22: 1422_ | B22: <NAME=CP_0001> and the others are granted an audience with the lord of Floneia, who agrees to ready an airship for them. They then set about looking for the missing shipwright, <NAME=NPC_10080>, in order to do so. On the way, they happen across a young boy named <NAME=CP_0005>, and together with him they find <NAME=NPC_10080>. The lord of the citadel's sinister plan is revealed, and he kidnaps <NAME=CP_0002> and <NAME=CP_0005>. As the party face off against the lord of the citadel, they are attacked once more by the scythe-wielding man. They manage to defeat him, but the airship explodes, and <NAME=CP_0002> is seriously injured. | C22: <NAME=CP_0001> và mọi người diện kiến Lãnh chúa Floneia, người đồng ý chuẩn bị phi thuyền cho họ. Họ lên đường tìm kiếm thợ đóng tàu mất tích, <NAME=NPC_10080>, để sửa chữa phi thuyền. Trên đường đi, họ gặp cậu bé <NAME=CP_0005>, và cùng cậu tìm ra <NAME=NPC_10080>. Âm mưu tà ác của Lãnh chúa bị vạch trần, hắn bắt cóc <NAME=CP_0002> và <NAME=CP_0005>. Khi đối đầu với Lãnh chúa, nhóm lại bị kẻ cầm lưỡi hái tấn công lần nữa. Họ đánh bại hắn nhưng phi thuyền phát nổ, và <NAME=CP_0002> bị thương nặng. | D22: ウカテイナの城主に謁見した<NAME=CP_0001>たちは、 飛空艇を動かすため、消息不明の操船技師<NAME=NPC_10080>の 捜索に乗りだす。 その途中、偶然知り合った少年<NAME=CP_0005>とともに、 <NAME=NPC_10080>を見つけた一行は城主の陰謀を知る。 <NAME=CP_0002>と<NAME=CP_0005>をさらった 城主との戦いのさなか、 大鎌を持った謎の男の襲撃を受け、一行は窮地に……。 何とか勝利したもの、飛空艇は大破し、 <NAME=CP_0002>が重傷を負ってしまうのだった。
A23: 1422.001_
A24: 1422.002_
A25: 1422.003_
A26: 1423_ | B26: A Full Life | C26: Sức Mạnh Cổ Xưa | D26: 輝ける命のために！
A27: 1424_ | B27: In order to save <NAME=CP_0002>, the party head to <NAME=MA_0022_01>, where they learn the secret of <NAME=CP_0005>'s people. They are rare-bloods - a tribe of people whose blood is said to be closer to that of monsters than of humans, and in exchange for great magical energy, have very short life spans. Thanks to <NAME=CP_0005>'s efforts, <NAME=CP_0002> recovers, but just at that moment, the village is invaded by monsters. In order to defeat them, <NAME=CP_0005> unlocks his true magical energy. Wanting to live his life with no regrets, no matter how short it may be, <NAME=CP_0005> joins the sacrifice's guard. Together, they set off towards the <NAME=MA_0041_01> once more. | C27: Để chữa trị cho <NAME=CP_0002>, nhóm tìm đến bộ tộc ma pháp sư cổ đại, nơi <NAME=CP_0005> sinh sống. Tại đây, họ biết được thân phận thực sự của <NAME=CP_0005> và nguồn gốc của ma thuật cổ đại. Sau khi <NAME=CP_0002> bình phục nhờ cỏ thần, cả nhóm tiếp tục hành trình vượt qua dải núi tuyết lạnh giá để đến thủ phủ của vương quốc cổ xưa. | D27: <NAME=CP_0002>を救うため、<NAME=MA_0022_01>を訪れた一行は そこで<NAME=CP_0005>たち種族の秘密を知る。 彼らは魔物と人間の混血種で、高い魔力と引き替えに、 寿命が極端に短かかった。 <NAME=CP_0005>の働きで<NAME=CP_0002>は回復するが、 そのころ里へ魔物が侵入してくる。 里を守るため魔力を解放した<NAME=CP_0005>は魔物を撃退。 限りある命を精一杯生きるため護衛隊に参加した <NAME=CP_0005>は<NAME=MA_0041_01>をめざして旅立つのだった。
A28: 1424.001_
A29: 1424.002_
A30: 1424.003_
A31: 1425_ | B31: The Village of Knights | C31: Vương Quốc Tuyết Phủ | D31: 騎士の村の悪夢
A32: 1426_ | B32: In search of a guide to help them cross the ice floes that cover the <NAME=MA_0025_01>, the party arrive in <NAME=MA_0026_01>. However, the village is deserted, save for one young boy, who tells them that the villagers have been kidnapped and are in the <NAME=MA_0027_01>. The party head there, but discover that the boy is in fact a monster. However, sensing that he bears them no ill will, <NAME=CP_0002> persuades him to escape. Just then, though, the female knight <NAME=CP_0006> arrives and blocks his path. | C32: Nhóm đặt chân đến vương quốc tuyết phủ <NAME=MA_0020_01>, nơi từng là trung tâm thịnh vượng của lục địa. Họ gặp <NAME=CP_0006>, nữ kỵ sĩ hoàng gia kiên cường đang bảo vệ những gì còn sót lại của vương triều. Cùng với <NAME=CP_0006>, nhóm khám phá ra bí mật về các di tích Spritnite cổ đại và mối liên kết giữa ma lực với sự biến đổi của quái vật. | D32: 道中、<NAME=MA_0025_01>で流氷を渡るため、案内人を探す。 一行は近くにある<NAME=MA_0026_01>を訪れる。 だが村は無人となっていた。 そこにひとり残っていた少年の案内で、 村人たちが囚われている<NAME=MA_0027_01>に向かう <NAME=CP_0001>たち。 だが、案内した少年こそが魔物であると発覚。 少年に悪意のないことを感じた<NAME=CP_0002>は少年を説得。 逃がそうとする。 だが、そこに女性騎士<NAME=CP_0006>が 立ちはだかるのだった。
A33: 1426.001_
A34: 1426.002_
A35: 1426.003_
A36: 1427_ | B36: United by Fate | C36: Sự Thật Về Lễ Hiến Tế | D36: 集いし宿命の仲間
A37: 1428_ | B37: Having rescued the villagers, <NAME=CP_0001> and the others receive a hero's welcome in Royburg. There, they learn that <NAME=CP_0006> is a descendant of an ancient royal family. As the party argue with <NAME=CP_0006> over the matter of the monster boy, she suddenly seems to change, and then loses consciousness. In order to cure <NAME=CP_0006>, <NAME=CP_0001> and the others defeat a monster that inhabits the <NAME=MA_0025_01> and obtain a <NAME=ITEM_MTR_171>. <NAME=CP_0006>'s life is saved, and she joins the guard. | C37: Tại đền thờ cổ xưa, nguồn gốc thực sự của Lễ Hiến Tế được hé lộ. Nghi lễ hiến tế không phải là giải pháp vĩnh viễn, mà chỉ là cách tạm thời kìm hãm sự trỗi dậy của Chúa Tể Thời Gian. <NAME=CP_0002> đứng trước lựa chọn hy sinh bản thân vì nhân loại hay tìm một con đường mới để chấm dứt vòng luân hồi bi kịch. | D37: 村人たちを救出したヤーガで歓待を受ける <NAME=CP_0001>たち。 そこで一行は<NAME=CP_0006>がいにしえの王国の 末裔であることを知る。 魔物の少年や騎士団の掟をめぐって軋轢がじるなか、 <NAME=CP_0006>の様子が急変、倒れてしまう。 <NAME=CP_0006>を治すため<NAME=CP_0001>たちは <NAME=MA_0025_01>にいる魔物を倒し、貴重な<NAME=ITEM_MTR_171>を 手に入れる。 思いがけず命を救われた<NAME=CP_0006>は、 護衛隊に加わるのだった。
A38: 1428.001_
A39: 1428.002_
A40: 1428.003_
A41: 1429_ | B41: Past Secrets | C41: Đối Đầu Định Mệnh | D41: 暴かれし過去と秘密
A42: 1430_ | B42: Inside the <NAME=MA_0028_01>, <NAME=CP_0001> and <NAME=CP_0004> are transported to another dimension - a metaphysical realm that replicates <NAME=CP_0004>'s past. <NAME=CP_0004>'s feelings of guilt surrounding the failed pilgrimage create phantom visions that torment him. With <NAME=CP_0001>'s help, he defeats the demons of his past, and it becomes clear that <NAME=CP_0002> is in fact his daughter. The two are returned to the real world, and continue on their journey, keeping this secret between the two of them. | C42: Kẻ cầm lưỡi hái, <NAME=CP_0007>, lộ diện chân tướng và mục đích thực sự của mình. Sau trận quyết chiến nảy lửa, nhận ra ý chí bất khuất của nhóm, <NAME=CP_0007> quyết định đồng hành cùng họ để đối mặt với nguồn cơn thực sự của bóng tối. | D42: 旅の途中、<NAME=MA_0028_01>にさしかかった <NAME=CP_0001>と<NAME=CP_0004>は異空間に巻きこまれる。 そこは<NAME=CP_0004>の過去を再現した精神世界だった。 かつて、いけにえの旅を失敗させた<NAME=CP_0004>は 自責の念が生みだした幻影に苦しめられる。 <NAME=CP_0001>の助けで過去の幻影に打ち勝つ <NAME=CP_0004>だったが、そのとき<NAME=CP_0002>が <NAME=CP_0004>の娘であることがわかる。 ふたりは元の世界に戻り、秘密を胸に 旅を続けるのだった。
A43: 1430.001_
A44: 1430.002_
A45: 1430.003_
A46: 1431_ | B46: Shattered Hope | C46: Vùng Đất Tận Cùng | D46: 砕かれた希望
A47: 1432_ | B47: <NAME=CP_0001> and the others arrive at <NAME=MA_0033_01>, the final obstacle between them and the <NAME=MA_0041_01>. However, there are no caves that lead through the mountain to be found. In <NAME=MA_0031_01>, the party learn how to cross the mountain from an old woman called <NAME=NPC_10170>. They defeat the monster that dwells in the mountain, and the <NAME=MA_0041_01> are right before them. However, they are now inaccessible, due to the uncrossable ravine of darkness that surrounds them. Then, to the party's shock, both <NAME=CP_0003> and <NAME=CP_0006> disappear. | C47: Nhóm vượt qua muôn vàn thử thách hiểm nguy và đặt chân đến Vùng Đất Tận Cùng, nơi ranh giới giữa không gian và thời gian bị bóp méo. Họ bước vào trận chiến cuối cùng để giải cứu tương lai của thế giới khỏi vòng luân hồi bi thương vĩnh cửu. | D47: <NAME=MA_0041_01>に向かう最後の難所 <NAME=MA_0033_01>に挑む<NAME=CP_0001>たち。 だが、山に続く洞窟が見当たらない。 訪れた<NAME=MA_0031_01>で<NAME=NPC_10170>という老婆から 山に入る方法を聞き出した一行は、山に住む魔物を倒し、 ついに<NAME=MA_0041_01>を目の当たりにする。 だが<NAME=MA_0041_01>の周囲は絶望的な深淵によって 隔絶していた。 そして愕然とする一行の前で<NAME=CP_0003>と<NAME=CP_0006>が 姿を消すのだった。
A48: 1432.001_
A49: 1432.002_
A50: 1432.003_
A51: 1433_ | B51: Lost Comrades | C51: Bình Minh Mới | D51: 甦れ！ 失われた絆
A52: 1434_ | B52: <NAME=CP_0001> and the others comfort <NAME=CP_0002> as she despairs over her lost comrades. <NAME=CP_0003> soon rejoins the party, and with the help of her and <NAME=NPC_10080> the shipwright, they begin searching for the royal airship. However, in order to enter the <NAME=MA_0035_01>, <NAME=CP_0006> must be with them. <NAME=CP_0002> learns a secret spell from <NAME=NPC_10170> in order to free <NAME=CP_0006> from the effects of the monster blood inside her. Having successfully saved <NAME=CP_0006>, the party head inside the royal ruins... | C52: Sau khi đánh bại hiện thân bóng tối và giải thoát cho linh hồn của Chúa Tể Thời Gian, vòng luân hồi hiến tế ngàn năm chính thức chấm dứt. Tuyết tan trên khắp đại lục, và một kỷ nguyên hòa bình rạng rỡ bắt đầu mở ra cho toàn nhân loại. | D52: 仲間を失い、絶望する<NAME=CP_0002>を励ます <NAME=CP_0001>たち。 一行は操船技師の<NAME=NPC_10080>や帰還した<NAME=CP_0003>の 助けを借り、旧王家の飛空艇を探しはじめる。 しかし<NAME=MA_0035_01>に入るには、 <NAME=CP_0006>の力が必要だった。 魔物の血の影響を受けた<NAME=CP_0006>を助けるため、 <NAME=CP_0002>は<NAME=NPC_10170>からある秘技を伝授される。 無事、<NAME=CP_0006>を救出した一行は ナニハナに向かうのだった。
A53: 1434.001_
A54: 1434.002_
A55: 1434.003_
A56: 1435_ | B56: Heir to the Throne | C56: Ghi Chép Lữ Hành | D56: 玉座を継ぐ者
A57: 1436_ | B57: <NAME=CP_0001> and the others enter the <NAME=MA_0035_01> in search of the royal airship. However, many trials await them inside the ancient ruins. The party head further inside, answering various riddles as they go. Then, in the deepest depths of the ruins, they meet <NAME=NPC_10180>, the spirit guardian of the ruins. As their final trial, the party do battle with <NAME=NPC_10180>, and once they defeat him, are deemed worthy to receive the royal airship. | C57: Nhật ký hành trình ghi lại chi tiết các sự kiện, nhân vật và vùng đất mà đoàn hành hương đã đi qua trên suốt chặng đường từ Đảo Nive đến Vùng Đất Tận Cùng. | D57: 王家の飛空艇を求めて、<NAME=MA_0035_01>に入る <NAME=CP_0001>たち。 だが、そこには幾多の試練が待ち構えていた。 数々の問答に答え、遺跡の奥へと進んでいく一行。 そして、ナニハナの最深部で一行は遺跡の守護者である <NAME=NPC_10180>と遭遇する。 最後の試練として<NAME=NPC_10180>との戦いがはじまる。 <NAME=NPC_10180>に勝利した<NAME=CP_0001>たちは、 資格ありと認められ、旧王家の飛空艇を 授けられるのだった。
A58: 1436.001_
A59: 1436.002_
A60: 1436.003_
A61: 1437_ | B61: Between Dreams and Eternity | C61: Ký Ức Cổ Xưa | D61: 夢幻と永遠の狭間で
A62: 1438_ | B62: Flying on the royal airship, <NAME=CP_0001> and the others arrive in the <NAME=MA_0041_01>. The party advance further inside what was once the capital of the old kingdom. Inside the castle, their way is blocked by the mysterious scythe-wielding man. The party defeat him, and continue on. They then meet a woman who looks identical to <NAME=CP_0003> and calls herself "the Time Judge." From her, <NAME=CP_0001> and the others learn the truth behind the sacrificial rites, and of an almighty foe who is the reason for them. | C62: Những mảnh ký ức còn lưu lại trong các phiến đá Spritnite cổ, kể về thời kỳ hoàng kim của ma thuật và cội nguồn của thảm họa quái vật. | D62: 旧王家の飛空艇で、ついに<NAME=MA_0041_01>へと 乗りこむ<NAME=CP_0001>たち。 そこはいにしえの王国の王都が残されていた。 奥へと進んでいく一行の前に、 大鎌を持った謎の男が立ちはだかる。 男を倒し、奥へと進んだ一行は、 <NAME=CP_0003>にそっくりな姿をした、 時の審判者と名乗る女性と遭遇する。 そこで<NAME=CP_0001>たちはいけにえの真実と、 いけにえが必要とされる元凶となった 巨大な敵の存在を明かされるのだった。
A63: 1438.001_
A64: 1438.002_
A65: 1438.003_
A66: 1439_ | B66: The Dark Samsara | C66: Lời Nguyện Cầu Của Vật Tế | D66: 輪廻の闇
A67: 1440_ | B67: <NAME=CP_0001> and the others learn that time has been wound back again and again, and that the world is at a standstill, unable to advance into the future. They choose to do battle with their final foe, the <NAME=EB_END1_01>. <NAME=CP_0007> is revived using the Time Judge's power, and joins the party. They then begin their battle with the <NAME=EB_END1_01> and the four lesser monsters surrounding it. After a grueling battle, the party defeat the <NAME=EB_END1_01>, but it uses the last of its energy to escape into the past. | C67: Tâm nguyện sâu kín của những thiếu nữ từng gánh vác sứ mệnh hiến tế qua các thời kỳ, gửi gắm niềm tin vào một tương lai không còn chia ly và mất mát. | D67: 何度も時が巻き戻され、世界は停滞したまま、 未来に進んでいないということを知った <NAME=CP_0001>たちは、最後の敵である<NAME=EB_END1_01>と 戦うことを選ぶ。 時の審判者の力で甦った大鎌の男<NAME=CP_0007>を 戦力に加え、<NAME=CP_0001>たちは<NAME=EB_END1_01>と それを取り巻く眷属の魔物たちと総力戦を繰り広げる。 死闘の末、一行は敵を倒すが、<NAME=EB_END1_01>は 最後の力を使って過去へと逃亡してしまう。
A68: 1440.001_
A69: 1440.002_
A70: 1440.003_
A71: 1441_ | B71: Towards the Future | C71: Hướng Tới Tương Lai | D71: 旅の終わり、まだ見ぬ未来へ
A72: 1442_ | B72: Following the <NAME=EB_END1_01> back in time, <NAME=CP_0001> and <NAME=CP_0002> find themselves in <NAME=MA_0003_01>'s past. The final battle then begins, in front of the <NAME=MA_0006_01>. However, having learned of their enemy's pain, <NAME=CP_0002> makes up her mind to die together with the <NAME=EB_END1_01>, and asks <NAME=CP_0001> to deliver the finishing blow. After some agonizing, <NAME=CP_0001> makes his final decision. Everything is over. The world moves towards the future, and the surviving members of the party begin their own journeys... | C72: Theo chân <NAME=EB_END1_01> quay ngược thời gian, <NAME=CP_0001> và <NAME=CP_0002> nhận ra họ đang ở quá khứ của <NAME=MA_0003_01>. Trận quyết chiến cuối cùng nổ ra trước <NAME=MA_0006_01>. Tuy nhiên, thấu hiểu nỗi đau khổ cùng cực của kẻ thù, <NAME=CP_0002> quyết định cùng chết với <NAME=EB_END1_01>, và xin <NAME=CP_0001> hãy vung nhát kiếm kết liễu. Sau hồi dằn vặt khôn nguôi, <NAME=CP_0001> đưa ra quyết định cuối cùng của đời mình. Mọi chuyện đã khép lại. Thế giới bước tiếp về phía tương lai, và những người còn sống bắt đầu hành trình của riêng mình... | D72: <NAME=EB_END1_01>が逃げた先は、 過去の<NAME=MA_0003_01>だった。 <NAME=CP_0001>と<NAME=CP_0002>は<NAME=EB_END1_01>を追跡し、 <NAME=MA_0006_01>の前で最後の戦いがはじまる。 だが、敵の哀しみを知った<NAME=CP_0002>は <NAME=EB_END1_01>とともに最期を遂げようと決意し、 自分ごと、とどめを刺すよう<NAME=CP_0001>に頼む。 苦悩の末、最後の決断を下す<NAME=CP_0001>。 すべてが終わり、生き残った仲間たちは未来へと、 それぞれの道を歩みはじめる。
A73: 1442.001_
A74: 1442.002_
A75: 1442.003_

Sheet BraveStoryPersonMessage
A1: ID | B1: English | C1: Vietnamese | D1: Note
A2: 1443.001_ | B2: 2 | D2: 2
A3: 1444_ | B3: True | D3: True
A4: 1444.001_ | B4: 0 | D4: 0
A5: 1445_ | B5: 24 | D5: 24
A6: 1446_ | B6: A young man who is a member of the masked tribe and makes his living as a mercenary. He is strikingly cold and aloof, but this stems from the bitter experiences he has endured, and his reluctance to entrust his decisions and choices to others. He is known for his strength, and is renowned for having seen every mission he ever took on through to its end. He has no master, and his self-taught sword technique has been developed through combat experience alone, but his prowess in battle speaks for itself. | C6: Một người đàn ông trẻ đến từ bộ tộc Mặt Nạ và là lính đánh thuê. Anh ta lạnh lùng và xa cách đến đáng kinh ngạc, tất cả xuất phát từ những kỉ niệm cay đắng mà anh đã phải trải qua, và anh ta không tin tưởng bất kì ai. Anh ta rất mạnh, và luôn hoàn thành nhiệm vụ của mình. Anh ta không có chủ, và thứ kiếm pháp tự học của anh ta được mài giũa thông qua chiến đấu, chính sự thông thạo chiến trường của anh ta đã nói lên điều này. | D6: 仮面の一族で、傭兵を生業 としている若者。 素っ気なく他者を突き放す ような言動が目立つが、 これはかなりの修羅場を くぐり抜けてきた経験から 来るものであり、 自分の意志や決定を他人の 手にゆだねることを嫌って いるためである。 「引き受けた依頼は確実に 完遂してきた」という実績 から、その筋ではかなり 知られているらしい。 師を持たず、剣技も戦いの中 で自然と磨かれた我流である が、その強さは一級品である。
A7: 1447_ | B7: Endir | C7: Endir | D7: エンド
A8: 1448_ | B8: Endir | C8: Endir | D8: エンド
A9: 1449_ | B9: Endir | C9: Endir | D9: エンド
A10: 1450_ | B10: The sacrifice, a girl from <NAME=MA_0003_01>. She inherited great magical energy from her mother. Since childhood, she has had a habit of staring into space. Worried, her father, <NAME=NPC_10010>, once consulted with the wisest woman in the village. Far from being worried, though, the old woman was amazed - she said she was able to see "connections" that cannot be seen by ordinary people. She is a cheerful and earnest girl, and although she can sometimes be stubborn, her sense of duty is extremely strong. | C10: Vật hiến tế, một cô gái đến từ <NAME=MA_0003_01>. Cô thừa kế pháp lực cực lớn từ mẹ mình. Từ khi còn bé, cô thường hay nhìn vào khoảng không. Lo lắng, bố cô, <NAME=NPC_10010>, từng đến hỏi ý kiến của người thông thái nhất trong làng. Bà ấy chỉ ngạc nhiên, cô có khả năng nhìn thấy những mối liên kết không người thường nào thấy được. Cô rất vui vẻ, chân thành, đôi khi hơi cứng đầu và tinh thần trách nhiệm rất cao. | D10: <NAME=MA_0003_01>出身の いけにえの少女。母親譲りの 魔力の高さもさることながら、 幼い頃から、何もない虚空に 目を向けるクセがあった。 それを心配した父親の<NAME=NPC_10010> は、村で一番の物知り老婆に 相談したという。 老婆が言うには、「この子には 常人の目には映らないつながり が見えてるんだねえ」と逆に 感心されたらしい。 性格が明るく真面目な反面、 融通が利かないという欠点が あるものの、いけにえとしての 使命感は強い。
A11: 1451_ | B11: Setsuna | C11: Setsuna | D11: セツナ
A12: 1452_ | B12: Setsuna | C12: Setsuna | D12: セツナ
A13: 1453_ | B13: Setsuna | C13: Setsuna | D13: セツナ
A14: 1454_ | B14: A girl who arrived in <NAME=MA_0003_01> to join the sacrifice's guard. Her cute looks and cuddly dress-sense belie a formidable magical ability. The pilgrimage's success seems to be of the utmost importance to her, and perhaps because of this, she can often come across as coldhearted. She sometimes says and does things with a very accustomed air, almost as if she has said or done them before. Whenever her companions question her about this, though, she will simply shrug it off. | C14: Một cô gái đến <NAME=MA_0003_01> để tham gia đội bảo vệ vật tế. Đằng sau vẻ ngoài đáng yêu của cô là năng lực pháp thuật lợi hại đáng kinh ngạc. Sự thành công của buổi tế lễ với cô có lẽ rất quan trọng, và có lẽ vì vậy, cô thường bị coi là lạnh lùng. Đôi khi cô hành động như thể cô đã làm những điều này từ rất lâu rồi. Mỗi khi bạn đồng hành hỏi cô về vấn đề này, cô từ chối trả lời. | D14: 護衛隊として、 <NAME=MA_0003_01>を 訪れていた少女。 ほんわかとした可愛らしい外見 とは裏腹に、魔法の腕前は かなりのものである。 いけにえの旅に対する思いは 誰よりも強く、絶対に失敗でき ないという責任感のためか、 一見すると冷酷ともいえる行動 を取ることもしばしば。 時折、既視感を感じさせる 言動をすることがあり、 仲間にそのことを指摘されると 「気のせいでしょ」のひと言で 素っ気なく片づけてしまう。
A15: 1455_ | B15: Aeterna | C15: Aeterna | D15: クオン
A16: 1456_ | B16: Aeterna | C16: Aeterna | D16: クオン
A17: 1457_ | B17: Aeterna | C17: Aeterna | D17: クオン
... A101: 1541_ | B101: Dark Samsara | C101: Sinh Vật Hắc Ám | D101: 輪廻の闇

Sheet BraveStorySetsunaMessage
A1: ID | B1: English | C1: Vietnamese | D1: Note
A2: 1541.001_ | B2: 2 | D2: 2
A3: 1542_ | B3: True | D3: True
A4: 1542.001_ | B4: 0 | D4: 0
A5: 1543_ | B5: 31 | D5: 31
A6: 1544_ | B6: Causes additional physical damage. Power, element, and number of hits will change according to the tech or combo used. Some will also gain damage adjustments or status effects. | C6: Gây thêm sát thương vật lý phụ. Uy lực, nguyên tố và số đòn đánh sẽ thay đổi tùy theo kỹ năng hoặc liên chiêu được sử dụng. Một số kỹ năng sẽ nhận thêm hiệu ứng tăng sát thương hoặc hiệu ứng trạng thái. | D6: 物理攻撃が追加で発生する。 威力やヒット数や属性は元となる魔法や連携によって変わる。 特殊補正や状態変化が発生するものもある。
A7: 1545_ | B7: Causes additional magical damage. Power, element, and number of hits will change according to the tech or combo used. Some will also gain damage adjustments or status effects. | C7: Gây thêm sát thương ma thuật phụ. Uy lực, nguyên tố và số đòn đánh sẽ thay đổi tùy theo kỹ năng hoặc liên chiêu được sử dụng. Một số kỹ năng sẽ nhận thêm hiệu ứng tăng sát thương hoặc hiệu ứng trạng thái. | D7: 魔法攻撃が追加で発生する。 威力やヒット数や属性は元となる魔法や連携によって変わる。 特殊補正や状態変化が発生するものもある。
A8: 1546_ | B8: Causes additional special damage. Power, element, and number of hits will change according to the tech or combo used. Some will also gain damage adjustments or status effects. | C8: Gây thêm sát thương đặc biệt phụ. Uy lực, nguyên tố và số đòn đánh sẽ thay đổi tùy theo kỹ năng hoặc liên chiêu được sử dụng. Một số kỹ năng sẽ nhận thêm hiệu ứng tăng sát thương hoặc hiệu ứng trạng thái. | D8: 特殊攻撃が追加で発生する。 威力やヒット数や属性は元となる魔法や連携によって変わる。 特殊補正や状態変化が発生するものもある。
A9: 1547_ | B9: Special damage will instead be inflicted. | C9: Sát thương gây ra sẽ được chuyển đổi thành sát thương đặc biệt. | D9: 攻撃の種類が特殊攻撃となる。
A10: 1548_ | B10: Damage of all elemental types will instead be inflicted. | C10: Sát thương gây ra sẽ mang đầy đủ tất cả các loại nguyên tố cùng lúc. | D10: 攻撃の属性が全ての属性を持つようになる。
A11: 1549_ | B11: Damage adjustment counters will no longer be reset when using the tech or combo. The counters that will no longer be reset are: Hit Chain, Skill Chain, Same-Element Chain, Multi-Element Chain, Actions (Total), Actions (Type), Used Momentum, Unused Momentum, Total Healed, Attacks Received, Damage Taken, and Critical Hits. | C11: Các bộ đếm gia tăng sát thương sẽ không còn bị đặt lại về 0 sau khi thi triển kỹ năng hoặc liên chiêu. Các bộ đếm được giữ nguyên gồm: Chuỗi Đòn, Chuỗi Kỹ Năng, Chuỗi Đồng Nguyên Tố, Chuỗi Đa Nguyên Tố, Tổng Hành Động, Loại Hành Động, Xung Lực Đã Dùng, Xung Lực Chưa Dùng, Tổng Trị Liệu, Đòn Đã Nhận, Sát Thương Đã Chịu và Đòn Chí Mạng. | D11: 魔法や連携の威力補正用のカウントがリセットされなくなる。 リセットされないカウントは、「ヒットコンボ補正」「スキルコンボ補正」「同属性コンボ補正」「異属性コンボ補正」「行動回数補正」「行動種数補正」「刹那発動回数補正」「刹那未発動回数補正」「回復合計補正」「防御回数補正」「被ダメージ補正」「クリティカル回数補正」である。
A12: 1550_ | B12: HP will also be recovered. Type (Strength/Intelligence-based) and power will change according to the tech or combo used. | C12: Gia tăng tỉ lệ đánh chí mạng của đòn tấn công phụ trong chế độ Xung Lực. | D12: HP回復が追加で発生する。 種類や威力は元となる魔法や連携によって変わる。
A13: 1551_ | B13: MP will also be recovered. Type (Strength/Intelligence-based) and power will change according to the tech or combo used. | C13: Hồi phục thêm một lượng HP cho toàn bộ đồng minh khi kích hoạt Xung Lực. | D13: MP回復が追加で発生する。 種類や威力は元となる魔法や連携によって変わる。
A14: 1552_ | B14: Heals all status ailments. | C14: Hồi phục thêm một lượng MP cho toàn bộ đồng minh khi kích hoạt Xung Lực. | D14: 全ての状態異常を解除する。
A15: 1553_ | B15: An additional status boost will be generated. Type, boost amount, and duration will change according to the tech or combo used. | C15: Giải trừ toàn bộ trạng thái bất lợi cho người dùng khi kích hoạt Xung Lực. | D15: 状態強化が追加で発生する。 種類や上昇値や発生時間は元となる魔法や連携によって変わる。
A16: 1554_ | B16: An additional status ailment will be inflicted. Type, reduction amount, and duration will change according to the tech or combo used. | C16: Ban trạng thái Vô Hình (Tàng Hình) tạm thời cho nhân vật sau khi xuất chiêu Xung Lực. | D16: 状態異常が追加で発生する。 種類や低下値や発生時間は元となる魔法や連携によって変わる。
A17: 1555_ | B17: The tech or combo will now affect all allies or enemies. | C17: Lập tức nạp sẵn một phần thanh ATB sau khi hoàn tất đòn tấn công Xung Lực. | D17: 魔法や連携の効果範囲を全体化する。
... A36: 1574_ | B36: Causes Fluxation to occur more easily. Also increases damage according to the number of Fluxes added to equipped spritnite. | C36: Tạo xung lực cộng hưởng khiến đòn đánh lan sang toàn bộ kẻ địch xung quanh. | D36: 昇華が発生しやすくなる。また、装備している法石の昇華数が多いほど、行動の威力が大きくなる効果もある。

Sheet BraveStorySublimationMessage
A1: ID | B1: English | C1: Vietnamese | D1: Note
A2: 1574.001_ | B2: 2 | D2: 2
A3: 1575_ | B3: True | D3: True
A4: 1575.001_ | B4: 0 | D4: 0
A5: 1576_ | B5: 19 | D5: 19
A6: 1577_ | B6: Increases the power of the corresponding tech. Each tech will change in different ways. When more than one "Tech Power" Flux is added, power will be further increased. | C6: Tăng uy lực của kỹ năng tương ứng. Mỗi kỹ năng sẽ có cách biến đổi khác nhau. Khi gắn nhiều hơn một Flux 'Uy Lực Kỹ Năng', sức mạnh sẽ tăng thêm nữa. | D6: 魔法によって発生する効果が大きくなる。 強化内容は発生効果によって、さまざまである。 ［魔法威力］が複数昇華しているときは、魔法の効果がさらに大きくなる。
A7: 1578_ | B7: Increases the power of corresponding combos. Each combo will change in different ways. When more than one "Combo Power" Flux is added, power will be further increased. | C7: Tăng uy lực của liên chiêu (Combo) tương ứng. Mỗi liên chiêu sẽ biến đổi khác nhau. Khi gắn nhiều hơn một Flux 'Uy Lực Liên Chiêu', sức mạnh sẽ tăng thêm nữa. | D7: 連携によって発生する効果が大きくなる。 強化内容は発生効果によって、さまざまである。 ［連携威力］が複数昇華しているときは、連携の効果がさらに大きくなる。
A8: 1579_ | B8: Increases the power of the additional effects generated when using the corresponding tech/combos in Momentum mode. Different effects will change in different ways. When more than one "Momentum Effect" Flux is added, power will be further increased. | C8: Gia tăng sức mạnh của hiệu ứng phụ khi dùng kỹ năng/liên chiêu tương ứng ở chế độ Xung Lực. Khi gắn nhiều hơn một Flux 'Hiệu Ứng Xung Lực', hiệu quả sẽ tăng thêm nữa. | D8: 魔法や連携を使用したときに、刹那システムを発動することで発生する効果が大きくなる。 強化内容は発生効果によって、さまざまである。 ［刹那威力］が複数昇華しているときは、刹那システムの効果がさらに大きくなる。
A9: 1580_ | B9: Increases the critical hit rate of the corresponding tech/combos. When critical hits are generated, attack techs will cause more damage, healing techs will recover more HP/MP, and the turn duration of status effects will be increased. When more than one "Critical Hit Rate" Flux is added, the rate will be further increased. | C9: Gia tăng tỉ lệ chí mạng của kỹ năng/liên chiêu tương ứng. Khi đánh chí mạng, đòn tấn công gây thêm sát thương, đòn trị liệu hồi nhiều máu hơn và thời gian hiệu lực bùa lợi tăng lên. Khi gắn nhiều hơn một Flux 'Tỉ Lệ Chí Mạng', tỉ lệ sẽ tăng thêm nữa. | D9: 効果のクリティカル率が高くなる。 クリティカルが発生すると、攻撃や回復では効果値が上昇し、状態発生では発生するターンが長くなる。 ［クリティカル率］が複数昇華しているときは、クリティカル率がさらに高くなる。
A10: 1581_ | B10: Increases the level of the ATB gauge immediately after using the corresponding tech. When more than one "ATB Bonus" Flux is added, the level will be further increased. | C10: Gia tăng mức nạp sẵn của thanh ATB ngay sau khi dùng kỹ năng tương ứng. Khi gắn nhiều hơn một Flux 'Thưởng ATB', thanh ATB sẽ nạp sẵn nhiều hơn nữa. | D10: 魔法を使用した直後のATB値が高くなる。 ［行動後ATB値］が複数昇華しているときは、ATB値がさらに高くなる。
A11: 1582_ | B11: Reduces the amount of MP consumed when using the corresponding tech. When more than one "MP Consumed" Flux is added, the amount consumed will be further reduced. | C11: Giảm lượng MP tiêu hao khi dùng kỹ năng tương ứng. Khi gắn nhiều hơn một Flux 'Giảm Tiêu Hao MP', lượng MP tiêu tốn sẽ giảm thêm nữa. | D11: 魔法を使用するときに消費するMPが小さくなる。 ［消費MP］が複数昇華しているときは、消費MPがさらに高くなる。
A12: 1583_ | B12: Increases the amount of SP accumulated when the corresponding tech is used. When more than one "SP Accumulated" Flux is added, the amount accumulated will be further increased. | C12: Gia tăng lượng HP hồi phục khi dùng các kỹ năng trị thương tương ứng. Khi gắn nhiều hơn một Flux 'Cường Hóa Trị Liệu', lượng máu hồi phục sẽ tăng thêm nữa. | D12: 魔法を使用したときに蓄積するSPが大きくなる。 ［蓄積SP］が複数昇華しているときは、蓄積SPがさらに高くなる。
A13: 1584_ | B13: Reduces the amount of damage received when attacked immediately after using the corresponding tech. This reduction stays in effect until another action is performed. When more than one "Momentary Defense" Flux is added, the amount received will be further reduced. | C13: Kéo dài thời gian duy trì của các hiệu ứng tăng chỉ số (Buff) trên đồng minh. Khi gắn nhiều hơn một Flux 'Kéo Dài Bùa Lợi', thời gian hiệu lực sẽ tăng thêm nữa. | D13: 魔法を使用した直後の被ダメージが小さくなる。 被ダメージ低下の効果が発生するのは、次の行動が終了するまでとなる。 ［行動後防御］が複数昇華しているときは、被ダメージがさらに小さくなる。
A14: 1585_ | B14: Recovers HP immediately after using the corresponding tech. HP is only recovered by the tech's user, and nearby allies will not be affected. When more than one "Momentary Recovery" Flux is added, the amount recovered will be increased. | C14: Gia tăng tỉ lệ xuất hiện hiệu ứng bất lợi (Debuff) lên kẻ địch khi dùng kỹ năng. Khi gắn nhiều hơn một Flux 'Hiệu Ứng Bất Lợi', tỉ lệ áp đặt sẽ tăng thêm nữa. | D14: 魔法を使用した直後にHPが回復する。 回復の対象となるのは、魔法の使用者単体であり、周囲には発生しない。 ［行動後回復］が複数昇華しているときは、HP回復量が大きくなる。
A15: 1586_ | B15: Boosts Strength and Intelligence immediately after using the corresponding tech. This boost stays in effect until another action is performed. When more than one "Momentary Boost" Flux is added, stats will be boosted by a larger amount. | C15: Bỏ qua một phần chỉ số Phòng Thủ của mục tiêu khi thực hiện đòn tấn công. Khi gắn nhiều hơn một Flux 'Xuyên Giáp', lượng phòng thủ bị bỏ qua sẽ lớn hơn. | D15: 魔法を使用した直後の腕力と魔力が上昇する。 能力上昇の効果が発生するのは、次の行動が終了するまでとなる。 ［行動後支援］が複数昇華しているときは、腕力と魔力がさらに大きくなる。
A16: 1587_ | B16: Enables Combo Release for corresponding combos, meaning they can be used even when only one character has a full ATB gauge. However, when a combo is used in this way, the amount of MP consumed is increased. When more than one "Combo Release" Flux is added, MP consumption will be increased by a lower amount. | C16: Gia tăng lượng SP tích lũy nhận được sau mỗi đòn tấn công hoặc hành động. Khi gắn nhiều hơn một Flux 'Tăng Tích Lũy SP', tốc độ nạp thanh SP sẽ nhanh hơn. | D16: ［連携解放］が昇華した法石に対応した連携を使用するときに、連携に参加するキャラクターが全て、ATBがたまっていなくても使用できるようになる。 ただし、ATBがたまっていないキャラクターがいる状態で連携を使用しようとすると、消費MPが上昇してしまうデメリットもある。 ［連携解放］が複数昇華しているときは、消費MPの上昇を抑えることができる。
A17: 1588_ | B17: Increases the power of the corresponding tech/combos when the user's HP is at 80% or more of his or her maximum HP. When more than one "Unscathed Power" Flux is added, power will be further increased. | C17: Gia tăng sát thương gây ra khi đánh trúng điểm yếu nguyên tố của kẻ địch. Khi gắn nhiều hơn một Flux 'Đòn Điểm Yếu', sát thương điểm yếu sẽ tăng mạnh mẽ. | D17: 魔法や連携を使用するとき、使用者のHPが最大HPの80%以上であれば、発生する効果が大きくなる。 ［無傷時威力］が複数昇華しているときは、魔法や連携の効果がさらに大きくなる。
... A24: 1595_ | B24: This type of Flux is only added to Support Spritnite. When Fluxation occurs in one Support Spritnite, the effect of another equipped Support Spritnite will be added to it. However, this added effect will only possess 1/10 of its original power. When more than one "Support Bonus" Flux is added, the power of this added effect will be increased. | C24: Kích hoạt hiệu ứng ma thuật ngẫu nhiên có lợi khi thanh SP đạt trạng thái tối đa. Khi gắn nhiều hơn một Flux 'Kỳ Tích SP', hiệu quả kích hoạt sẽ vượt bậc. | D24: サポート法石のみに発生する昇華である。 昇華が発生したときに、発生対象の法石以外で、装備しているサポート法石のどれかの効果が1/10の効果値ながら、発生するようになる。 同じサポート法石の効果が複数昇華しているときは、そのサポート効果がさらに大きくなる。

Sheet BraveStoryWeaponMessage
A1: ID | B1: English | C1: Vietnamese | D1: Note
A2: 1595.001_ | B2: 2 | D2: 2
A3: 1596_ | B3: True | D3: True
A4: 1596.001_ | B4: 0 | D4: 0
A5: 1597_ | B5: 79 | D5: 79
A6: 1598_ | B6: The forging process behind this sword is passed down in the masked tribe. All members forge their own swords when they begin working as mercenaries. Its blade is made from a special metal that responds to the forger's magical energy, thus preventing anyone else from equipping it. In return, it provides incredible ease of use. It boasts an excellent balance between offensive and defensive ability, and is perfect for solo combat. | C6: Quy trình rèn thanh kiếm này được truyền đời trong bộ tộc Mặt Nạ. Mọi thành viên đều tự tay rèn thanh kiếm cho riêng mình khi bắt đầu hành nghề lính đánh thuê. Lưỡi kiếm được chế tác từ kim loại đặc biệt phản ứng với ma lực của người rèn, ngăn không cho bất kỳ ai khác sử dụng. Đổi lại, nó mang lại sự linh hoạt tuyệt vời, cân bằng hoàn hảo giữa công và thủ, lý tưởng cho chiến đấu độc hành. | D6: 傭兵の一族として有名な、仮面の一族に製法が伝わる剣。 一族の者が稼業として、傭兵を始めるときに自ら鍛えあげる。刀身に使用している金属は魔力に感応する性質があり鍛えあげるときに、本人の魔力に感応させることで鍛えあげた本人以外は装備できなくなるが抜群の扱いやすさを誇る。 攻撃と防御のバランスに優れた性能であり傭兵らしく、一人で戦う事に適した剣と言える。
A7: 1599_ | B7: This sword has been forged entirely from an ultra-hard, lightweight metal known as Levissium. Although Levissium is well known among blacksmiths, it is difficult to process using current technology, and few other people know of it. The focus of this sword's forger was clearly on usability, and although it is somewhat lacking in terms of attack power, it makes up for this in defensive ability. Its lightness means that the user can move more swiftly and dodge sudden attacks. | C7: Thanh kiếm này được rèn hoàn toàn từ loại kim loại siêu cứng và siêu nhẹ mang tên Levissium. Dù Levissium rất nổi tiếng trong giới thợ rèn, nó cực kỳ khó gia công với công nghệ hiện nay và rất ít người biết đến. Người rèn thanh kiếm này tập trung tối đa vào độ tiện dụng; tuy sức tấn công khiêm tốn, nó bù đắp bằng khả năng phòng thủ xuất sắc. Trọng lượng nhẹ giúp người dùng di chuyển mau lẹ và né tránh đòn đánh bất ngờ. | D7: 軽量であり高硬度のレウィス金属のみで作られた剣。 レウィス金属はその性質から鍛冶を志す者からは注目されている金属ではあるものの現在の技術力では加工するのが難しいため、あまり知られることがない金属である。 扱いやすさを優先した結果、攻撃力がやや劣るところはあるもののその軽さゆえに、素早く動けるようになるだけではなく咄嗟の攻撃も素早く受け流すことができ、防御に優れている。
A8: 1600_ | B8: A sword made using a time-elemental spritnite stone. Long ago, a magician carrying out forbidden research succeeded in sealing time energy inside a physical object, and this taboo blade is a result of transferring that energy into a weapon. Everything its blade slices through turns a frosty white before crumbling into nothingness, and this is the reason behind its name. Foes hit with this blade receive time-elemental damage. | C8: Thanh kiếm được chế tác từ đá Spritnite nguyên tố Thời Gian. Thuở xưa, một pháp sư nghiên cứu cấm thuật đã phong ấn thành công năng lượng thời gian vào vật thể, và lưỡi kiếm cấm kỵ này là kết quả của việc chuyển hóa năng lượng đó vào vũ khí. Mọi thứ bị lưỡi kiếm chém qua đều chuyển sang màu trắng băng giá trước khi tan biến vào hư không, đó cũng là nguồn gốc tên gọi của nó. Đòn đánh mang sát thương hệ Thời Gian. | D8: 時の魔力の法石で作られた剣。遙か昔、禁じられた時の研究を行っていた魔術師が物質に時の魔力を封じ込めることに成功し、武器に時エネルギーを転化することで生まれた異端の武器。斬り付けられた箇所は霜が落ちたかの様に白く染まり、まるで何も無かったかのようにボロボロと崩れ落ち、流星のように煌めき消える様が名前の由来となった。 この剣で斬られた者は時の魔力によるダメージを受ける。
A9: 1601_ | B9: A thin sword that glows with a golden hue. It was forged from a magnetized metal that was repeatedly refined using powerful magical energy in order to further increase its density. The effect of the magnetism and magical energy have given it a curved and jutted blade. Although thin, its blade is incredibly strong and supple, and the powerful magical energy imbued in it means it does not nick easily. The special metal and magical energy used when forging it cause it to inflict light-elemental damage. | C9: Thanh kiếm mảnh phát ra ánh hào quang hoàng kim rực rỡ. Nó được rèn từ kim loại nhiễm từ được tinh luyện nhiều lần bằng ma lực hùng mạnh nhằm gia tăng mật độ vật chất. Tác động của từ tính và ma lực tạo nên lưỡi kiếm uốn cong độc đáo. Dù mỏng manh, lưỡi kiếm cực kỳ dẻo dai và chắc khỏe, được yểm ma lực giúp không bao giờ bị mẻ. Vũ khí gây sát thương nguyên tố Quang. | D9: 黄金に輝く細剣。 磁気を帯びた金属に対して、強い魔力を浴びせながら何日も練り上げ続け、練り上げる前よりも密度が濃くなった金属を、一気に鍛造し仕上げた剣。 磁気と魔力のせいで刃が幾重にも飛び出している。 細身の剣だがとても強くしなやかで、強い魔力により刀身が傷付きにくい。 また、特殊な金属と魔力を浴びせて作ったことにより、天属性を併せ持つ。
A10: 1602_ | B10: This curved sword is wrapped in blazing flames. It was created using a spritnite stone containing fire energy with a particular affinity to metal. In order to best extract this energy, the blade has been tempered using Teruru ore that has accumulated natural magical energy over many years. It is very easy to wield, and produces powerful slashes without much force being exerted. The brightly burning crimson gem set in its guard and the fire energy sealed inside it inflict powerful fire-elemental damage. | C10: Thanh kiếm cong rực cháy trong ngọn lửa đỏ thẫm. Nó được tạo ra từ đá Spritnite chứa năng lượng hỏa có ái lực đặc biệt với kim loại. Để khai thác tối đa nguồn năng lượng này, lưỡi kiếm được tôi luyện bằng quặng Teruru tích tụ ma lực tự nhiên qua hàng trăm năm. Kiếm rất dễ sử dụng, tạo ra những nhát chém uy lực mà không tốn nhiều sức. Viên ngọc đỏ rực trên chuôi kiếm gây sát thương nguyên tố Hỏa mạnh mẽ. | D10: 燃え盛る炎を纏った剣。 金属と特に相性の良い炎の魔力を秘めた法石を用い、その力を最大限に引き出すために長年自然の魔力を溜めこんだテルル鉱石を使用して見事に鍛え上げられた剣。 剣全体が波のように湾曲しており、持ち易く力を入れずとも相手を深く斬り付けることができる。力強く燃え盛る紅蓮の刀身と炎の魔力を封じ込めた核により斬り付けた相手に火の魔力で大ダメージを与える。
A11: 1603_ | B11: A sword thought to have been created by an organization that once carried out research into magical energy. Its dull red blade leaves little to be desired in terms of attack power, but also contains an enormous amount of magical energy, which can be further increased through tempering. It was created based around the concept of "a demon to slay demons." Few weapons created by the organization that made it remain, and its rarity and historical value make it a highly-sought-after item among collectors. | C11: Thanh kiếm được cho là do một tổ chức từng nghiên cứu ma lực cổ đại chế tạo. Lưỡi kiếm đỏ thẫm mang sức mạnh tấn công đáng nể cùng lượng ma lực khổng lồ có thể gia tăng qua rèn đúc. Nó được tạo ra dựa trên tôn chỉ 'dùng quỷ để diệt quỷ'. Rất ít vũ khí của tổ chức này còn sót lại, độ hiếm và giá trị lịch sử khiến nó trở thành báu vật săn lùng của các nhà sưu tầm. | D11: 過去に魔力の研究を行ったある機関が作り出したとされる剣。鈍く赤い刀身は直接的な攻撃力も申し分ないが、途方も無い強力な魔力が込められており、鍛えることで更にその魔力が向上する。 「魔を以って魔を絶つ」を理念に作られたこの剣は、特出して魔力が高い。 この機関が作りあげた武器は現存している数はとても少なく、希少性の高い物であることは間違いなく、歴史的価値も高いことから、この剣を欲しがるコレクターは多数存在する。
A12: 1604_ | B12: This sword is wrapped in a freezing aura of ice. It was forged using an extremely laborious and time-consuming process. The water-elemental spritnite stone used is said to have a bad affinity with metal, but it is also able to permeate other substances, so it was made to gradually permeate the metal over a long period of time. Its whole blade is cloaked in elemental magical energy, and the energy emanating from its guard also further increases the water-elemental damage inflicted. | C12: Thanh kiếm này được bao bọc trong luồng hàn khí băng giá buốt lạnh. Nó được rèn bằng quặng băng vĩnh cửu khai thác từ độ sâu hàng ngàn mét dưới lòng đất. Hàn khí tỏa ra từ lưỡi kiếm làm chậm dòng máu của kẻ thù khi chém trúng, gây sát thương hệ Thủy và có khả năng làm đóng băng mục tiêu. | D12: 凍てつく凍気を纏った剣。 金属と相性が悪いとされる水属性の法石を、他の物質に侵食するという特性を活かし、金属の元となる元素に長年かけて少しずつ侵食させた後、金属として鍛え上げた手間と時間が掛かる剣。 刀身全体に属性魔力を帯び、大きな核から送られる魔力から水属性の魔力を更に高めることが出来る。 斬り付けた相手は水の魔力により大きなダメージを受ける。
A13: 1605_ | B13: A sword forged using techniques that originate from an ancient land, where it was known as a "wazamono." Unlike heavier blades that employ great force when striking at foes, its light and simple blade relies on a fearsome sharpness, and is able to easily slice through even bone. Its edge is completely smooth, to the point where it can be considered a work of art. Its fine blade can cut through anything, and will produce even greater attack power when sharpened. | C13: Thanh kiếm được rèn theo kỹ nghệ bí truyền từ một vùng đất viễn đông cổ kính. Kiếm được tôi luyện hàng trăm lần để đạt tới độ sắc bén hoàn hảo, có thể chém đứt cả ngọn gió mà không phát ra tiếng động. Kiếm tăng mạnh tỉ lệ đánh chí mạng. | D13: 大陸に存在した古の国から伝わった製法で鍛え上げた剣。 軽くシンプルなその刃は、相手に力強く叩きつける剛剣とは違い、刃を引くことで凄まじい切れ味を発揮し、骨をも綺麗に切断する。 切断面には一切の凹凸がなく、まさに芸術といってよい。 古の国ではワザモノと呼ぶ。 細く粘りのあるその刀身に切断できないものは無く、研ぎ澄ますことでより高い攻撃力が期待できる。
A14: 1606_ | B14: A sword created from ancient relics excavated from the ruins of the ancient kingdom that once ruled over the mainland. When analyzed, these relics were found to contain vast magical energy. The sword's blade was forged using a process that cannot be replicated today, and combined with this great magical energy, it gives the weapon truly mighty power. However, the weapon's true value lies in the increased damage inflicted when striking a foe's weak element. | C14: Thanh kiếm được chế tác từ các cổ vật khai quật tại tàn tích vương triều cổ xưa. Năng lượng cổ đại còn lưu lại trên thân kiếm ban cho người sử dụng khả năng hấp thụ một phần ma lực của đối thủ sau mỗi đòn đánh trúng. | D14: 古の遺産から作られた剣。 遙か昔、大陸を支配していた古の王国の遺跡から出土した物質を解析したところ、膨大な魔力が秘められている事が分かった。また、現代では再現できない製法で作られた刀身と併せることでその威力が増大することを突き止めた。 ただしその真価は弱点属性を攻撃したときにあり、より威力が大きくなるという。
A15: 1607_ | B15: A sword created entirely from materialized magical energy. Momentum power was used when materializing it, and the blade can still control this power. It is able to cut through the flow of time itself, a feat thought to be impossible. The weapon's true worth lies in the honing effect it has on the user's senses, which boosts the rate at which the SP gauge rises, allowing the user to strike at gaps in foes' defenses with perfect precision. | C15: Thanh kiếm được ngưng tụ hoàn toàn từ ma lực thuần khiết vật chất hóa. Ở chế độ Xung Lực, thanh kiếm giải phóng toàn bộ tiềm năng ma thuật, gia tăng uy lực đòn tấn công gấp bội. | D15: 全てが魔力を物質化して作られた剣。 物質化するときに刹那の力を持って、作りあげられたがゆえに、刀身はその力を刻み続けている。また、本来は斬ることができない、魔力の流れすらも斬ることができる特性を持つ。 その真価は己の神経を研ぎ澄まし、SPのゲージ上昇を促すことで、相手の隙を的確に突くことができることにある。
A16: 1608_ | B16: A giant, sinister blade crafted using various monster bones and metals. It was wielded by one of the three rare-blood sisters. Their sadness, rage, and suffering can be felt through the blade, and these negative emotions eat away at the wielder's heart. However, when the wielder understands the reasons for the sisters' pain, a vague kindness and sense of relief can also be sensed. Its blade is soaked with the blood of countless battles and the negative emotions of those it has slain, and it is steeped in shadow-elemental energy. | C16: Thanh đại kiếm khổng lồ hắc ám được chế tạo từ các bộ phận của quái vật hung hãn nhất. Nguồn tà khí bên trong thanh kiếm khuấy động sự cuồng nộ của người cầm lái, đổi lấy sức tấn công vật lý vô song. | D16: 三姉妹が所持していた巨大剣。禍々しいそれは、様々な魔物の骨や金属から作られており、持つ者の心に彼女たちの悲しみや怒り、苦悩といった負の感情が感じられ、持つ者の心を蝕む。しかし彼女たちの心を理解した今、少しのやさしさや安堵感を感じられる。 刀身には幾多の戦いから染み込んだ血や、斬った者の負の感情を吸収しており、冥属性が染み付いている。
A17: 1609_ | B17: A mysterious sword created in an alternate dimension. Its jet-black blade belies an unbelievable lightness, and it fits the hand with a strange sense of familiarity, feeling like an extension of the user's own body. Its guard is shaped like two crossed swords, which are likely some sort of crest or symbol. When held in the hand, the sword imbues a strangely calm feeling, filling the user with bravery and benevolence. It possesses exceptional physical attack power, and is even said to bring good luck. | C17: Thanh kiếm huyền bí được tạo ra từ một chiều không gian dị giới. Lưỡi kiếm dường như tồn tại giữa các ranh giới thực tại, cho phép nó chém xuyên qua các lớp phòng ngự kiên cố nhất của kẻ thù. | D17: この世界ではない異次元で作られた謎の剣。 漆黒の刀身からは想像もできない軽さで自分の体の一部のように不思議と手に馴染み、何故か懐かしさすら感じさせる。 柄は剣が交差するような形となっており、何かしらの紋章のようにも見える。 握っていると不思議と気持ちが晴れ、勇気と優しさが溢れてくる。この剣は特に物理攻撃力に優れており、またこれを持つことで幸運が訪れる。
... A84: 1676_ | B84: A scythe that was excavated from the ruins of an ancient civilization. It cannot be analyzed using today's technology, and the details of how it was made are unknown. According to ancient texts, the red part of its blade feeds on the blood and magical energy of its victims. This red part is in fact a liquid organism with no fixed shape, but the upper part of the blade fixes it in place, allowing it to be used as a weapon. However, the blade is able to extend when attacking, and it offers a particularly wide attack range. | C84: Lưỡi hái khai quật từ lăng mộ của một vị vua cổ đại. Chứa đựng lời nguyền ngàn năm có thể đoạt mạng kẻ địch trong chớp mắt. | D84: 古代文明の遺跡から発掘された鎌。現代の技術で解析不可能な代物で、どう組み立てられ、何の素材でできているのかわからない。古い書物によれば、赤い刀身部分は外部から栄養を摂取するかのように、斬った相手の魔力と血を取り込む。もともと赤い刀身は形状の無い液体のような生命体であり、刃の外側に設けられたカバーのようなものと柄部分が赤い刀身を抑え込む役割を果たしており、液体を刃の形状に抑え込むことで初めて武器として扱えるようだ。しかし抑え込んだ今も攻撃時に刀身が伸び、通常の武器よりも広い範囲を攻撃できる。

Sheet ConsumptionItemMessage
A1: ID | B1: English | C1: Vietnamese | D1: Note
A2: 1676.001_ | B2: 2 | D2: 2
A3: 1677_ | B3: True | D3: True
A4: 1677.001_ | B4: 0 | D4: 0
A5: 1678_ | B5: 16 | D5: 16
A6: 1679_ | B6: Potion | C6: Thuốc Hồi Máu | D6: ポーション
A7: 1680_ | B7: Recovers a small amount of HP. | C7: Hồi phục một lượng nhỏ HP | D7: HPが小回復する。
A8: 1681_ | B8: Mid-Potion | C8: Thuốc Hồi Máu - Trung | D8: ミドルポーション
A9: 1682_ | B9: Recovers a medium amount of HP. | C9: Hồi phục một lượng vừa HP | D9: HPが中回復する。
A10: 1683_ | B10: Hi-Potion | C10: Thuốc Hồi Máu - Cao | D10: ハイポーション
A11: 1684_ | B11: Recovers a large amount of HP. | C11: Hồi phục lượng lớn HP | D11: HPが大回復する。
A12: 1685_ | B12: Ether | C12: Thuốc Hồi MP | D12: エーテル
A13: 1686_ | B13: Recovers a small amount of MP. | C13: Hồi phục lượng nhỏ MP | D13: MPが小回復する。
A14: 1687_ | B14: Mid-Ether | C14: Thuốc Hồi MP - Trung | D14: ミドルエーテル
A15: 1688_ | B15: Recovers a medium amount of MP. | C15: Hồi phục lượng vừa MP | D15: MPが中回復する。
A16: 1689_ | B16: Hi-Ether | C16: Thuốc Hồi MP - Cao | D16: ハイエーテル
A17: 1690_ | B17: Recovers a large amount of MP. | C17: Hồi phục lượng lớn MP | D17: MPが大回復する。
... A37: 1710_ | B37: Creates a smoke screen, allowing escape from battle. | C37: Để chuồn~ Rất có ích. | D37: 煙幕を発生させてバトルから逃走できる。

Sheet CookingItemMessage
A1: ID | B1: English | C1: Vietnamese | D1: Note
A2: 1710.001_ | B2: 2 | D2: 2
A3: 1711_ | B3: True | D3: True
A4: 1711.001_ | B4: 0 | D4: 0
A5: 1712_ | B5: 20 | D5: 20
A6: 1713_ | B6: Purikka Cobbler Salad | C6: Purikka Cobbler Salad | D6: 伯爵イモサラダ
A7: 1714_ | B7: A scrumptious salad that's enjoyed across the mainland. It boosts the amount of EXP earned, number of drops, and maximum HP. | C7: Món salad ròn giụm được ưa chuộng khắp Lục Địa. Chúng tăng lượng EXP được nhận, lượng vật phẩm rớt ra và máu tối đa. | D7: 入手経験値とドロップ数と最大HPの上昇 が発生する料理である。 雪世界では定番の料理。おいしい。
A8: 1715_ | B8: Hailbean Stew | C8: Hailbean Stew | D8: しずく豆腐の野菜鍋
A9: 1716_ | B9: A satisfying stew that's loved by everyone. It boosts the amount of EXP earned, number of drops, and physical attack power. | C9: Món hầm mang lại cảm giác thỏa mãn cho mọi người. Nó tăng lượng EXP nhận được, lượng vật phẩm rơi ra và vật công. | D9: 入手経験値とドロップ数と物理攻撃力の上昇 が発生する料理である。 みんなのごちそう。おいしい。
A10: 1717_ | B10: Fluffshroom Stir-Fry | C10: Fluffshroom Stir-Fry | D10: ふわりマイタケの炒め物
A11: 1718_ | B11: An addictive dish with a unique texture. It boosts the amount of EXP earned, number of drops, and physical defense power. | C11: Một món ăn gây nghiện với kết cấu độc đáo. Tăng lượng EXP nhận được, lượng vật phẩm rớt ra và điểm phòng thủ vật công. | D11: 入手経験値とドロップ数と物理防御力の上昇 が発生する料理である。 独特の歯ごたえに病みつきになる。
A12: 1719_ | B12: Floneian Vegetable Stew | C12: Floneian Vegetable Stew | D12: ウカテイナ風野菜土鍋蒸し
A13: 1720_ | B13: This stew fills the whole body with a warm, gentle feeling. It boosts the amount of EXP earned, number of drops, and critical hit rate. | C13: Món hầm khiến người ta bị lấp đầy bởi cảm giác ấm áp, nhẹ nhàng. Tăng lượng EXP nhận được, lượng vật phẩm rớt ra cùng khả năng chí mạng. | D13: 入手経験値とドロップ数とクリティカル率の上昇 が発生する料理である。 体にしみわたる優しい味がする。
A14: 1721_ | B14: Winterwhistle Soup | C14: Winterwhistle Soup | D14: 笛エノキ汁
A15: 1722_ | B15: A wonderful soup that really stimulates the taste buds. It boosts the amount of EXP earned, number of drops, and shadow-elemental resistance. | C15: Món súp tuyệt vời đánh thức tất cả vị giác của con người. Tăng lượng EXP nhận được, lượng vật phẩm rớt ra và khả năng kháng Hắc Ám nguyên tố | D15: 入手経験値とドロップ数と冥属性耐性の上昇 が発生する料理である。 舌を刺激するような食感が病みつきになる。
A16: 1723_ | B16: Lonely Mushroom Soup | C16: Lonely Mushroom Soup | D16: おさびしナメコ汁
A17: 1724_ | B17: A thick soup that will have you coming back for more. It boosts the amount of EXP earned, number of drops, and fire-elemental resistance. | C17: Món súp đặc quánh sẽ khiến bạn phải quay lại lần hai. Tăng lượng EXP nhận được, lượng vật phẩm rớt ra và khả năng kháng Hỏa nguyên tố. | D17: 入手経験値とドロップ数と火属性耐性の上昇 が発生する料理である。 ぬるっとした食感がクセになる。
... A45: 1752_ | B45: A simple but flavorsome soup. It greatly boosts the amount of EXP earned, and also boosts the number of drops. | C45: Món súp đơn giản mà đậm đà.Tăng lượng EXP nhận vào rất nhiều, cũng như khả năng rớt vật phẩm. | D45: 入手経験値［効果大］とドロップ数の上昇 が発生する料理である。 さっぱりだけど、それでいて濃厚な味わいがある。

Sheet EventItemMessage
A1: ID | B1: English | C1: Vietnamese | D1: Note
A2: 2210.001_ | B2: 2 | D2: 2
A3: 2211_ | B3: True | D3: True
A4: 2211.001_ | B4: 3 | D4: 3
A5: 2212_ | B5: 30 | D5: 30
A6: 2213_ | B6: Mother's Keepsake | C6: Mother's Keepsake | D6: 母のお守り
A7: 2214_ | B7: A pouch given to <NAME=CP_0002> by Raishin when her pilgrimage began. It was once carried by her mother, and contains a small stone. | C7: Một chiếc ví của mẹ <NAME=CP_0002> do bố trao cho cô trước khi cuộc hành hương bắt đầu. Có 1 hòn đá nhỏ. | D7: 旅立ちの日、ライシンから渡された <NAME=CP_0002>の母マナが生前身に着けていたという お守り。袋の中には何か硬い石が入っている。
A8: 2215_ | B8: Old Man's Letter | C8: Old Man's Letter | D8: ご隠居の手紙
A9: 2216_ | B9: A letter written by Dinas to Akash. It apparently contains "a little magic spell of sorts"... | C9: Một lá thư Dinas viết cho Akash. Có vẻ bên trong có "một loại pháp thuật nào đó". | D9: シャンバがアマツ宛てに書いた手紙。 ちょっとしたおまじないが書いてあるという。
A10: 2217_ | B10: Madara Spritnite | C10: Madara Spritnite | D10: マダラ法石
A11: 2218_ | B11: A mysterious spritnite stone taken from a Scarly. Its power is unknown, and to most people it would appear to be no more than a worthless pebble. | C11: Loại đá phép rơi khi đánh Scarly. Mang sức mạnh bí ẩn, đối với một số người, Madara chỉ như một viên đá cuội vô dụng | D11: 流氷地帯に生息するベシィがもつ不思議な法石。法石だがその力は未だ未知で一部の商会員 以外は価値のないただの石として見ている。
A12: 2219_ | B12: Secret Medicine | C12: Secret Medicine | D12: 魔導の秘薬
A13: 2220_ | B13: A powerful secret medicine carried by members of the Magic Consortium. It is said to be able to cure any illness. Its ingredients are unknown. | C13: Một loại thuốc bí ẩn được các thành viên Thương Hội Pháp Thuật mang theo mình. Tương truyền loại thuốc này có thể chữa mọi loại bệnh. Thành phần không rõ | D13: 旅をする魔導商会員が持つ、商会秘蔵の秘薬。 その効果は絶大でどんな病をもたちまち 治してしまうといわれている。原料は不明。
A14: 2221_ | B14: Memory Pendant | C14: Memory Pendant | D14: 思い出のペンダント
A15: 2222_ | B15: A pendant that was treasured by Sayagi the healer. It is no regular pendant, however, and possesses the power to unlock magic seals. | C15: Mặt dây chuyền được trị liệu sư Sayagi trân quý. Nó không phải mặt dây chuyền bình thường, có khả năng giải trừ phong ấn ma thuật | D15: 薬師サヤギが大切に持っていたペンダント。 しかし、それはただの装飾品ではなく、 魔力の封印を解くための魔法具の一種。
A16: 2223_ | B16: World Key | C16: World Key | D16: セカイノ鍵
A17: 2224_ | B17: A key received from Rhydderch. As well as activating the airship, it also unlocks the ancient treasure chests and ruins found across the land. | C17: Chiếc chìa khoá nhận được từ Rhydderch. Không chỉ dùng để khởi động tàu bay, nó còn có thể mở rương kho báu và cổng tàn tích trên khắp châu lục | D17: 王家の番人、英霊テンバから授かった古代文明 の封を解く鍵。飛空艇をはじめ、世界に散らばる 封印された宝箱や、扉などを解放する力をもつ。
... A65: 2272_ | B65: What was previously the "Prosperity Spritnite." It was reborn by being channeled with the power of the ancients. Part of it emits a faint, red glow. | C65: What was previously the "Prosperity Spritnite." It was reborn by being channeled with the power of the ancients. Part of it emits a faint, red glow. | D65: 繁栄の法石が古代人の残した力を受け、 「終焉の法石」として生まれ変わったもの。 一部が赤い色をかすかにはなっている。

Sheet EnemyBossSkillDataMessage
A1: ID | B1: English | C1: Vietnamese | D1: Note
A2: 1752.001_ | B2: 2 | D2: 2
A3: 1753_ | B3: True | D3: True
A4: 1753.001_ | B4: 1 | D4: 1
A5: 1754_ | B5: 272 | D5: 272
A6: 1755_ | B6: Dive Attack | C6: Lao Xuống Tấn Công | D6: ダイブアタック
A7: 1755.001_
A8: 1756_ | B8: Wing Slice | C8: Cánh Cắt | D8: ウイングカッター
A9: 1756.001_
A10: 1757_ | B10: Burning Breath | C10: Hơi Thở Rực Cháy | D10: ヒートブレス
A11: 1757.001_
A12: 1758_ | B12: Blazing Breath | C12: Hơi Thở Bốc Hỏa | D12: ファイアーブレス
A13: 1758.001_
A14: 1759_ | B14: Inhale | C14: Hít Vào | D14: 息を吸い込む
A15: 1759.001_
A16: 1760_ | B16: Inhale | C16: Hít Vào | D16: 息を吸い込む
A17: 1760.001_
A18: 1761_ | B18: Frosty Breath | C18: Hơi Thở Băng Giá | D18: アイスブレス
A19: 1761.001_
A20: 1762_ | B20: Blizzard Breath | C20: Hơi Thở Bão Tuyết | D20: ブリザードブレス
A21: 1762.001_
A22: 1763_ | B22: Inhale | C22: Hít Vào | D22: 息を吸い込む
A23: 1763.001_
A24: 1764_ | B24: Inhale | C24: Hít Vào | D24: 息を吸い込む
A25: 1764.001_
A26: 1765_ | B26: Big Bite | C26: Cú Đớp Lớn | D26: 咬みつく
A27: 1765.001_
A28: 1766_ | B28: Bodyslam | C28: Đè Toàn Thân | D28: 体あたり
A29: 1766.001_
A30: 1767_ | B30: Water Spray | C30: Phun Nước | D30: 水しぶき
A31: 1767.001_
A32: 1768_ | B32: Tsunami | C32: Sóng Thần | D32: 津波
A33: 1768.001_
A34: 1769_ | B34: Bellow | C34: Rống To | D34: ハウリング
A35: 1769.001_
A36: 1770_ | B36: Dive | C36: Lao Xuống | D36: 潜る
A37: 1770.001_
A38: 1771_ | B38: Tidal Wave | C38: Thủy Triều Sóng Thần | D38: 大海嘯
A39: 1771.001_
A40: 1772_ | B40: Big Bite | C40: Cú Đớp Lớn | D40: 咬みつく
A41: 1772.001_
A42: 1773_ | B42: Bodyslam | C42: Đè Toàn Thân | D42: 水しぶき
A43: 1773.001_
A44: 1774_ | B44: Tsunami | C44: Sóng Thần | D44: 津波
A45: 1774.001_
A46: 1775_ | B46: Snowstorm | C46: Bão Tuyết | D46: 猛吹雪
A47: 1775.001_
A48: 1776_ | B48: Tidal Wave | C48: Thủy Triều Sóng Thần | D48: 大海嘯
A49: 1776.001_
A50: 1777_ | B50: Slash | C50: Chém | D50: 斬りつける
A51: 1777.001_
A52: 1778_ | B52: Swipe | C52: Quét Móng | D52: 斬りはらう
A53: 1778.001_
A54: 1779_ | B54: Fire | C54: Hỏa Cầu | D54: ファイア
A55: 1779.001_
A56: 1780_ | B56: Fire II | C56: Hỏa Cầu II | D56: ファイガ
A57: 1780.001_
A58: 1781_ | B58: Ice | C58: Băng Cầu | D58: アイス
A59: 1781.001_
A60: 1782_ | B60: Ice II | C60: Băng Cầu II | D60: アイスガ
A61: 1782.001_
A62: 1783_ | B62: Toxic Breath | C62: Hơi Thở Độc Hại | D62: 猛毒の吐息
A63: 1783.001_
A64: 1784_ | B64: Hide in Shell | C64: Thu Vào Mai Rùa | D64: 甲羅にこもる
A65: 1784.001_
A66: 1785_ | B66: Emerge from Shell | C66: Chui Ra Khỏi Mai Rùa | D66: 甲羅から出る
A67: 1785.001_
A68: 1786_ | B68: Sweeping Spin | C68: Xoay Quét Toàn Diện | D68: 大回転
A69: 1786.001_
A70: 1787_ | B70: Lightning II | C70: Lôi Điệp II | D70: サンダガ
A71: 1787.001_
A72: 1788_ | B72: Demi II | C72: Trọng Lực II | D72: グラビガ
A73: 1788.001_
A74: 1789_ | B74: Deadly Claw | C74: Móng Vuốt Tử Thần | D74: キラークロー
A75: 1789.001_
A76: 1790_ | B76: Deadly Bite | C76: Cú Cắn Tử Thần | D76: キラーバイト
A77: 1790.001_
A78: 1791_ | B78: Transform | C78: Biến Hình | D78: 変身
A79: 1791.001_
A80: 1792_ | B80: Golden Claw | C80: Móng Vuốt Hoàng Kim | D80: 黄金の爪
A81: 1792.001_
A82: 1793_ | B82: Golden Fang | C82: Nanh Vuốt Hoàng Kim | D82: 黄金の牙
A83: 1793.001_
A84: 1794_ | B84: Golden Wind | C84: Gió Hoàng Kim | D84: 黄金の風
A85: 1794.001_
A86: 1795_ | B86: Slow | C86: Làm Chậm | D86: スロウ
A87: 1795.001_
A88: 1796_ | B88: Stop | C88: Ngưng Đọng | D88: ストップ
A89: 1796.001_
A90: 1797_ | B90: Missile Punch | C90: Đấm Tên Lửa | D90: ミサイルパンチ
A91: 1797.001_
A92: 1798_ | B92: Twin Missile Punch | C92: Song Đấm Tên Lửa | D92: ダブルミサイルパンチ
A93: 1798.001_
A94: 1799_ | B94: Laser Beam | C94: Tia Laser | D94: レーザービーム
A95: 1799.001_
A96: 1800_ | B96: Rampage | C96: Cuồng Nộ Hung Tợn | D96: 暴走
A97: 1800.001_
A98: 1801_ | B98: Slow II | C98: Làm Chậm II | D98: スロウガ
A99: 1801.001_
A100: 1802_ | B100: Stop II | C100: Ngưng Đọng II | D100: ストプガ
...

Sheet EnemyCoopSkillDataMessage
A1: ID | B1: English | C1: Vietnamese | D1: Note
A2: 1972.001_ | B2: 2 | D2: 2
A3: 1973_ | B3: True | D3: True
A4: 1973.001_ | B4: 1 | D4: 1
A5: 1974_ | B5: 38 | D5: 38
A6: 1975_ | B6: Hellflame Hammer | C6: Búa Lửa Địa Ngục | D6: 獄炎の鉄槌
A7: 1975.001_
A8: 1976_ | B8: Icy Sentence | C8: Bản Án Băng Giá | D8: 魔氷の断罪
A9: 1976.001_
A10: 1977_ | B10: Delta Attack | C10: Đòn Đánh Tam Giác Delta | D10: デルタアタック
A11: 1977.001_
A12: 1978_ | B12: Rocket Rush | C12: Tên Lửa Vút Bay | D12: ロケットラッシュ
A13: 1978.001_
A14: 1979_ | B14: Rocket Rush | C14: Tên Lửa Vút Bay | D14: ロケットラッシュ
A15: 1979.001_
A16: 1980_ | B16: Trigger Explosion | C16: Kích Nổ Vụ Nổ | D16: 誘爆
A17: 1980.001_
A18: 1981_ | B18: Trigger Explosion | C18: Kích Nổ Vụ Nổ | D18: 誘爆
A19: 1981.001_
A20: 1982_ | B20: Bushy Bond | C20: Liên Kết Đáng Yêu | D20: 共鳴
A21: 1982.001_
A22: 1983_ | B22: Thunderclap | C22: Tiếng Sét Đánh | D22: 迅雷
A23: 1983.001_
A24: 1984_ | B24: Thunderstorm | C24: Bão Sấm Sét | D24: 轟雷
A25: 1984.001_
A26: 1985_ | B26: Bushy Bond | C26: Liên Kết Đáng Yêu | D26: 共鳴
A27: 1985.001_
A28: 1986_ | B28: Feed | C28: Nuôi Ăn | D28: 捕食
A29: 1986.001_
A30: 1987_ | B30: Feed | C30: Nuôi Ăn | D30: 捕食
A31: 1987.001_
A32: 1988_ | B32: Feed | C32: Nuôi Ăn | D32: 捕食
A33: 1988.001_
A34: 1989_ | B34: Feed | C34: Nuôi Ăn | D34: 捕食
A35: 1989.001_
A36: 1990_ | B36: Pengy Fusion | C36: Hợp Thể Pengy | D36: ペンギィ合体
A37: 1990.001_
A38: 1991_ | B38: Hoppy Fusion | C38: Hợp Thể Hoppy | D38: イワトビィ合体
A39: 1991.001_
A40: 1992_ | B40: Empy Fusion | C40: Hợp Thể Empy | D40: コウティ合体
A41: 1992.001_
A42: 1993_ | B42: Delta Attack | C42: Đòn Đánh Tam Giác Delta | D42: デルタアタック
A43: 1993.001_
A44: 1994_ | B44: Rocket Rush | C44: Tên Lửa Vút Bay | D44: ロケットラッシュ
A45: 1994.001_
A46: 1995_ | B46: Rocket Rush | C46: Tên Lửa Vút Bay | D46: ロケットラッシュ
A47: 1995.001_
A48: 1996_ | B48: Rocket Rush | C48: Tên Lửa Vút Bay | D48: ロケットラッシュ
A49: 1996.001_
A50: 1997_ | B50: Rocket Rush | C50: Tên Lửa Vút Bay | D50: ロケットラッシュ
A51: 1997.001_
A52: 1998_ | B52: Rocket Rush | C52: Tên Lửa Vút Bay | D52: ロケットラッシュ
A53: 1998.001_
A54: 1999_ | B54: Rocket Rush | C54: Tên Lửa Vút Bay | D54: ロケットラッシュ
A55: 1999.001_
A56: 2000_ | B56: Rocket Rush | C56: Tên Lửa Vút Bay | D56: ロケットラッシュ
A57: 2000.001_
A58: 2001_ | B58: Bushy Bond | C58: Liên Kết Đáng Yêu | D58: 共鳴
A59: 2001.001_
A60: 2002_ | B60: Bushy Bond | C60: Liên Kết Đáng Yêu | D60: 共鳴
A61: 2002.001_
A62: 2003_ | B62: Bushy Bond | C62: Liên Kết Đáng Yêu | D62: 共鳴
A63: 2003.001_
A64: 2004_ | B64: Bushy Bond | C64: Liên Kết Đáng Yêu | D64: 共鳴
A65: 2004.001_
A66: 2005_ | B66: Bushy Bond | C66: Liên Kết Đáng Yêu | D66: 共鳴
A67: 2005.001_
A68: 2006_ | B68: Thunderclap | C68: Tiếng Sét Đánh | D68: 迅雷
A69: 2006.001_
A70: 2007_ | B70: Thunderclap | C70: Tiếng Sét Đánh | D70: 迅雷
A71: 2007.001_
A72: 2008_ | B72: Thunderstorm | C72: Bão Sấm Sét | D72: 轟雷
A73: 2008.001_
A74: 2009_ | B74: Thunderclap | C74: Tiếng Sét Đánh | D74: 迅雷
A75: 2009.001_
A76: 2010_ | B76: Thunderstorm | C76: Bão Sấm Sét | D76: 轟雷
A77: 2010.001_
A78: 2011_ | B78: Thunderclap | C78: Tiếng Sét Đánh | D78: 迅雷
A79: 2011.001_
A80: 2012_ | B80: Heavenly Wrath | C80: Cơn Thịnh Nộ Thiên Đường | D80: 天罰
A81: 2012.001_

Sheet EnemySetParameterMessage
A1: ID | B1: English | C1: Vietnamese | D1: Note
A2: 2013.001_ | B2: 2 | D2: 2
A3: 2014_ | B3: True | D3: True
A4: 2014.001_ | B4: 1 | D4: 1
A5: 2015_ | B5: 102 | D5: 102
A6: 2016_ | B6: Pengy | C6: Pengy | D6: ペンギィ
A7: 2016.001_
A8: 2017_ | B8: Hoppy | C8: Hoppy | D8: イワトビィ
A9: 2017.001_
A10: 2018_ | B10: Empy | C10: Empy | D10: コウティ
A11: 2018.001_
A12: 2019_ | B12: Rocky | C12: Rocky | D12: ホウセキィ
A13: 2019.001_
A14: 2020_ | B14: Scarly | C14: Scarly | D14: ベスィ
A15: 2020.001_
A16: 2021_ | B16: Hoot-Hoot | C16: Hoot-Hoot | D16: ハクホウ
A17: 2021.001_
A18: 2022_ | B18: Toot-Hoot | C18: Toot-Hoot | D18: メンホウ
A19: 2022.001_
A20: 2023_ | B20: Woot-Hoot | C20: Woot-Hoot | D20: コクホウ
A21: 2023.001_
A22: 2024_ | B22: Zoot-Hoot | C22: Zoot-Hoot | D22: ホウホウ
A23: 2024.001_
A24: 2025_ | B24: White Flapper | C24: Flapper Trắng | D24: シロバッサ
A25: 2025.001_
A26: 2026_ | B26: Black Flapper | C26: Flapper Đen | D26: クロバッサ
A27: 2026.001_
A28: 2027_ | B28: Rainbow Flapper | C28: Flapper Cầu Vồng | D28: ニジバッサ
A29: 2027.001_
A30: 2028_ | B30: Stone Flapper | C30: Flapper Đá | D30: イシバッサ
A31: 2028.001_
A32: 2029_ | B32: Skullian | C32: Skullian | D32: ドクロリアン
A33: 2029.001_
A34: 2030_ | B34: Spikoon | C34: Spikoon | D34: スパイクーン
A35: 2030.001_
A36: 2031_ | B36: Armonite | C36: Armonite | D36: アーモナイト
A37: 2031.001_
A38: 2032_ | B38: Fallout Shell | C38: Ốc Phóng Xạ | D38: シェルーター
A39: 2032.001_
A40: 2033_ | B40: Poison Puff-Puff | C40: Puff-Puff Độc | D40: ドクボーン
A41: 2033.001_
A42: 2034_ | B42: Prickly Puff-Puff | C42: Puff-Puff Gai | D42: チクボーン
A43: 2034.001_
A44: 2035_ | B44: Fiery Puff-Puff | C44: Puff-Puff Lửa | D44: メラボーン
A45: 2035.001_
A46: 2036_ | B46: Atomic Puff-Puff | C46: Puff-Puff Nguyên Tử | D46: ピカボーン
A47: 2036.001_
A48: 2037_ | B48: Waloompa | C48: Waloompa | D48: ズシシーン
A49: 2037.001_
A50: 2038_ | B50: Baloompa | C50: Baloompa | D50: ビシシーン
A51: 2038.001_
A52: 2039_ | B52: Galoompa | C52: Galoompa | D52: ガシシーン
A53: 2039.001_
A54: 2040_ | B54: Maloompa | C54: Maloompa | D54: ドシシーン
A55: 2040.001_
A56: 2041_ | B56: Muffy | C56: Muffy | D56: ミミィ
A57: 2041.001_
A58: 2042_ | B58: Chocolly | C58: Chocolly | D58: チョコン
A59: 2042.001_
A60: 2043_ | B60: Sherbetty | C60: Sherbetty | D60: シャベット
A61: 2043.001_
A62: 2044_ | B62: Jewelly | C62: Jewelly | D62: ジュエルルー
A63: 2044.001_
A64: 2045_ | B64: Versa | C64: Versa | D64: バーバ
A65: 2045.001_
A66: 2046_ | B66: Vulpara | C66: Vulpara | D66: フォクンバ
A67: 2046.001_
A68: 2047_ | B68: Lupara | C68: Lupara | D68: ウルルンバ
A69: 2047.001_
A70: 2048_ | B70: Silvara | C70: Silvara | D70: シルバンバ
A71: 2048.001_
A72: 2049_ | B72: Snecter | C72: Snecter | D72: スネクター
A73: 2049.001_
A74: 2050_ | B74: Boa Tigris | C74: Trăn Hổ | D74: コブライガー
A75: 2050.001_
A76: 2051_ | B76: Hellviper | C76: Rắn Địa Ngục | D76: ヘルバイバー
A77: 2051.001_
A78: 2052_ | B78: Magiconda | C78: Trăn Ma Thuật | D78: ジュエルコンダ
A79: 2052.001_
A80: 2053_ | B80: Roly-Poly | C80: Roly-Poly | D80: コロリン
A81: 2053.001_
A82: 2054_ | B82: Bowly-Poly | C82: Bowly-Poly | D82: コロロリン
A83: 2054.001_
A84: 2055_ | B84: Snowly-Poly | C84: Snowly-Poly | D84: コロコロリン
A85: 2055.001_
A86: 2056_ | B86: Glowly-Poly | C86: Glowly-Poly | D86: キラリン
A87: 2056.001_
A88: 2057_ | B88: Shroomback | C88: Nấm Lưng Gai | D88: キノコング
A89: 2057.001_
A90: 2058_ | B90: Mountain Shroomback | C90: Nấm Lưng Núi | D90: シメジン
A91: 2058.001_
A92: 2059_ | B92: Cave Shroomback | C92: Nấm Lưng Hang | D92: エノキング
A93: 2059.001_
A94: 2060_ | B94: Crystal Shroomback | C94: Nấm Lưng Pha Lê | D94: ホウセキノコング
A95: 2060.001_
A96: 2061_ | B96: Jaboo | C96: Jaboo | D96: ジャブー
A97: 2061.001_
A98: 2062_ | B98: Uppa | C98: Uppa | D98: アッパ
A99: 2062.001_
A100: 2063_ | B100: Hookee | C100: Hookee | D100: ストレー
...

Sheet EnemySkillDataMessage
A1: ID | B1: English | C1: Vietnamese | D1: Note
A2: 2118.001_ | B2: 2 | D2: 2
A3: 2119_ | B3: True | D3: True
A4: 2119.001_ | B4: 1 | D4: 1
A5: 2120_ | B5: 88 | D5: 88
A6: 2121_ | B6: Test Attack | C6: Đòn Đánh Thử Nghiệm | D6: 試作たたかう
A7: 2122_ | B7: Regular Attack | C7: Đòn Đánh Thường | D7: 普通の攻撃
A8: 2123_ | B8: Dive | C8: Lao Xuống | D8: ダイブ
A9: 2123.001_
A10: 2124_ | B10: Rocket Dive | C10: Lao Tên Lửa | D10: ロケットダイブ
A11: 2124.001_
A12: 2125_ | B12: Slap | C12: Vả | D12: ビンタ
A13: 2125.001_
A14: 2126_ | B14: Bite | C14: Cắn | D14: かじる
A15: 2126.001_
A16: 2127_ | B16: Focus | C16: Tập Trung | D16: ためる
A17: 2127.001_
A18: 2128_ | B18: Swoop | C18: Sà Xuống | D18: 急降下
A19: 2128.001_
A20: 2129_ | B20: Wingbeat | C20: Đập Cánh | D20: はばたき
A21: 2129.001_
A22: 2130_ | B22: Flee | C22: Bỏ Chạy | D22: 飛び去る
A23: 2130.001_
A24: 2131_ | B24: Blinding Gaze | C24: Ánh Nhìn Mù Lòa | D24: スタン眼
A25: 2131.001_
A26: 2132_ | B26: Petrifying Gaze | C26: Ánh Nhìn Hóa Đá | D26: 石化眼
A27: 2132.001_
A28: 2133_ | B28: Paralyzing Gaze | C28: Ánh Nhìn Tê Liệt | D28: 麻痺眼
A29: 2133.001_
A30: 2134_ | B30: Cure | C30: Trị Liệu | D30: ケアル
A31: 2134.001_
A32: 2135_ | B32: Healing Feather | C32: Lông Vũ Trị Thương | D32: 癒しの羽根
A33: 2135.001_
A34: 2136_ | B34: Whirlwind | C34: Lốc Xoáy | D34: つむじ風
A35: 2136.001_
A36: 2137_ | B36: Hurricane | C36: Cuồng Phong | D36: 竜巻
A37: 2137.001_
A38: 2138_ | B38: Glide Attack | C38: Lướt Tấn Công | D38: グライダー
A39: 2138.001_
A40: 2139_ | B40: Shell Shield | C40: Mai Rùa Hộ Thuẫn | D40: シェルガード
A41: 2139.001_
A42: 2140_ | B42: Accumulate Power | C42: Tụ Lực | D42: パワー集中
A43: 2140.001_
A44: 2141_ | B44: Poison Claw | C44: Vuốt Độc | D44: ポイズンクロー
A45: 2141.001_
A46: 2142_ | B46: Shell Boomerang | C46: Mai Rùa Boomerang | D46: 貝殻ブーメラン
A47: 2142.001_
A48: 2143_ | B48: Tackle | C48: Húc | D48: タックル
A49: 2143.001_
A50: 2144_ | B50: Self-Destruct | C50: Tự Phát Nổ | D50: 自爆
A51: 2144.001_
A52: 2145_ | B52: Roll Over | C52: Lăn Tròn | D52: 転げまわる
A53: 2145.001_
A54: 2146_ | B54: Groundrush | C54: Lao Đất | D54: 地擦り残月
A55: 2146.001_
A56: 2147_ | B56: Poisonous Breath | C56: Hơi Thở Độc Tố | D56: ポイズンブレス
A57: 2147.001_
A58: 2148_ | B58: Spin Attack | C58: Xoay Người Tấn Công | D58: スピンアタック
A59: 2148.001_
A60: 2149_ | B60: Roar | C60: Gầm Rú | D60: 雄叫び
A61: 2149.001_
A62: 2150_ | B62: Super Slap | C62: Siêu Vả | D62: スーパービンタ
A63: 2150.001_
A64: 2151_ | B64: Tremor | C64: Rung Chấn | D64: 地鳴り
A65: 2151.001_
A66: 2152_ | B66: Counterslap | C66: Vả Phản Đòn | D66: リベンジビンタ
A67: 2152.001_
A68: 2153_ | B68: Earthquake | C68: Động Đất | D68: 大地震
A69: 2153.001_
A70: 2154_ | B70: Gnaw | C70: Gặm Nhấm | D70: かみつく
A71: 2154.001_
A72: 2155_ | B72: Fire | C72: Hỏa Cầu | D72: ファイア
A73: 2155.001_
A74: 2156_ | B74: Lightning | C74: Tia Sét | D74: サンダー
A75: 2156.001_
A76: 2157_ | B76: Ice | C76: Băng Cầu | D76: アイス
A77: 2157.001_
A78: 2158_ | B78: Slap | C78: Vả | D78: ビンタ
A79: 2158.001_
A80: 2159_ | B80: Triple Slap | C80: Tam Liên Vả | D80: 往復ビンタ
A81: 2159.001_
A82: 2160_ | B82: Snowdust | C82: Bụi Tuyết | D82: スノーダスト
A83: 2160.001_
A84: 2161_ | B84: Freezing Gaze | C84: Ánh Nhìn Băng Giá | D84: フリーズアイ
A85: 2161.001_
A86: 2162_ | B86: Ice | C86: Băng Cầu | D86: アイス
A87: 2162.001_
A88: 2163_ | B88: Powder Cloud | C88: Mây Bụi | D88: パウダー
A89: 2163.001_
A90: 2164_ | B90: Burning Bite | C90: Cắn Cháy Bỏng | D90: ヒートバイト
A91: 2164.001_
A92: 2165_ | B92: Frosty Bite | C92: Cắn Băng Giá | D92: アイスバイト
A93: 2165.001_
A94: 2166_ | B94: Burning Breath | C94: Hơi Thở Rực Cháy | D94: ヒートブレス
A95: 2166.001_
A96: 2167_ | B96: Frosty Breath | C96: Hơi Thở Băng Giá | D96: アイスブレス
A97: 2167.001_
A98: 2168_ | B98: Soul Breath | C98: Hơi Thở Linh Hồn | D98: ソウルブレス
A99: 2168.001_
A100: 2169_ | B100: Snowball Throw | C100: Ném Cầu Tuyết | D100: 雪つぶて
...

Sheet GrimreaperSkillDataMessage
A1: ID | B1: English | C1: Vietnamese | D1: Note
A2: 2272.001_ | B2: 2 | D2: 2
A3: 2273_ | B3: True | D3: True
A4: 2273.001_ | B4: 0 | D4: 0
A5: 2274_ | B5: 17 | D5: 17
A6: 2275_ | B6: Attack | C6: Tấn Công | D6: たたかう
A7: 2275.001_
A8: 2276_ | B8: Helix Slash | C8: Xoáy Tử Thần | D8: 螺旋斬り
A9: 2277_ | B9: Utilizes the scythe's range to its maximum potential, causing special damage [Null/2 hits] to all enemies near the user. | C9: Tận dụng tối đa tầm quét của lưỡi hái, gây sát thương đặc biệt [Vô hệ/2 đòn] lên toàn bộ kẻ địch gần bản thân. | D9: 大鎌の射程を最大限に生かした 特殊攻撃［無/2ヒット］が使用者中心に発生する。
A10: 2278_ | B10: Dark Mist | C10: Hắc Vụ | D10: ダーク
A11: 2279_ | B11: Uses magical energy to amplify the user's dark power, causing magical damage [Shadow] to all enemies near the target. | C11: Dùng ma lực khuếch đại sức mạnh bóng tối, gây sát thương ma thuật [Hắc Ám] lên toàn bộ kẻ địch gần mục tiêu. | D11: 暗黒の力を魔力によって増幅し 魔法攻撃［冥］が対象中心に発生する。
A12: 2280_ | B12: Cursed Slash | C12: Nguyền Trảm | D12: 呪詛斬り
A13: 2281_ | B13: Causes physical damage [Shadow] to all enemies near the user. Can also inflict Sap. | C13: Gây sát thương vật lý [Hắc Ám] lên toàn bộ kẻ địch gần bản thân. Có tỉ lệ gây trạng thái Suy Kiệt. | D13: 物理攻撃［冥］が対象中心に発生する。 スリップが発生することもある。
A14: 2282_ | B14: Endark | C14: Ban Hắc | D14: エンダーク
A15: 2283_ | B15: Adds the Shadow element to the attacks of all allies near the target. Shadow-elemental attacks will also cause more damage. | C15: Thêm nguyên tố Hắc Ám vào đòn đánh của đồng minh gần mục tiêu. Các đòn đánh hệ Hắc Ám cũng sẽ gây thêm nhiều sát thương. | D15: 冥属性付与が対象中心に発生する。 効果中に冥属性攻撃を行うと、威力が大きくなる。
A16: 2284_ | B16: Earthsplitter | C16: Phá Địa Trảm | D16: 大地断
A17: 2285_ | B17: Energy flows from the scythe and rends the earth, causing physical damage [Null] to all enemies near the target. | C17: Năng lượng tuôn trào từ lưỡi hái xé toạc mặt đất, gây sát thương vật lý [Vô hệ] lên toàn bộ kẻ địch gần mục tiêu. | D17: 大鎌から流れ込む魔力で大地を割り 物理攻撃［無］が対象中心に発生する。
A18: 2286_ | B18: Hellfire | C18: Ngục Hỏa | D18: 瞬獄
A19: 2287_ | B19: Attacks from behind, causing physical damage [Shadow] to all enemies near the target. Can also inflict Death. | C19: Tập kích từ phía sau, gây sát thương vật lý [Hắc Ám] lên kẻ địch gần mục tiêu. Có tỉ lệ gây Tử Vong tức thì. | D19: 敵の背後から物理攻撃［冥］が対象中心に発生する。 即死が発生することもある。
... A39: 2307_ | B39: Causes special damage [Null] to all enemies near the target. Inflicts more damage the higher the Unused Momentum counter is. | C39: Gây sát thương đặc biệt [Vô hệ] lên kẻ địch gần mục tiêu. Càng có nhiều điểm Xung Lực chưa sử dụng, sát thương càng khủng khiếp. | D39: 刹那未使用回数が多いほど威力が大きくなる 特殊攻撃［無］が対象中心に発生する。

Sheet IntensifyMessage
A1: ID | B1: English | C1: Vietnamese | D1: Note
A2: 2307.001_ | B2: 2 | D2: 2
A3: 2308_ | B3: True | D3: True
A4: 2308.001_ | B4: 0 | D4: 0
A5: 2308.002_ | B5: 4 | D5: 4
A6: 2309_ | B6: Mythril | D6: ミスリル
A7: 2310_ | B7: This item can be used to strengthen weapons, raising attack and defense power. It can strengthen a weapon to roughly 1/4 of its maximum stats. | D7: 武器を強化することができる。 強化することで攻撃力と防御力が上昇する。 武器の限界値の約1/4まで強化できる。
A8: 2311_ | B8: Damascus | D8: ダマスカス
A9: 2312_ | B9: This item can be used to strengthen weapons, raising attack and defense power. It can strengthen a weapon to roughly 1/2 of its maximum stats. | D9: 武器を強化することができる。 強化することで攻撃力と防御力が上昇する。 武器の限界値の約1/2まで強化できる。
A10: 2313_ | B10: Crystal | D10: クリスタル
A11: 2314_ | B11: This item can be used to strengthen weapons, raising attack and defense power. It can strengthen a weapon to roughly 3/4 of its maximum stats. | D11: 武器を強化することができる。 強化することで攻撃力と防御力が上昇する。 武器の限界値の約3/4まで強化できる。
A12: 2315_ | B12: Orichalcum | D12: オリハルコン
A13: 2316_ | B13: This item can be used to strengthen weapons, raising attack and defense power. It can strengthen a weapon to its maximum stats. | D13: 武器を強化することができる。 強化することで攻撃力と防御力が上昇する。 武器の限界値まで強化できる。

Sheet ItemSkillDataMessage
A1: ID | B1: English | C1: Vietnamese | D1: Note
A2: 2316.001_ | B2: 2 | D2: 2
A3: 2317_ | B3: True | D3: True
A4: 2317.001_ | B4: 0 | D4: 0
A5: 2317.002_ | B5: 3 | D5: 3
A6: 2318_ | B6: Potion | C6: Thuốc Hồi Máu | D6: ポーション
A7: 2319_ | B7: Recovers 50 HP. | C7: Hồi 50 HP | D7: 体力を50回復する。
A8: 2320_ | B8: Hi-Potion | C8: Thuốc Hồi Máu - Cao | D8: ハイポーション
A9: 2321_ | B9: Recovers 200 HP. | C9: Hồi 200 HP | D9: 体力を200回復する。
A10: 2322_ | B10: Mega-Potion | C10: WOW Hồi Máu | D10: メガポーション
A11: 2323_ | B11: Recovers 500 HP. | C11: Hồi 500 HP | D11: 体力を500回復する。

Sheet KishilSkillDataMessage
A1: ID | B1: English | C1: Vietnamese | D1: Note
A2: 2323.001_ | B2: 2 | D2: 2
A3: 2324_ | B3: True | D3: True
A4: 2324.001_ | B4: 0 | D4: 0
A5: 2325_ | B5: 17 | D5: 17
A6: 2326_ | B6: Attack | C6: Tấn Công | D6: たたかう
A7: 2326.001_
A8: 2327_ | B8: Fire | C8: Hỏa Cầu | D8: ファイア
A9: 2328_ | B9: Shapes magical energy into flames that cause magical damage [Fire] to all enemies near the target. | C9: Ngưng tụ ma lực thành ngọn lửa, gây sát thương ma thuật [Hỏa] lên toàn bộ kẻ địch gần mục tiêu. | D9: 練りあげた魔力を火炎に変換して 魔法攻撃［火］が対象中心に発生する。
A10: 2329_ | B10: Drain | C10: Hút Máu | D10: ドレイン
A11: 2330_ | B11: Causes magical damage [Null] to all enemies near the target, and absorbs 100% of inflicted damage as HP. | C11: Gây sát thương ma thuật [Vô hệ] lên kẻ địch gần mục tiêu, và hấp thụ 100% sát thương gây ra thành HP. | D11: 魔法攻撃［無］が対象中心に発生する。 与えたダメージの100%を使用者がHP吸収する。
A12: 2331_ | B12: Enflame | C12: Ban Hỏa | D12: エンファイア
A13: 2332_ | B13: Adds the Fire element to the attacks of all allies in the area near the target. Fire-elemental attacks will also cause more damage. | C13: Thêm nguyên tố Hỏa vào đòn đánh của đồng minh gần mục tiêu. Các đòn tấn công hệ Hỏa cũng sẽ gây thêm nhiều sát thương. | D13: 火属性付与が対象中心に発生する。 効果中に火属性攻撃を行うと、威力が大きくなる。
A14: 2333_ | B14: Dispel | C14: Hóa Giải | D14: ディスペル
A15: 2334_ | B15: Causes magical damage [Null] to all enemies near the target. Also cancels all status boosts. | C15: Gây sát thương ma thuật [Vô hệ] lên toàn bộ kẻ địch gần mục tiêu. Đồng thời xóa bỏ toàn bộ hiệu ứng tăng chỉ số của chúng. | D15: 魔法攻撃［無］が対象中心に発生する。 全ての状態強化を解除する効果もある。
A16: 2335_ | B16: Magma | C16: Nham Thạch | D16: マグマ
A17: 2336_ | B17: Channels the earth's rage, releasing a torrent of lava that causes magical damage [Fire/4 hits] to all enemies near the target. | C17: Dẫn truyền cơn thịnh nộ của đất mẹ, phóng dòng dung nham gây sát thương ma thuật [Hỏa/4 đòn] lên kẻ địch gần mục tiêu. | D17: 大地の怒りを感じとり、溶岩の奔流を放出する 魔法攻撃［火/4ヒット］が対象中心に発生する
A18: 2337_ | B18: Regen | C18: Hồi Phục | D18: リジェネ
A19: 2338_ | B19: Casts Restore on all allies near the target. While in this state, HP is recovered automatically. | C19: Niệm Hồi Phục lên toàn bộ đồng minh gần mục tiêu. Khi ở trạng thái này, HP sẽ tự động hồi phục liên tục. | D19: 再生が対象中心に発生する。 再生になるとHPが自動で回復するようになる。
... A39: 2358_ | B39: Causes special damage [Null] to all enemies and allies. Inflicts more damage the more allies are knocked out. | C39: Gây sát thương đặc biệt [Vô hệ] lên toàn bộ kẻ địch và đồng minh. Càng có nhiều đồng minh bị hạ gục, sát thương gây ra càng khủng khiếp. | D39: 戦闘不能数が多いほど威力が大きくなる 特殊攻撃［無］が敵・味方全体に発生する。

Sheet MaterialItemMessage
A1: ID | B1: English | C1: Vietnamese | D1: Note
A2: 2358.001_ | B2: 2 | D2: 2
A3: 2359_ | B3: True | D3: True
A4: 2359.001_ | B4: 0 | D4: 0
A5: 2360_ | B5: 407 | D5: 407
A6: 2361_ | B6: Majestic Crest | C6: Majestic Crest | D6: りりしいトサカ
A7: 2362_ | B7: A material dropped by members of the Pengy species. | C7: Nguyên liệu rơi ra từ members of the Pengy species. | D7: ペンギィ系モンスターからドロップする素材。
A8: 2363_ | B8: Round Stone | C8: Round Stone | D8: まるい石
A9: 2364_ | B9: A material dropped by members of the Pengy species. | C9: Nguyên liệu rơi ra từ members of the Pengy species. | D9: ペンギィ系モンスターからドロップする素材。
A10: 2365_ | B10: Sturdy Sheet Metal | C10: Sturdy Sheet Metal | D10: 厚い板金
A11: 2366_ | B11: A material dropped by members of the Pengy species. | C11: Nguyên liệu rơi ra từ members of the Pengy species. | D11: ペンギィ系モンスターからドロップする素材。
A12: 2367_ | B12: Miniature Cherry Branch | C12: Miniature Cherry Branch | D12: イチネンサクラの枝
A13: 2368_ | B13: A material dropped by members of the Pengy species. | C13: Nguyên liệu rơi ra từ members of the Pengy species. | D13: ペンギィ系モンスターからドロップする素材。
A14: 2369_ | B14: Miniature Cherry Blossom | C14: Miniature Cherry Blossom | D14: イチネンサクラの花
A15: 2370_ | B15: A material dropped by members of the Pengy species. | C15: Nguyên liệu rơi ra từ members of the Pengy species. | D15: ペンギィ系モンスターからドロップする素材。
A16: 2371_ | B16: Miniature Cherry Root | C16: Miniature Cherry Root | D16: イチネンサクラの根
A17: 2372_ | B17: A material dropped by members of the Pengy species. | C17: Nguyên liệu rơi ra từ members of the Pengy species. | D17: ペンギィ系モンスターからドロップする素材。
... A819: 3174_ | B819: A relic found on the Remote Islands. | C819: A relic found on the Remote Islands. | D819: 絶海群島で採取できる遺物。

Sheet MateriaMessage
A1: ID | B1: English | C1: Vietnamese | D1: Note
A2: 3174.001_ | B2: 2 | C2: 2 | D2: 2
A3: 3175_ | B3: True | C3: True | D3: True
A4: 3175.001_ | B4: 0 | C4: 0 | D4: 0
A5: 3176_ | B5: 218 | C5: 218 | D5: 218
A6: 3177_ | B6: Cyclone | C6: Cuồng Phong | D6: 回転斬り
A7: 3178_ | B7: Enables use of Cyclone. Offers a wide attack range, and can also knock back enemies. Causes physical damage [Null] to all enemies near the user. | C7: Trang bị để sử dụng kỹ năng Cuồng Phong. Đòn tấn công phạm vi rộng, có thể đẩy lùi kẻ địch. Gây sát thương vật lý [Vô hệ] lên mọi kẻ địch quanh bản thân. | D7: 戦闘で回転斬りが使用できるようになる。 広範囲に攻撃できるうえに、敵を吹っ飛ばせる 物理攻撃［無］が使用者中心に発生する。
A8: 3178.001_
A9: 3178.002_
A10: 3179_ | B10: Aura | C10: Hào Quang | D10: オーラ
A11: 3180_ | B11: Enables use of Aura. Healing energy recovers the HP of all allies near the target. Also heals status ailments when used in Momentum mode. | C11: Trang bị để sử dụng kỹ năng Hào Quang. Năng lượng trị thương hồi phục HP cho toàn bộ đồng minh gần mục tiêu. Giải trừ trạng thái bất lợi khi dùng ở chế độ Xung Lực. | D11: 戦闘でオーラが使用できるようになる。 癒しの魔力で、HP回復が対象中心に発生する。 刹那を発動すると、状態異常解除も発生する。
A12: 3180.001_
A13: 3180.002_
A14: 3181_ | B14: Shock | C14: Chấn Động | D14: ショック
A15: 3182_ | B15: Enables use of Shock. Unleashes a blast of concentrated magical energy, causing physical damage [Null] to all enemies near the target. | C15: Trang bị để sử dụng kỹ năng Chấn Động. Giải phóng chùm ma lực tập trung, gây sát thương ma thuật [Vô hệ] lên toàn bộ kẻ địch gần mục tiêu. | D15: 戦闘でショックが使用できるようになる。 圧縮した魔力を暴発させることにより 魔法攻撃［無］が対象中心に発生する。
A16: 3182.001_
A17: 3182.002_
A18: 3183_ | B18: Wall | C18: Bức Tường | D18: ウォール
A19: 3184_ | B19: Enables use of Wall. Deploys a wall of magical energy around a single target that defends against both physical and magical attacks. | C19: Trang bị để sử dụng kỹ năng Bức Tường. Dựng bức tường ma thuật quanh một mục tiêu, chống đỡ cả đòn tấn công vật lý lẫn ma thuật. | D19: 戦闘でウォールが使用できるようになる。 魔力の障壁を展開し、敵の攻撃を防いでくれる 物理盾と魔法盾が対象単体に発生する。
A20: 3184.001_
A21: 3184.002_
A22: 3185_ | B22: Blade Wave | C22: Kiếm Khí | D22: 無刃波
A23: 3186_ | B23: Enables use of Blade Wave. Fires an energy blade that causes physical damage [Null] to all enemies in a line from the user. | C23: Trang bị để sử dụng kỹ năng Kiếm Khí. Phóng ra lưỡi kiếm năng lượng gây sát thương vật lý [Vô hệ] lên toàn bộ kẻ địch trên đường thẳng. | D23: 戦闘で無刃波が使用できるようになる。 闘気の刃を敵に向けて飛ばすことで 物理攻撃［無］が使用者前方に発生する。
A24: 3186.001_
A25: 3186.002_
A26: 3187_ | B26: Backslash | C26: Tập Kích | D26: 影斬り
A27: 3188_ | B27: Enables use of Backslash. Darts behind foes, catching them off guard. Causes physical damage [Null] to all enemies near the target. | C27: Trang bị để sử dụng kỹ năng Tập Kích. Lướt ra sau lưng kẻ địch trong chớp mắt, đánh úp bất ngờ. Gây sát thương vật lý [Vô hệ] lên toàn bộ kẻ địch gần mục tiêu. | D27: 戦闘で影斬りが使用できるようになる。 敵の虚を突いて、一瞬に敵の背後に回り込み 物理攻撃［無］が対象中心に発生する。
A28: 3188.001_
A29: 3188.002_
A30: 3189_ | B30: Radiance | C30: Quang Mang | D30: 輝跡
A31: 3190_ | B31: Enables use of Radiance. Creates a blast that causes special damage [Null/4 hits] to all enemies near the target. | C31: Trang bị để sử dụng kỹ năng Quang Mang. Kết hợp năng lượng vật lý và ma thuật tạo vụ nổ gây sát thương đặc biệt [Vô hệ/4 đòn] lên kẻ địch gần mục tiêu. | D31: 戦闘で輝跡が使用できるようになる。 闘気と魔力を練り合わせて作った衝撃によって 特殊攻撃［無/4HIT］が対象中心に発生する。
A32: 3190.001_
A33: 3190.002_
A34: 3191_ | B34: Magen | C34: Ma Nguyên | D34: マジェネ
A35: 3192_ | B35: Enables use of Magen. Casts Concentration on all allies near the target. While in this state, MP is recovered automatically. | C35: Trang bị để sử dụng kỹ năng Ma Nguyên. Niệm Tập Trung lên toàn bộ đồng minh gần mục tiêu. Khi ở trạng thái này, MP sẽ tự động hồi phục. | D35: 戦闘でマジェネが使用できるようになる。 集中が対象中心に発生する。 集中になるとMPが自動で回復するようになる。
A36: 3192.001_
A37: 3192.002_
A38: 3193_ | B38: Life | C38: Hồi Sinh | D38: レイズ
A39: 3194_ | B39: Enables use of Life. The power of salvation revives all allies near the target. Also recovers HP, even if the ally is not knocked out. | C39: Trang bị để sử dụng kỹ năng Hồi Sinh. Sức mạnh cứu rỗi hồi sinh đồng minh gần mục tiêu. Đồng thời hồi phục HP kể cả khi đồng minh chưa bị hạ gục. | D39: 戦闘でレイズが使用できるようになる。 慈悲の力でHP回復と蘇生が対象中心に発生する。 戦闘不能でなくても回復することができる。
A40: 3194.001_
A41: 3194.002_
A42: 3195_ | B42: Cleave | C42: Trảm Kích | D42: 全力斬り
A43: 3196_ | B43: Enables use of Cleave. Unleashes full power at the exact moment of impact, causing physical damage [Null] to all enemies near the target. | C43: Trang bị để sử dụng kỹ năng Trảm Kích. Giải phóng toàn bộ sức mạnh vào đúng khoảnh khắc va chạm, gây sát thương vật lý [Vô hệ] lên toàn bộ kẻ địch gần mục tiêu. | D43: 戦闘で全力斬りが使用できるようになる。 全ての力を攻撃する一瞬に爆発させる 物理攻撃［無］が対象中心に発生する。
A44: 3196.001_
A45: 3196.002_
A46: 3197_ | B46: Realization | C46: Giác Ngộ | D46: リアラズ
A47: 3198_ | B47: Enables use of Realization. Instantly fills the SP gauges of all allies near the target, and increases the rate at which they accumulate SP. | C47: Trang bị để sử dụng kỹ năng Giác Ngộ. Lập tức làm đầy thanh SP của toàn bộ đồng minh gần mục tiêu, và tăng tốc độ tích lũy SP của họ. | D47: 戦闘でリアラズが使用できるようになる。 SP上昇とSP強制蓄積が対象中心に発生する。 SPがたまりやすくなり、さらにSPが一気に蓄積する。
A48: 3198.001_
A49: 3198.002_
A50: 3199_ | B50: Spark | C50: Tia Lửa | D50: 天閃
A51: 3200_ | B51: Enables use of Spark. Causes physical damage [Null] to all enemies near the target. The higher SP is, the more damage. Also accumulates a lot of SP. | C51: Trang bị để sử dụng kỹ năng Tia Lửa. Gây sát thương vật lý [Vô hệ] lên kẻ địch gần mục tiêu. Sát thương càng cao khi SP càng nhiều, và tích lũy lượng lớn SP. | D51: 戦闘で天閃が使用できるようになる。 SPがたまりやすく、SPが高いほど威力大きくなる 物理攻撃［無］が対象中心に発生する。
A52: 3200.001_
A53: 3200.002_
A54: 3201_ | B54: Battlecry | C54: Chiến Hống | D54: 叫ぶ
A55: 3202_ | B55: Enables use of Battlecry. Boosts the Attack, Defense, and speed of all allies. Effect only lasts for one turn, but gives a large boost to each stat. | C55: Trang bị để sử dụng kỹ năng Chiến Hống. Tăng mạnh Tấn Công, Phòng Thủ và tốc độ ATB của toàn đội. Hiệu ứng chỉ duy trì 1 lượt nhưng tăng chỉ số cực lớn. | D55: 戦闘で叫ぶが使用できるようになる。 攻撃・防御・速度の能力上昇が味方全体に発生する。 1ターン限定ながら、上昇値は極めて大きい。
A56: 3202.001_
A57: 3202.002_
A58: 3203_ | B58: Meteo | C58: Thiên Thạch | D58: メテオ
A59: 3204_ | B59: Enables use of Meteo. Summons a meteor shower that causes magical damage [Null] to all enemies, ignoring 50% of Defense. | C59: Trang bị để sử dụng kỹ năng Thiên Thạch. Triệu hồi mưa thiên thạch gây sát thương ma thuật [Vô hệ] lên toàn bộ kẻ địch, bỏ qua 50% Phòng Thủ. | D59: 戦闘でメテオが使用できるようになる。 天から流星を降りそそぎ、防御を50%無視する 魔法攻撃［無］が敵全体に発生する。
A60: 3204.001_
A61: 3204.002_
A62: 3205_ | B62: Quick | C62: Tăng Tốc | D62: クイック
A63: 3206_ | B63: Enables use of Quick. Casts ATB Boost on a single target. After performing an action, the ATB gauge will already be partially full. | C63: Trang bị để sử dụng kỹ năng Tăng Tốc. Niệm Tăng ATB lên một mục tiêu. Sau khi hành động, thanh ATB sẽ được lấp đầy một phần ngay lập tức. | D63: 戦闘でクイックが使用できるようになる。 行動準備が対象単体に発生する。 行動後にATBがたまる状態になり、すぐ行動できる。
A64: 3206.001_
A65: 3206.002_
A66: 3207_ | B66: Genesis | C66: Khởi Nguyên | D66: ジェネシス
A67: 3208_ | B67: Enables use of Genesis. Causes special damage [All/8 hits] to all enemies near the target. Damage increases based on Used Momentum/Fluxes. | C67: Trang bị để sử dụng kỹ năng Khởi Nguyên. Gây sát thương đặc biệt [Đa hệ/8 đòn] lên kẻ địch gần mục tiêu. Sát thương tăng theo số lần dùng Xung Lực và số lượng Flux tích lũy. | D67: 戦闘でジェネシスが使用できるようになる。 刹那発動数と昇華数が多いほど威力が大きくなる 特殊攻撃［全/8ヒット］が対象中心に発生する。
A68: 3208.001_
A69: 3208.002_
A70: 3209_ | B70: Cure | C70: Trị Liệu | D70: ケアル
A71: 3210_ | B71: Enables use of Cure. Raises the user's healing magical energy, recovering the HP of all allies near the target. | C71: Trang bị để sử dụng kỹ năng Trị Liệu. Được kích hoạt bởi trái tim nhân từ, tăng cường ma lực trị thương, hồi phục HP cho toàn bộ đồng minh gần mục tiêu. | D71: 戦闘でケアルが使用できるようになる。 慈愛の心を持つ者の癒しの魔力を高めることで 威力の高いHP回復が対象中心に発生する。
A72: 3210.001_
A73: 3210.002_
A74: 3211_ | B74: Lightning | C74: Lôi Điệp | D74: サンダー
A75: 3212_ | B75: Enables use of Lightning. Uses magical energy to create a bolt of lightning, causing magical damage [Light] to all enemies near the target. | C75: Trang bị để sử dụng kỹ năng Lôi Điệp. Dùng ma lực tạo ra tia sét, gây sát thương ma thuật [Quang] lên toàn bộ kẻ địch gần mục tiêu. | D75: 戦闘でサンダーが使用できるようになる。 魔力によって生み出した雷を天から降らせる 魔法攻撃［天］が対象中心に発生する。
A76: 3212.001_
A77: 3212.002_
A78: 3213_ | B78: Incite | C78: Khiêu Khích | D78: 誘導
A79: 3214_ | B79: Enables use of Incite. Casts Provoke on a single target, causing enemy attacks to be directed towards that character. | C79: Trang bị để sử dụng kỹ năng Khiêu Khích. Niệm Khiêu Khích lên một mục tiêu, khiến kẻ địch dồn mọi đòn tấn công vào nhân vật đó. | D79: 戦闘で誘導が使用できるようになる。 挑発が対象単体に発生する。 挑発になったキャラクターに敵の攻撃が誘導できる。
A80: 3214.001_
A81: 3214.002_
A82: 3215_ | B82: Enthunder | C82: Ban Lôi | D82: エンサンダ
A83: 3216_ | B83: Enables use of Enthunder. Adds the Light element to the attacks of all allies near the target. Light- elemental attacks will also cause more damage. | C83: Trang bị để sử dụng kỹ năng Ban Lôi. Thêm nguyên tố Quang vào đòn đánh của đồng minh gần mục tiêu. Các đòn tấn công hệ Quang cũng sẽ gây nhiều sát thương hơn. | D83: 戦闘でエンサンダが使用できるようになる。 天属性付与が対象中心に発生する。 効果中に天属性攻撃を行うと、威力が大きくなる。
A84: 3216.001_
A85: 3216.002_
A86: 3217_ | B86: Sanctity | C86: Thánh Quang | D86: セイクリッド
A87: 3218_ | B87: Enables use of Sanctity. Throws chakrams charged with magical energy, causing physical damage [Light] to all enemies in a line from the user. | C87: Trang bị để sử dụng kỹ năng Thánh Quang. Ném luân đao tích tụ ma lực, gây sát thương vật lý [Quang] lên toàn bộ kẻ địch trên một đường thẳng. | D87: 戦闘でセイクリッドが使用できるようになる。 魔力を込めた円月輪を投げて、物理攻撃［天］が 使用者前方に発生する。刹那発動でHP回復もできる。
A88: 3218.001_
A89: 3218.002_
A90: 3219_ | B90: Remedy | C90: Thanh Tẩy | D90: エスナ
A91: 3220_ | B91: Enables use of Remedy. Heals all status ailments of all allies near the target. Also nullifies status ailments for the next two turns. | C91: Trang bị để sử dụng kỹ năng Thanh Tẩy. Giải trừ toàn bộ trạng thái bất lợi cho đồng minh gần mục tiêu. Đồng thời miễn nhiễm trạng thái bất lợi trong 2 lượt tiếp theo. | D91: 戦闘でエスナが使用できるようになる。 全ての状態異常解除が対象中心に発生する。 ２ターンの間、状態異常を無効にする効果もある。
A92: 3220.001_
A93: 3220.002_
A94: 3221_ | B94: Cheer | C94: Cổ Vũ | D94: 応援
A95: 3222_ | B95: Enables use of Cheer. Casts Combo Release on all allies, allowing combos to be used even when only one of the characters has a full ATB gauge. | C95: Trang bị để sử dụng kỹ năng Cổ Vũ. Niệm Giải Phóng Liên Chiêu lên toàn đội, cho phép dùng combo ngay cả khi chỉ có một nhân vật đầy thanh ATB. | D95: 戦闘で応援が使用できるようになる。 連携解放が味方全体に発生する。 全員のATBがたまっていなくても連携が使用できる。
A96: 3222.001_
A97: 3222.002_
A98: 3223_ | B98: Prayer | C98: Cầu Nguyện | D98: 祈り
A99: 3224_ | B99: Enables use of Prayer. Sharpens spiritual power, granting harmony with the earth itself and recovering the MP of all allies near the target. | C99: Trang bị để sử dụng kỹ năng Cầu Nguyện. Mài sắc tâm linh, hòa nhập cùng đất mẹ và hồi phục MP cho toàn bộ đồng minh gần mục tiêu. | D99: 戦闘で祈りが使用できるようになる。 精神を研ぎ澄まし、世界と同調する力を得ることで MP回復が対象中心に発生する。
A100: 3224.001_
...

Sheet NPCSetParameterMessage
A1: ID | B1: English | C1: Vietnamese | D1: Note
A2: 3709.001_ | B2: 2 | D2: 2
A3: 3710_ | B3: True | D3: True
A4: 3710.001_ | B4: 2 | D4: 2
A5: 3711_ | B5: 331 | D5: 331
A6: 3712_ | B6: ??? | C6: ??? | D6: ？？？
A7: 3712.001_
A8: 3713_ | B8: Fair-Skinned Girl | C8: Cô Gái Da Trắng | D8: 白い肌の少女
A9: 3713.001_
A10: 3714_ | B10: Hooded Girl | C10: Cô Gái Đội Mũ | D10: フードの少女
A11: 3714.001_
A12: 3715_ | B12: Burly Swordsman | C12: Kiếm Sĩ Lực Lưỡng | D12: 巨大な剣を持つ男
A13: 3715.001_
A14: 3716_ | B14: Smart-Looking Boy | C14: Chàng Trai Thông Minh | D14: 利発そうな少年
A15: 3716.001_
A16: 3717_ | B16: Female Knight | C16: Nữ Kị Sĩ | D16: 白い鎧の女
A17: 3717.001_
A18: 3718_ | B18: Reaper | C18: Thần Chết | D18: 大鎌の男
A19: 3718.001_
A20: 3719_ | B20: Raishin | C20: Raishin | D20: ライシン
A21: 3719.001_
A22: 3720_ | B22: Wise-Looking Man | C22: Người Đàn Ông Thông Thái | D22: 賢そうな男
A23: 3720.001_
A24: 3721_ | B24: Raishin | C24: Raishin | D24: ライシン
A25: 3721.001_
A26: 3722_ | B26: Hapsper | C26: Hapsper | D26: キト
A27: 3722.001_
A28: 3723_ | B28: Old Masked Man | C28: Ông Già Mặt Nạ | D28: 仮面の老人
A29: 3723.001_
A30: 3724_ | B30: Cornelius | C30: Cornelius | D30: ロッカス
A31: 3724.001_
A32: 3725_ | B32: Mysterious Man | C32: Người Đàn Ông Bí Ẩn | D32: 謎の男
A33: 3725.001_
A34: 3726_ | B34: Magic Consortium Member | C34: Thành Viên Thương Hội | D34: 魔導商会員
A35: 3726.001_
A36: 3727_ | B36: Traveling Merchant | C36: Thương Nhân Lang Bạt | D36: 行商人
A37: 3727.001_
A38: 3728_ | B38: Lutius | C38: Lutius | D38: イチギ
A39: 3728.001_
A40: 3729_ | B40: Freyja | C40: Freyja | D40: タギシ
A41: 3729.001_
A42: 3730_ | B42: Captain | C42: Đội Trưởng | D42: 団長
A43: 3730.001_
A44: 3731_ | B44: Avalo | C44: Avalo | D44: アヴァロ
A45: 3731.001_
A46: 3732_ | B46: Lord of the Citadel | C46: Thành Chủ | D46: 城主
A47: 3732.001_
A48: 3733_ | B48: Dinas | C48: Dinas | D48: シャンバ
A49: 3733.001_
A50: 3734_ | B50: Old Man | C50: Ông Già | D50: ご隠居
A51: 3734.001_
A52: 3735_ | B52: Akash | C52: Akash | D52: アマツ
A53: 3735.001_
A54: 3736_ | B54: Grumpy-Looking Man | C54: Ông Già Cáu Kỉnh | D54: 気難しそうな男
A55: 3736.001_
A56: 3737_ | B56: Blue Knight | C56: Lam Kị Sĩ | D56: 青い騎士
A57: 3737.001_
A58: 3738_ | B58: Tor | C58: Tor | D58: トール
A59: 3738.001_
A60: 3739_ | B60: Hydor | C60: Hydor | D60: ヒドロ
A61: 3739.001_
A62: 3740_ | B62: Skinny Child | C62: Đứa Trẻ Gầy Gò | D62: 痩せ細った子供
A63: 3740.001_
A64: 3741_ | B64: Skinny Monster | C64: Quái Vật Ốm Yếu | D64: 痩せ細った魔物
A65: 3741.001_
A66: 3742_ | B66: Lilus | C66: Lilus | D66: ライーラ
A67: 3742.001_
A68: 3743_ | B68: Timid Young Man | C68: Thanh Niên Mít Ướt | D68: 気の弱そうな青年
A69: 3743.001_
A70: 3744_ | B70: Burly Swordsman | C70: Kiếm Sĩ Lực Lưỡng | D70: 巨大な剣を持つ男
A71: 3744.001_
A72: 3745_ | B72: Nanase | C72: Nanase | D72: ナナセ
A73: 3745.001_
A74: 3746_ | B74: Mana | C74: Mana | D74: マナ
A75: 3746.001_
A76: 3747_ | B76: Setsuna (Child) | C76: Setsuna (Bé) | D76: セツナ（子供）
A77: 3747.001_
A78: 3748_ | B78: Sayagi | C78: Sayagi | D78: サヤギ
A79: 3748.001_
A80: 3749_ | B80: Gloomy Old Woman | C80: Bà Lão U Ám | D80: 陰のある老婆
A81: 3749.001_
A82: 3750_ | B82: Rhydderch | C82: Rhydderch | D82: テンバ
A83: 3750.001_
A84: 3751_ | B84: Mysterious Voice | C84: Giọng Nói Bí Ẩn | D84: 謎の声
A85: 3751.001_
A86: 3752_ | B86: Time Judge | C86: Thẩm Phán Thời Gian | D86: 時の審判者
A87: 3752.001_
A88: 3753_ | B88: <Aeterna>? | C88: <Aeterna>? | D88: ＜ツクシ＞？
A89: 3753.001_
A90: 3754_ | B90: Eutess | C90: Eutess | D90: ユーテス
A91: 3754.001_
A92: 3755_ | B92: Youth | C92: Youth | D92: 青年
A93: 3755.001_
A94: 3756_ | B94: Shinku | C94: Shinku | D94: シンク
A95: 3756.001_
A96: 3757_ | B96: Black Sheep | C96: Cừu Đen | D96: 黒羊
A97: 3757.001_
A98: 3758_ | B98: Syg | C98: Syg | D98: シグ
A99: 3758.001_
A100: 3759_ | B100: Quotra | C100: Quotra | D100: クロトワ
...

Sheet PlayerSetParameterMessage
A1: ID | B1: English | C1: Vietnamese | D1: Note
A2: 4043.001_ | B2: 2 | D2: 2
A3: 4044_ | B3: True | D3: True
A4: 4044.001_ | B4: 0 | D4: 0
A5: 4044.002_ | B5: 7 | D5: 7
A6: 4045_ | B6: Endir | C6: Endir | D6: エンド
A7: 4045.001_
A8: 4046_ | B8: Setsuna | C8: Setsuna | D8: セツナ
A9: 4046.001_
A10: 4047_ | B10: Aeterna | C10: Aeterna | D10: クオン
A11: 4047.001_
A12: 4048_ | B12: Nidr | C12: Nidr | D12: ヨミ
A13: 4048.001_
A14: 4049_ | B14: Kir | C14: Kir | D14: キール
A15: 4049.001_
A16: 4050_ | B16: Julienne | C16: Julienne | D16: ジュリオン
A17: 4050.001_
A18: 4051_ | B18: Fides | C18: Fides | D18: フィデス
A19: 4051.001_

Sheet PlayerSkillDataMessage
A1: ID | B1: English | C1: Vietnamese | D1: Note
A2: 4052.001_ | B2: 2 | D2: 2
A3: 4053_ | B3: True | D3: True
A4: 4053.001_ | B4: 0 | D4: 0
A5: 4054_ | B5: 17 | D5: 17
A6: 4055_ | B6: Attack | C6: Tấn Công | D6: たたかう
A7: 4055.001_
A8: 4056_ | B8: Cyclone | C8: Cuồng Phong | D8: 回転斬り
A9: 4057_ | B9: Offers a wide attack range, and can also knock back enemies. Causes physical damage [Null] to all enemies near the user. | C9: Đòn tấn công phạm vi rộng, có thể đẩy lùi kẻ địch. Gây sát thương vật lý [Vô hệ] lên mọi kẻ địch quanh bản thân. | D9: 広範囲に攻撃できるうえに、敵を吹っ飛ばせる 物理攻撃［無］が使用者中心に発生する。
A10: 4058_ | B10: Aura | C10: Hào Quang | D10: オーラ
A11: 4059_ | B11: Healing energy recovers the HP of all allies near the target. Also heals status ailments when used in Momentum mode. | C11: Năng lượng trị thương hồi phục HP cho toàn bộ đồng minh gần mục tiêu. Giải trừ trạng thái bất lợi khi dùng ở chế độ Xung Lực. | D11: 癒しの魔力で、HP回復が対象中心に発生する。 刹那を発動すると、状態異常解除も発生する。
A12: 4060_ | B12: Shock | C12: Chấn Động | D12: ショック
A13: 4061_ | B13: Unleashes a blast of concentrated magical energy, causing magical damage [Null] to all enemies near the target. | C13: Giải phóng chùm ma lực tập trung, gây sát thương ma thuật [Vô hệ] lên toàn bộ kẻ địch gần mục tiêu. | D13: 圧縮した魔力を暴発させることにより 魔法攻撃［無］が対象中心に発生する。
A14: 4062_ | B14: Wall | C14: Bức Tường | D14: ウォール
A15: 4063_ | B15: Deploys a wall of magical energy around a single target that defends against both physical and magical attacks. | C15: Dựng bức tường ma thuật quanh một mục tiêu, chống đỡ cả đòn tấn công vật lý lẫn ma thuật. | D15: 魔力の障壁を展開し、敵の攻撃を防いでくれる 物理盾と魔法盾が対象単体に発生する。
A16: 4064_ | B16: Blade Wave | C16: Kiếm Khí | D16: 無刃波
A17: 4065_ | B17: Fires an energy blade that causes physical damage [Null] to all enemies in a line from the user. | C17: Phóng ra lưỡi kiếm năng lượng gây sát thương vật lý [Vô hệ] lên toàn bộ kẻ địch trên đường thẳng. | D17: 闘気の刃を敵に向けて飛ばすことで 物理攻撃［無］が使用者前方に発生する。
A18: 4066_ | B18: Backslash | C18: Tập Kích | D18: 影斬り
A19: 4067_ | B19: Darts behind foes in a split second, catching them off guard. Causes physical damage [Null] to all enemies near the target. | C19: Lướt ra sau lưng kẻ địch trong chớp mắt, đánh úp bất ngờ. Gây sát thương vật lý [Vô hệ] lên toàn bộ kẻ địch gần mục tiêu. | D19: 敵の虚を突いて、一瞬に敵の背後に回り込み 物理攻撃［無］が対象中心に発生する。
... A39: 4087_ | B39: Causes special damage [All/8 hits] to all enemies near the target. Damage increases according to the Momentum Uses counter and no. of added Fluxes. | C39: Gây sát thương đặc biệt [Đa hệ/8 đòn] lên kẻ địch gần mục tiêu. Sát thương tăng theo số lần dùng Xung Lực và số lượng Flux tích lũy. | D39: 刹那発動数と昇華数が多いほど威力が大きくなる 特殊攻撃［全/8ヒット］が対象中心に発生する。

Sheet ScenarioMessageData_Chapter_1
A1: ID | B1: English | C1: Vietnamese | D1: Note
A2: 4087.001_ | B2: 1
A3: 4088_{"NpcNm":"","QuestNm":"","Head":{"Type":-1,"Id":0,"NpcId":0,"QuestId":0}} | B3: Presented by SQUARE ENIX | C3: Từ SQUARE ENIX | D3: SQUARE ENIX presents
A4: 4089_{"NpcNm":"","QuestNm":"","Head":{"Type":-1,"Id":1,"NpcId":0,"QuestId":0}} | B4: Developed by Tokyo RPG Factory | C4: Phát triển bởi Tokyo RPG Factory | D4: developed by Tokyo RPG Factory
A5: 4090_{"NpcNm":"","QuestNm":"","Head":{"Type":-1,"Id":2,"NpcId":0,"QuestId":0}} | B5: Setsuna: A Tale of Snow & Sacrifice | C5: Setsuna: Khúc Ca Của Tuyết Và Lễ Hiến Tế | D5: セ 雪 い ツ の け ナ に え と
A6: 4091_{"NpcNm":"NPC_90001","QuestNm":"","Head":{"Type":-1,"Id":3,"NpcId":2,"QuestId":0}} | B6: Mm... It seems you live up to the rumors. A natural mercenary. | C6: Ừm... Đúng như lời đồn. Một lính đánh thuê bẩm sinh. | D6: ほう……ウワサどおりの傭兵だな。 良い感覚を持っている。
A7: 4092_{"NpcNm":"NPC_90001","QuestNm":"","Head":{"Type":-1,"Id":4,"NpcId":2,"QuestId":0}} | B7: Or... | C7: Hoặc là... | D7: あるいは……
A8: 4093_{"NpcNm":"NPC_10021","QuestNm":"","Head":{"Type":-1,"Id":5,"NpcId":2,"QuestId":0}} | B8: Perhaps my own skills as a mercenary simply grow weak... | C8: Chỉ đơn giản kĩ năng của ta đang mai một dần | D8: 傭兵としてのワシの 能力が衰えたか……。
A9: 4094_{"NpcNm":"NPC_10021","QuestNm":"","Head":{"Type":-1,"Id":6,"NpcId":2,"QuestId":0}} | B9: I am <NAME=NPC_10020>. I will be working with you on this mission. | C9: Ta là <NAME=NPC_10020>. Là bạn đồng hành của ngươi trong nhiệm vụ|này. | D9: 今回の依頼で、キミと組む <NAME=NPC_10020>だ。
A10: 4095_{"NpcNm":"NPC_10020","QuestNm":"","Head":{"Type":-1,"Id":7,"NpcId":2,"QuestId":0}} | B10: What is your name? | C10: Tên người là gì? | D10: キミの名はなんという？
A11: 4096_{"NpcNm":"NPC_10020","QuestNm":"","Head":{"Type":-1,"Id":8,"NpcId":2,"QuestId":0}} | B11: Nice to be working with you, <NAME=CP_0001>. | C11: Đồng hành vui vẻ, <NAME=CP_0001>. | D11: よろしく<NAME=CP_0001>。
A12: 4097_{"NpcNm":"NPC_10020","QuestNm":"","Head":{"Type":-1,"Id":9,"NpcId":2,"QuestId":0}} | B12: Our mission is to recover a young girl who has been kidnapped by monsters. | C12: Nhiệm vụ lần này là giải cứu cô bé bị quái vật bắt|cóc. | D12: 依頼内容は、 魔物にさらわれた少女の奪還。
A13: 4098_{"NpcNm":"NPC_10020","QuestNm":"","Head":{"Type":-1,"Id":10,"NpcId":2,"QuestId":0}} | B13: Your job will be to exterminate any monsters we encounter along the way. | C13: Việc của ngươi là tiêu diệt mọi quái vật trên đường đi. | D13: <NAME=CP_0001>には 道中の魔物の駆逐を頼みたい。
A14: 4099_{"NpcNm":"NPC_10020","QuestNm":"","Head":{"Type":-1,"Id":11,"NpcId":2,"QuestId":0}} | B14: Once we are done, I shall return the girl to our client. | C14: Khi mọi chuyện kết thúc, ta sẽ đưa cô bé về chỗ khách|hàng. | D14: その後、少女を依頼人のもとへ 送り届けるのはワシの仕事だ。
... A1405: 5487_{"NpcNm":"CP_0005","QuestNm":"","Head":{"Type":-1,"Id":1402,"NpcId":2,"QuestId":0}} | B1405: There's an entrance inside the <NAME=MA_0013_01>. I'll show you the way. | C1405: Có một lối vào nằm bên trong <NAME=MA_0013_01>. Em sẽ dẫn đường cho|mọi người. | D1405: <NAME=MA_0013_01>に入り口があるんだ。 案内するよ。

Sheet ScenarioMessageData_Chapter_2
A1: ID | B1: English | C1: Vietnamese | D1: Note
A2: 5487.001_ | B2: 1
A3: 5488_{"NpcNm":"CP_0005","QuestNm":"","Head":{"Type":-1,"Id":1403,"NpcId":2,"QuestId":0}} | B3: There's a path just on from here that leads to my village. Come on, let's go. | C3: There's a con đường just on from here that leads to my|ngôi làng. Come on, let's go. | D3: この先におれの村、イルへ 行く道があるんだ。行こう。
A4: 5489_{"NpcNm":"CP_0005","QuestNm":"","Head":{"Type":-1,"Id":1404,"NpcId":2,"QuestId":0}} | B4: This is the path... | C4: Đây chính là con đường... | D4: こっちだよ。
A5: 5490_{"NpcNm":"CP_0004","QuestNm":"","Head":{"Type":-1,"Id":1405,"NpcId":2,"QuestId":0}} | B5: Path? There ain't no path here... | C5: Đường ư? Ở đây làm gì có đường... | D5: こっちって 道なんてないじゃないか。
A6: 5491_{"NpcNm":"CP_0005","QuestNm":"","Head":{"Type":-1,"Id":1406,"NpcId":2,"QuestId":0}} | B6: Yeah, there is...a secret one. | C6: Có mà... đó là lối đi bí mật. | D6: あるんだ。秘密の抜け道が。
A7: 5492_{"NpcNm":"CP_0005","QuestNm":"","Head":{"Type":-1,"Id":1407,"NpcId":2,"QuestId":0}} | B7: See? | C7: Thấy chưa? | D7: ほらね？
A8: 5493_{"NpcNm":"CP_0004","QuestNm":"","Head":{"Type":-1,"Id":1408,"NpcId":2,"QuestId":0}} | B8: Him again... What're we gonna do? | C8: Lại là hắn... Chúng ta tính sao đây? | D8: また、こいつか……。 どうする？
A9: 5494_{"NpcNm":"CP_0004","QuestNm":"","Head":{"Type":-1,"Id":1409,"NpcId":2,"QuestId":0}} | B9: Don't you think we better take care of him, <NAME=CP_0001>? Just to be safe... | C9: Don't you think we better take care of him, <NAME=CP_0001>? Just to|be safe... | D9: ここで片づけておいたほうが よくないか、<NAME=CP_0001>？
A10: 5495_{"NpcNm":"","QuestNm":"","Head":{"Type":-1,"Id":1410,"NpcId":0,"QuestId":0}} | B10: Ignore him. | C10: Mặc kệ hắn. | D10: 無視しよう
A11: 5496_{"NpcNm":"","QuestNm":"","Head":{"Type":-1,"Id":1411,"NpcId":0,"QuestId":0}} | B11: Get rid of him. | C11: Khử hắn đi. | D11: 倒しておこう
A12: 5497_{"NpcNm":"CP_0005","QuestNm":"","Head":{"Type":-1,"Id":1412,"NpcId":2,"QuestId":0}} | B12: Exactly! I'm with <NAME=CP_0001>! | C12: Chuẩn luôn! Tôi đồng ý với <NAME=CP_0001>! | D12: それがいいよ、うん。賛成。
A13: 5498_{"NpcNm":"CP_0004","QuestNm":"","Head":{"Type":-1,"Id":1413,"NpcId":2,"QuestId":0}} | B13: Don't you think the way he keeps followin' us around like this is a li'l creepy, though? | C13: Don't you think the way he keeps followin' us around|like this is a li'l creepy, though? | D13: でも、何か不気味じゃねえか。 こう俺たちの周りをうろつかれると。
A14: 5499_{"NpcNm":"CP_0005","QuestNm":"","Head":{"Type":-1,"Id":1414,"NpcId":2,"QuestId":0}} | B14: Maybe it is creepy, but he's harmless, so who cares? | C14: Có thể kỳ lạ thật, nhưng hắn vô hại, việc gì phải|bận tâm? | D14: 不気味でも無害だからいいだろ。
... A1715: 7198_{"NpcNm":"CP_0004","QuestNm":"","Head":{"Type":-1,"Id":3115,"NpcId":2,"QuestId":0}} | B1715: Yeah... I don't wanna hang around here any longer than I gotta... | C1715: Yeah... I don't wanna hang around here any longer than|I gotta... | D1715: ああ。こんな所に長居は無用だ。

Sheet ScenarioMessageData_Chapter_3
A1: ID | B1: English | C1: Vietnamese | D1: Note
A2: 7198.001_ | B2: 1
A3: 7199_{"NpcNm":"NPC_28020","QuestNm":"","Head":{"Type":-1,"Id":3116,"NpcId":2,"QuestId":0}} | B3: Well, I never... Come 'ere through the blizzard, 'ave ya? | C3: Well, I never... Come 'ere through the blizzard, 'ave|ya? | D3: 驚いたな……。あんたら、 この吹雪の中を来たのかね。
A4: 7200_{"NpcNm":"CP_0004","QuestNm":"","Head":{"Type":-1,"Id":3117,"NpcId":2,"QuestId":0}} | B4: Phew... | C4: Phew... | D4: いやぁ、まいったよ。
A5: 7201_{"NpcNm":"CP_0004","QuestNm":"","Head":{"Type":-1,"Id":3118,"NpcId":2,"QuestId":0}} | B5: I knew it'd be colder here, but I didn't think it was gonna be this bad... | C5: I knew it'd be colder here, but I didn't think it was|gonna be this bad... | D5: こっちの寒さが厳しいのは 知っていたが予想以上だった。
A6: 7202_{"NpcNm":"CP_0002","QuestNm":"","Head":{"Type":-1,"Id":3119,"NpcId":2,"QuestId":0}} | B6: <NAME=CP_0006>! | C6: <NAME=CP_0006>! | D6: <NAME=CP_0006>！！
A7: 7203_{"NpcNm":"NPC_10171","QuestNm":"","Head":{"Type":-1,"Id":3120,"NpcId":2,"QuestId":0}} | B7: Young lady... Are you... | C7: Young lady... Are you... | D7: お主……まさか……。
A8: 7204_{"NpcNm":"CP_0006","QuestNm":"","Head":{"Type":-1,"Id":3121,"NpcId":2,"QuestId":0}} | B8: There is no cause for alarm... I am merely somewhat fatigued. | C8: There is no cause for alarm... I am merely|somewhat fatigued. | D8: 大事ない。 少し疲れただけだ。
A9: 7205_{"NpcNm":"NPC_10171","QuestNm":"","Head":{"Type":-1,"Id":3122,"NpcId":2,"QuestId":0}} | B9: ...... | C9: ...... | D9: …………。
A10: 7206_{"NpcNm":"CP_0004","QuestNm":"","Head":{"Type":-1,"Id":3123,"NpcId":2,"QuestId":0}} | B10: Are you two from this town? We're on a journey... | C10: Are you two from this town? We're on a journey... | D10: あんたたち、この村の人かい？ 俺たちは旅をしているんだが……
A11: 7207_{"NpcNm":"NPC_28020","QuestNm":"","Head":{"Type":-1,"Id":3124,"NpcId":2,"QuestId":0}} | B11: A journey? Where on earth to? | C11: A journey? Where on earth to? | D11: ……旅だって？ いったいどこへ？
A12: 7208_{"NpcNm":"CP_0004","QuestNm":"","Head":{"Type":-1,"Id":3125,"NpcId":2,"QuestId":0}} | B12: We're headin' for the <NAME=MA_0041_01>... How far are they from here? | C12: We're headin' for the <NAME=MA_0041_01>... How far are they from here? | D12: <NAME=MA_0041_01>を目指してる。 ここからどのくらいだ？
A13: 7209_{"NpcNm":"NPC_28020","QuestNm":"","Head":{"Type":-1,"Id":3126,"NpcId":2,"QuestId":0}} | B13: The <NAME=MA_0041_01>, eh? They're on the other side of <NAME=MA_0033_01>. | C13: The <NAME=MA_0041_01>, eh? They're on the other side of <NAME=MA_0033_01>. | D13: <NAME=MA_0041_01>か…… そりゃ<NAME=MA_0033_01>の向こうさ。
A14: 7210_{"NpcNm":"NPC_28020","QuestNm":"","Head":{"Type":-1,"Id":3127,"NpcId":2,"QuestId":0}} | B14: But you'd be best off forgettin' that idea, if you value yer life... | That mountain can no longer be crossed. | C14: But you'd be best off forgettin' that idea, if|you value yer life... That mountain can no longer be|crossed. | D14: だがやめておけ。命が惜けりゃな。 もう越えられる山じゃない。
... A1346: 8541_{"NpcNm":"CP_0002","QuestNm":"","Head":{"Type":-1,"Id":4459,"NpcId":2,"QuestId":0}} | B1346: Let's go...to the <NAME=MA_0041_01>... | C1346: Let's go...to the <NAME=MA_0041_01>... | D1346: 行こう……<NAME=MA_0041_01>へ。

Sheet ScenarioMessageData_Chapter_4
A1: ID | B1: English | C1: Vietnamese | D1: Note
A2: 8541.001_ | B2: 1
A3: 8542_{"NpcNm":"CP_0002","QuestNm":"","Head":{"Type":-1,"Id":4460,"NpcId":2,"QuestId":0}} | B3: So these are the <NAME=MA_0041_01>... | C3: So these are the <NAME=MA_0041_01>... | D3: ここが……<NAME=MA_0041_01>……。
A4: 8543_{"NpcNm":"CP_0002","QuestNm":"","Head":{"Type":-1,"Id":4461,"NpcId":2,"QuestId":0}} | B4: Our journey's final destination... | C4: Our journey's final destination... | D4: 旅の終着点……。
A5: 8544_{"NpcNm":"CP_0002","QuestNm":"","Head":{"Type":-1,"Id":4462,"NpcId":2,"QuestId":0}} | B5: We're here at last... | C5: We're here at last... | D5: やっと……ここまで来たんだね。
A6: 8545_{"NpcNm":"","QuestNm":"","Head":{"Type":-1,"Id":4463,"NpcId":0,"QuestId":0}} | B6: I'll see you there safely. | C6: I'll see you there safely. | D6: 見届けてやる
A7: 8546_{"NpcNm":"","QuestNm":"","Head":{"Type":-1,"Id":4464,"NpcId":0,"QuestId":0}} | B7: Are you ready? | C7: Are you ready? | D7: 覚悟はできているか？
A8: 8547_{"NpcNm":"CP_0002","QuestNm":"","Head":{"Type":-1,"Id":4465,"NpcId":2,"QuestId":0}} | B8: <NAME=CP_0001>... | C8: <NAME=CP_0001>... | D8: <NAME=CP_0001>……
A9: 8548_{"NpcNm":"CP_0002","QuestNm":"","Head":{"Type":-1,"Id":4466,"NpcId":2,"QuestId":0}} | B9: You kept your promise to me, didn't you, <NAME=CP_0001>? | C9: You kept your promise to me, didn't you, <NAME=CP_0001>? | D9: <NAME=CP_0001>は約束を果たしてくれたね。
A10: 8549_{"NpcNm":"CP_0002","QuestNm":"","Head":{"Type":-1,"Id":4467,"NpcId":2,"QuestId":0}} | B10: Now it's my turn. | C10: Now it's my turn. | D10: 今度は私の番。
A11: 8550_{"NpcNm":"CP_0002","QuestNm":"","Head":{"Type":-1,"Id":4468,"NpcId":2,"QuestId":0}} | B11: I'm going to fulfill my duty. | C11: I'm going to fulfill my duty. | D11: 私は、私の役目を果たすよ。
A12: 8551_{"NpcNm":"CP_0002","QuestNm":"","Head":{"Type":-1,"Id":4469,"NpcId":2,"QuestId":0}} | B12: I've been ready all along, ever since we first set out. | C12: I've been ready all along, ever since we first set|out. | D12: 覚悟は変わっていないよ。ずっと。
A13: 8552_{"NpcNm":"CP_0002","QuestNm":"","Head":{"Type":-1,"Id":4470,"NpcId":2,"QuestId":0}} | B13: But... | C13: But... | D13: でも……
A14: 8553_{"NpcNm":"CP_0002","QuestNm":"","Head":{"Type":-1,"Id":4471,"NpcId":2,"QuestId":0}} | B14: I see my role as sacrifice a little differently now... Before, I didn't really think about it... | C14: I see my role as sacrifice a little differently now...|Before, I didn't really think about it... | D14: いけにえという役目を、ただ 受け入れていたあの頃とは少し違う。
... A807: 9346_{"NpcNm":"","QuestNm":"","Head":{"Type":-1,"Id":5264,"NpcId":0,"QuestId":0}} | B807: The End | C807: The End | D807: End

Sheet ScenarioMessageData_NormalConv
A1: ID | B1: English | C1: Vietnamese | D1: Note
A2: 5265_{"NpcNm":"NPC_21010","QuestNm":"s_talkLoop","Head":{"Type":0,"Id":5265,"NpcId":0,"QuestId":0}} | B2: It's not often anyone comes here from the mainland. Usually it's only the other way round... | There's a departure ceremony today, actually. | What? Who's departing? The sacrifice, of course! | C2: Hiếm khi có ai từ đại lục đặt chân đến đây. Thường|thì toàn theo chiều ngược lại... Thực ra, hôm nay có|lễ tiễn đưa đấy. Sao cơ? Ai lên đường ư? Vật hiến tế|chứ còn ai nữa!
A3: 5266_{"NpcNm":"NPC_21010","QuestNm":"s_talkLoop","Head":{"Type":0,"Id":5266,"NpcId":0,"QuestId":0}} | B3: What is it? If you're looking for the ferry, it's already set sail back to the mainland. | Anyway, seeing as you came all the way here, there's no need to rush back. | At least stay and watch the departure ceremony. Not that it's much of a spectacle... | C3: Có chuyện gì thế? Nếu tìm phà thì nó đã nhổ neo về|lại đại lục rồi. Dù sao cũng cất công tới tận đây,|việc gì phải vội vã quay về. Ít nhất hãy ở lại xem|lễ tiễn đưa đã. Dù nó cũng chẳng vui vẻ gì cho cam...
A4: 5267_{"NpcNm":"NPC_21010","QuestNm":"s_talkLoop","Head":{"Type":0,"Id":5267,"NpcId":0,"QuestId":0}} | B4: Hold on a minute... How'd you get back here without a boat!? | What? By airship!? Don't be ridiculous... | C4: Khoan đã nào... Không có thuyền thì làm sao cậu về|lại đây được!? Cái gì? Bằng phi thuyền á!? Đừng có nói|đùa...
A5: 5268_{"NpcNm":"NPC_21020","QuestNm":"s_talkLoop","Head":{"Type":0,"Id":5268,"NpcId":0,"QuestId":0}} | B5: You wanna get to the village? | After you leave the port, jus' head nord-west, and you'll soon see it... | C5: Cậu muốn tới làng hả? Rời cảng rồi cứ đi về phía tây|bắc, sẽ thấy nó ngay thôi...
A6: 5269_{"NpcNm":"NPC_21020","QuestNm":"s_talkLoop","Head":{"Type":0,"Id":5269,"NpcId":0,"QuestId":0}} | B6: Sorry, there won't be anudda ferry for a while now... | The next one'll be carrying the sacrifice. | C6: Thứ lỗi, còn lâu mới có chuyến phà tiếp theo...|Chuyến tới sẽ là chuyến chở vật hiến tế đi.
A7: 5270_{"NpcNm":"NPC_21020","QuestNm":"s_talkLoop","Head":{"Type":0,"Id":5270,"NpcId":0,"QuestId":0}} | B7: Chúc may mắn trên chuyến đi! Mang hy vọng trở lại nhé! <NAME=CP_0002>! | C7: Chúc may mắn trên chuyến đi! Mang hy vọng trở lại|nhé! <NAME=CP_0002>!
A8: 5271_{"NpcNm":"NPC_21020","QuestNm":"s_talkLoop","Head":{"Type":0,"Id":5271,"NpcId":0,"QuestId":0}} | B8: Gió đại dương thổi từ đồi... T <NAME=CP_0002>? | C8: Gió đại dương thổi từ đồi... T <NAME=CP_0002>?
A9: 5272_{"NpcNm":"NPC_21040","QuestNm":"s_talkLoop","Head":{"Type":0,"Id":5272,"NpcId":0,"QuestId":0}} | B9: Very few people travel to this island these days, what with all the monsters... | You're very brave to have come here. Let me welcome you on behalf of the village! | C9: Dạo này quái vật hoành hành, hiếm ai dám tới hòn|đảo này lắm... Cậu thật dũng cảm khi tới đây. Thay|mặt dân làng, ta nhiệt liệt chào đón!
A10: 5273_{"NpcNm":"NPC_21040","QuestNm":"s_talkLoop","Head":{"Type":0,"Id":5273,"NpcId":0,"QuestId":0}} | B10: The next ferry that'll be arriving will sail to the citadel town of Floneia. | The sacrifice's guard always head there first, to decide their journey's route. | Land...sea...air... From Floneia, you can determine the safest route. | C10: Chuyến phà cập bến tiếp theo sẽ giương buồm đến|thành trấn Floneia. Hộ vệ của vật hiến tế luôn tới đó|trước để định đoạt lộ trình chuyến đi. Đường bộ...|đường biển... đường không... Từ Floneia, mới có|thể chọn ra con đường an toàn nhất.
A11: 5274_{"NpcNm":"NPC_21040","QuestNm":"s_talkLoop","Head":{"Type":0,"Id":5274,"NpcId":0,"QuestId":0}} | B11: I never thought we'd be seeing off little <NAME=CP_0002> like this... | Thank you... Thank you so much... | C11: Ta chưa từng nghĩ sẽ phải tiễn biệt con bé <NAME=CP_0002> thế|này... Cảm ơn các cậu... Cảm ơn các cậu rất nhiều...
A12: 5275_{"NpcNm":"NPC_21040","QuestNm":"s_talkLoop","Head":{"Type":0,"Id":5275,"NpcId":0,"QuestId":0}} | B12: Ngôi làng bé nhỏ này <NAME=CP_0002>? | C12: Ngôi làng bé nhỏ này <NAME=CP_0002>?
A13: 5276_{"NpcNm":"NPC_21030","QuestNm":"s_talkLoop","Head":{"Type":0,"Id":5276,"NpcId":0,"QuestId":0}} | B13: Chào mừng, chào! | C13: Chào mừng, chào!
... A685: 5948_{"NpcNm":"NPC_10220","QuestNm":"","Head":{"Type":0,"Id":5948,"NpcId":0,"QuestId":0}} | B685: ...... | C685: ......

Sheet SetsunaSkillDataMessage
A1: ID | B1: English | C1: Vietnamese | D1: Note
A2: 9347.001_ | B2: 2 | D2: 2
A3: 9348_ | B3: True | D3: True
A4: 9348.001_ | B4: 0 | D4: 0
A5: 9349_ | B5: 17 | D5: 17
A6: 9350_ | B6: Attack | C6: Tấn Công | D6: たたかう
A7: 9350.001_
A8: 9351_ | B8: Cure | C8: Trị Liệu | D8: ケアル
A9: 9352_ | B9: When used by one with a benevolent heart, this tech raises the user's healing magical energy, recovering the HP of all allies near the target. | C9: Được kích hoạt bởi trái tim nhân từ, tăng cường ma lực trị thương, hồi phục HP cho toàn bộ đồng minh gần mục tiêu. | D9: 慈愛の心を持つ者の癒しの魔力を高めることで 威力の高いHP回復が対象中心に発生する。
A10: 9353_ | B10: Lightning | C10: Lôi Điệp | D10: サンダー
A11: 9354_ | B11: Uses magical energy to create a bolt of lightning, causing magical damage [Light] to all enemies near the target. | C11: Dùng ma lực tạo ra tia sét, gây sát thương ma thuật [Quang] lên toàn bộ kẻ địch gần mục tiêu. | D11: 魔力によって生み出した雷を天から降らせる 魔法攻撃［天］が対象中心に発生する。
A12: 9355_ | B12: Incite | C12: Khiêu Khích | D12: 誘導
A13: 9356_ | B13: Casts Provoke on a single target, causing enemy attacks to be directed towards that character. | C13: Niệm Khiêu Khích lên một mục tiêu, khiến kẻ địch dồn mọi đòn tấn công vào nhân vật đó. | D13: 挑発が対象単体に発生する。 挑発になったキャラクターに敵の攻撃が誘導できる。
A14: 9357_ | B14: Enthunder | C14: Ban Lôi | D14: エンサンダ
A15: 9358_ | B15: Adds the Light element to the attacks of all allies near the target. Light-elemental attacks will also cause more damage. | C15: Thêm nguyên tố Quang vào đòn đánh của đồng minh gần mục tiêu. Các đòn tấn công hệ Quang cũng sẽ gây nhiều sát thương hơn. | D15: 天属性付与が対象中心に発生する。 効果中に天属性攻撃を行うと、威力が大きくなる。
A16: 9359_ | B16: Sanctity | C16: Thánh Quang | D16: セイクリッド
A17: 9360_ | B17: Throws chakrams charged with magical energy, causing physical damage [Light] to all enemies in a line from the user. | C17: Ném luân đao tích tụ ma lực, gây sát thương vật lý [Quang] lên toàn bộ kẻ địch trên một đường thẳng. | D17: 魔力を込めた円月輪を投げて、物理攻撃［天］が 使用者前方に発生する。刹那発動でHP回復もできる。
A18: 9361_ | B18: Remedy | C18: Thanh Tẩy | D18: エスナ
A19: 9362_ | B19: Heals all status ailments of all allies near the target. Also nullifies status ailments for the next two turns. | C19: Giải trừ toàn bộ trạng thái bất lợi cho đồng minh gần mục tiêu. Đồng thời miễn nhiễm trạng thái bất lợi trong 2 lượt tiếp theo. | D19: 全ての状態異常解除が対象中心に発生する。 ２ターンの間、状態異常を無効にする効果もある。
... A39: 9382_ | B39: Draws in all nearby magical energy, causing magical damage [Light] to all enemies and recovering the HP of all allies. | C39: Hút toàn bộ ma lực xung quanh, gây sát thương ma thuật [Quang] lên toàn bộ kẻ địch và hồi phục HP cho toàn đội. | D39: 周囲にある全ての魔力を集束させて 魔法攻撃［天］とHP回復が全体に発生する。

Sheet SetsunaSystemDataMessage
A1: ID | B1: English | C1: Vietnamese | D1: Note
A2: 9382.001_ | B2: 2 | D2: 2
A3: 9383_ | B3: True | D3: True
A4: 9383.001_ | B4: 0 | D4: 0
A5: 9384_ | B5: 244 | D5: 244
A6: 9385_ | B6: Affect All | D6: 効果全体化
A7: 9385.001_
A8: 9386_ | B8: Duration Boost | D8: 発生時間延長
A9: 9386.001_
A10: 9387_ | B10: Guaranteed Critical | D10: クリティカル発生
A11: 9387.001_
A12: 9388_ | B12: Damage Reduction | D12: 被ダメージ減少
A13: 9388.001_
A14: 9389_ | B14: Perfect Defense | D14: 完全防御
A15: 9389.001_
A16: 9390_ | B16: Return Damage | D16: ダメージ返し
A17: 9390.001_
A18: 9391_ | B18: Double Effect | D18: 連続再生
A19: 9391.001_
A20: 9392_ | B20: Nullify Status Ailments | D20: 状態異常無効
A21: 9392.001_
A22: 9393_ | B22: Tactical Combo | D22: タクティカルコンボ
A23: 9393.001_
A24: 9394_ | B24: Revival Counter | D24: リバイバルカウンター
A25: 9394.001_
A26: 9395_ | B26: Duration Boost | D26: 発生時間延長
A27: 9395.001_
A28: 9396_ | B28: Duration Boost | D28: 発生時間延長
A29: 9396.001_
A30: 9397_ | B30: Duration Boost | D30: 発生時間延長
A31: 9397.001_ | D31: SETSUNA_SYS_012
A32: 9398_ | B32: Duration Boost | D32: 発生時間延長
A33: 9398.001_
A34: 9399_ | B34: Counters Not Reset | D34: カウントリセット無効
A35: 9399.001_
A36: 9400_ | B36: Special Damage | D36: 特殊攻撃化
A37: 9400.001_
A38: 9401_ | B38: All-Elemental Damage | D38: 全属性攻撃化
A39: 9401.001_
A40: 9402_ | B40: ATB Boost | D40: 行動準備
A41: 9402.001_
A42: 9403_ | B42: Item Stock Not Reduced | D42: アイテム消費なし
A43: 9403.001_
A44: 9404_ | B44: Guaranteed Critical | D44: クリティカル発生
A45: 9404.001_
A46: 9405_ | B46: Additional Effect | D46: 追加効果
A47: 9405.001_
A48: 9406_ | B48: Attack Reduction | D48: セツナシステム 攻撃低下
A49: 9406.001_
A50: 9407_ | B50: Freeze | D50: セツナシステム 凍結
A51: 9407.001_
A52: 9408_ | B52: Stun | D52: セツナシステム スタン
A53: 9408.001_
A54: 9409_ | B54: Death | D54: セツナシステム 即死
A55: 9409.001_
A56: 9410_ | B56: Stop | D56: セツナシステム 時間停止
A57: 9410.001_
A58: 9411_ | B58: Paralysis | D58: セツナシステム 麻痺
A59: 9411.001_
A60: 9412_ | B60: Confusion | D60: セツナシステム 混乱
A61: 9412.001_
A62: 9413_ | B62: User HP Recovery | D62: セツナシステム 使用者ＨＰ回復
A63: 9413.001_
A64: 9414_ | B64: Additional MP Recovery | D64: セツナシステム 追加ＭＰ回復
A65: 9414.001_
A66: 9415_ | B66: Additional Damage | D66: セツナシステム 追加攻撃
A67: 9415.001_
A68: 9416_ | B68: Area HP Recovery | D68: セツナシステム 範囲ＨＰ回復
A69: 9416.001_
A70: 9417_ | B70: Area Defense Reduction | D70: セツナシステム 範囲防御低下
A71: 9417.001_
A72: 9418_ | B72: Additional HP Recovery | D72: 昇華専用 追加HP回復 刹那威力効果
A73: 9418.001_
A74: 9419_ | B74: Add Physical Damage | D74: 物理攻撃
A75: 9419.001_
A76: 9420_ | B76: Add Physical Damage | D76: 物理攻撃
A77: 9420.001_ | D77: SKILL_SETSUNA_SYS_201
A78: 9421_ | B78: Add Magical Damage | D78: 魔法攻撃
A79: 9421.001_
A80: 9422_ | B80: HP Recovery | D80: HP回復
A81: 9422.001_
A82: 9423_ | B82: Add Physical Damage | D82: 物理攻撃
A83: 9423.001_ | D83: SKILL_SETSUNA_SYS_201
A84: 9424_ | B84: Affect All | D84: 効果全体化
A85: 9424.001_ | D85: SETSUNA_SYS_001
A86: 9425_ | B86: HP Recovery | D86: HP回復
A87: 9425.001_ | D87: SKILL_SETSUNA_SYS_204
A88: 9426_ | B88: Add Physical Damage | D88: 物理攻撃
A89: 9426.001_ | D89: SKILL_SETSUNA_SYS_201
A90: 9427_ | B90: Add Status Boost | D90: 状態強化発生
A91: 9427.001_
A92: 9428_ | B92: Heal Status Ailments | D92: 状態異常解除
A93: 9428.001_
A94: 9429_ | B94: Add Special Damage | D94: 特殊攻撃
A95: 9429.001_
A96: 9430_ | B96: Add Status Boost | D96: 状態強化発生
A97: 9430.001_ | D97: SKILL_SETSUNA_SYS_209
A98: 9431_ | B98: ATB Boost | D98: 行動準備
A99: 9431.001_ | D99: SETSUNA_SYS_018
A100: 9432_ | B100: Add Physical Damage | D100: 物理攻撃
...

Sheet SionSkillDataMessage
A1: ID | B1: English | C1: Vietnamese | D1: Note
A2: 9629.001_ | B2: 2 | D2: 2
A3: 9630_ | B3: True | D3: True
A4: 9630.001_ | B4: 0 | D4: 0
A5: 9631_ | B5: 17 | D5: 17
A6: 9632_ | B6: Attack | C6: Tấn Công | D6: たたかう
A7: 9632.001_
A8: 9633_ | B8: Jump | C8: Phi Thân | D8: ジャンプ
A9: 9634_ | B9: Jumps into the air, temporarily withdrawing from battle. Upon descending, causes physical damage [Null] to all enemies near the target. | C9: Nhảy vút lên không trung, tạm thời rời khỏi chiến trường. Khi đáp xuống, gây sát thương vật lý [Vô hệ] lên kẻ địch gần mục tiêu. | D9: 上空へジャンプして戦闘から離脱し、落下するときに 物理攻撃［無］を対象中心に発生する。
A10: 9635_ | B10: Chase | C10: Tiếp Ứng | D10: チェイス
A11: 9636_ | B11: The user assumes a stance, and when an ally performs a physical attack will execute a follow- up attack that causes physical damage [Null]. | C11: Vào thế thủ, khi đồng minh thực hiện đòn tấn công vật lý, sẽ lập tức bồi thêm đòn đánh gây sát thương vật lý [Vô hệ]. | D11: 構えを取り、味方が物理攻撃を行うと 物理攻撃［無］を追撃として行うことができる。
A12: 9637_ | B12: Precise Thrust | C12: Xuyên Tâm | D12: 急所突き
A13: 9638_ | B13: Causes special damage [Null/15% Crit.] to enemies near the target. Critical hits will cause increased damage. | C13: Gây sát thương đặc biệt [Vô hệ/15% Chí Mạng] lên kẻ địch gần mục tiêu. Đòn chí mạng sẽ gây thêm nhiều sát thương. | D13: クリティカルが発生すると威力が大きくなる 特殊攻撃［無/CRT15%］が対象中心に発生する。
A14: 9639_ | B14: Ice | C14: Băng Kích | D14: アイス
A15: 9640_ | B15: Lowers the surrounding temperature to freezing point, causing magical damage [Water] to all enemies near the target. | C15: Hạ nhiệt độ xung quanh xuống điểm đóng băng, gây sát thương ma thuật [Thủy] lên toàn bộ kẻ địch gần mục tiêu. | D15: 周囲の温度を低下させて凝固させる 魔法攻撃［水］が対象中心に発生する。
A16: 9641_ | B16: Enfrost | C16: Ban Băng | D16: エンアイス
A17: 9642_ | B17: Adds the Water element to the attacks of all allies near the target. Water-elemental attacks will also cause more damage. | C17: Thêm nguyên tố Thủy vào đòn đánh của đồng minh gần mục tiêu. Các đòn tấn công hệ Thủy cũng sẽ gây thêm nhiều sát thương. | D17: 水属性付与が対象中心に発生する。 効果中に水属性攻撃を行うと、威力が大きくなる。
A18: 9643_ | B18: Icicle Lance | C18: Băng Thương | D18: 凍結槍
A19: 9644_ | B19: Causes physical damage [Water] to all enemies in a line from the user. Can also inflict Freeze. | C19: Gây sát thương vật lý [Thủy] lên toàn bộ kẻ địch trên đường thẳng. Có tỉ lệ gây trạng thái Đóng Băng. | D19: 物理攻撃［水］が使用者前方に発生する。 凍結が発生することもある。
... A39: 9664_ | B39: Causes special damage [Null] to all enemies near the target. Inflicts more damage the higher the Critical Hits Counter is. | C39: Gây sát thương đặc biệt [Vô hệ] lên kẻ địch gần mục tiêu. Sát thương càng tăng cao khi số lần đánh chí mạng càng nhiều. | D39: クリティカルの発生回数が多いほど 特殊攻撃［無］が対象中心に発生する。

Sheet SublimationDataMessage
A1: ID | B1: English | C1: Vietnamese | D1: Note
A2: 9664.001_ | B2: 2 | D2: 2
A3: 9665_ | B3: True | D3: True
A4: 9665.001_ | B4: 0 | D4: 0
A5: 9666_ | B5: 20 | D5: 20
A6: 9667_ | B6: Tech Power | C6: Tech Power | D6: 魔法威力
A7: 9668_ | B7: Increases damage or recovery amount. | C7: Gia tăng sát thương hoặc lượng hồi phục của kỹ năng. | D7: 攻撃や回復の威力が大きくなる
A8: 9669_ | B8: Combo Power | C8: Combo Power | D8: 連携威力
A9: 9670_ | B9: Increases the power of combos. | C9: Gia tăng uy lực của các đòn liên chiêu phối hợp combo. | D9: 連携の威力が大きくなる
A10: 9671_ | B10: Momentum Effect | C10: Momentum Effect | D10: 刹那威力
A11: 9672_ | B11: Increases the power of Momentum mode effects. | C11: Gia tăng sức mạnh của các hiệu ứng kích hoạt từ chế độ Xung Lực. | D11: 刹那システムを発動したときの威力が大きくなる
A12: 9673_ | B12: Critical Hit Rate | C12: Critical Hit Rate | D12: クリティカル率
A13: 9674_ | B13: Boosts critical hit rate and status infliction rate. | C13: Gia tăng tỉ lệ xuất hiện đòn đánh chí mạng và khả năng áp đặt bùa hại. | D13: クリティカル率や状態発生率が上昇する
A14: 9675_ | B14: ATB Bonus | C14: ATB Bonus | D14: 行動後ATB値
A15: 9676_ | B15: Increases the level of the ATB gauge after use. | C15: Nạp sẵn một phần thanh đo ATB ngay sau khi tung kỹ năng. | D15: スキル使用直後のATB初期値が大きくなる
A16: 9677_ | B16: MP Consumed | C16: MP Consumed | D16: 消費MP
A17: 9678_ | B17: Reduces the amount of MP consumed. | C17: Giảm bớt the amount of MP consumed. | D17: スキルを使用したときに消費するMPが減少する
... A42: 9703_ | B42: Support Bonus | C42: Support Bonus | D42: サポート効果
A43: 9703.001_ | C43: Cho phép chuyển giao một phần sức mạnh sang Pháp Thạch Hỗ Trợ khác.
A44: 9704_ | B44: Combo Lock Power | C44: Combo Lock Power | D44: 連携無効威力アップ
A45: 9705_ | B45: Tech's power increases, but combos cannot be used. | C45: Tech's power increases, but combos cannot be used. | D45: 対応連携が使えなくなる代わりに威力が上昇する

Sheet SubQuestMessageData
A1: ID | B1: English | C1: Vietnamese | D1: Note
A2: 9705.001_ | B2: 1
A3: 9706_{"NpcNm":"NPC_21020","QuestNm":"SUB_QUEST_0001","Head":{"Type":0,"Id":0,"NpcId":0,"QuestId":0}} | B3: Aha! You're <NAME=CP_0001> of the masked people, ain't ya! | I've got a letter for you! | C3: Aha! Ngươi là <NAME=CP_0001> của tộc Mặt Nạ phải không! Ta có thư|gửi cho ngươi đây! | D3: ……お！！ | 仮面の<NAME=CP_0001>ってのは あんたのことだよな？ な？ | 手紙預かってるんだ。
A4: 9707_{"NpcNm":"CP_0005","QuestNm":"SUB_QUEST_0001","Head":{"Type":0,"Id":1,"NpcId":0,"QuestId":0}} | B4: A letter for <NAME=CP_0001>!? From who? | C4: Thư gửi cho <NAME=CP_0001> ư!? Từ ai vậy? | D4: <NAME=CP_0001>に手紙！？ 誰から？
A5: 9708_{"NpcNm":"CP_0004","QuestNm":"SUB_QUEST_0001","Head":{"Type":0,"Id":2,"NpcId":0,"QuestId":0}} | B5: Hey! Whadd'ya think you're doin', kid!? You can't just read someone else's letter like that! | C5: Này! Nhóc con đang làm cái gì thế hả!? Sao lại tự tiện|đọc thư của người khác như vậy! | D5: おい！ こら！ 人の手紙を！
A6: 9709_{"NpcNm":"CP_0004","QuestNm":"SUB_QUEST_0001","Head":{"Type":0,"Id":3,"NpcId":0,"QuestId":0}} | B6: So...what's it say? | C6: Thế... trong thư viết gì vậy? | D6: で、なんて書いてあるんだ？
A7: 9710_{"NpcNm":"CP_0003","QuestNm":"SUB_QUEST_0001","Head":{"Type":0,"Id":4,"NpcId":0,"QuestId":0}} | B7: *Sigh*... | C7: *Thở dài*... | D7: あなたたち……。
A8: 9711_{"NpcNm":"","QuestNm":"SUB_QUEST_0001","Head":{"Type":0,"Id":5,"NpcId":0,"QuestId":0}} | B8: I am leaving this to you as I believe you have the potential to make use of it. | C8: Ta để lại vật này cho ngươi vì tin rằng ngươi có đủ|năng lực để phát huy sức mạnh của nó. | D8: 未来あるキミへの手向けとして この手紙を残す。
A9: 9712_{"NpcNm":"","QuestNm":"SUB_QUEST_0001","Head":{"Type":0,"Id":6,"NpcId":0,"QuestId":0}} | B9: As you perhaps know, in these lands there are three important altars. | It is said that if you hold up this spritnite stone at those altars, you will receive guidance for the future. | C9: Ở vùng này có ba bệ thờ trọng yếu. Nếu giơ viên|spritnite trước bệ thờ, ngươi sẽ được dẫn lối cho|tương lai. | D9: この島に３つの重要な祭壇が 存在することを知っているか？ | それらの祭壇にこの法石を掲げれば 大いなる導きが得られるという。
A10: 9713_{"NpcNm":"","QuestNm":"SUB_QUEST_0001","Head":{"Type":0,"Id":7,"NpcId":0,"QuestId":0}} | B10: First, you should visit the altar in <NAME=MA_0009_01>. | Next, the altar on <NAME=MA_0021_01>. | Then, finally, the altar in the <NAME=MA_0100_01>. | Remember this order well. | C10: Đầu tiên, hãy đến bệ thờ ở <NAME=MA_0009_01>. Tiếp theo là bệ thờ trên|<NAME=MA_0021_01>. Và cuối cùng là bệ thờ tại <NAME=MA_0100_01>. Hãy ghi nhớ kỹ thứ tự|này. | D10: はじめに訪れるべきは <NAME=MA_0009_01>の祭壇。 | 次に<NAME=MA_0021_01>の祭壇。 | 最後は<NAME=MA_0100_01>にある祭壇だ。 | よく覚えておくのだぞ。
A11: 9714_{"NpcNm":"","QuestNm":"SUB_QUEST_0001","Head":{"Type":0,"Id":8,"NpcId":0,"QuestId":0}} | B11: When you require guidance for the future, please remember this letter. | C11: Khi cần một lời chỉ dẫn cho con đường tương lai, hãy|nhớ lại nội dung bức thư này. | D11: キミの未来に導きが必要なときは この手紙の存在を思い出して欲しい。
A12: 9715_{"NpcNm":"","QuestNm":"SUB_QUEST_0001","Head":{"Type":0,"Id":9,"NpcId":0,"QuestId":0}} | B12: I hope that the wisdom of ancients can give you strength, and shine a guiding light towards the future. | C12: Ta hy vọng trí tuệ của người xưa sẽ tiếp thêm sức|mạnh và soi rọi ánh sáng dẫn lối cho ngươi. | D12: 古代の英知が、未来を照らし キミの力になることを願う。
A13: 9716_{"NpcNm":"","QuestNm":"SUB_QUEST_0001","Head":{"Type":0,"Id":10,"NpcId":0,"QuestId":0}} | B13: You obtained the <NAME=ITEM_EVT_027>. | C13: Bạn nhận được <NAME=ITEM_EVT_027>. | D13: <NAME=ITEM_EVT_027>を手に入れた。
A14: 9717_{"NpcNm":"CP_0005","QuestNm":"SUB_QUEST_0001","Head":{"Type":0,"Id":11,"NpcId":0,"QuestId":0}} | B14: What...? Who's this from? A friend of yours, <NAME=CP_0001>? | C14: Gì cơ...? Ai gửi thế này? Người quen của anh hả, <NAME=CP_0001>? | D14: なにこれ？ <NAME=CP_0001>の知り合い？
... A23: 9726_{"NpcNm":"CP_0004","QuestNm":"SUB_QUEST_0001","Head":{"Type":0,"Id":20,"NpcId":0,"QuestId":0}} | B23: You think we can really trust what this letter says? We've got an important duty to fulfill... | Do we really wanna put that at risk over somethin' we read in some shady letter? | Well, the first place it said to go to was <NAME=MA_0009_01>... | It's your decision, but if we're gonna go there, we sure as hell better keep our guard up. | C23: Mọi người nghĩ chúng ta có thể thực sự tin bức thư này|sao? Chúng ta có nhiệm vụ lớn phải làm... Chẳng lẽ|lại mạo hiểm tính mạng chỉ vì thứ viết trong một lá|thư đáng ngờ ư? Thôi được rồi, địa điểm đầu tiên nói|đến là <NAME=MA_0009_01>... Quyết định thế nào là ở cậu, nhưng nếu đến|đó, nhất định phải hết sức đề phòng. | D23: その手紙、本当に信頼できるのか？ | 俺たちにはやるべきことがあるんだ。 | 怪しい話に首ツッコんで 大事な戦力失うわけにはいかないぜ？ | 手紙で指定されてた場所は <NAME=MA_0009_01>……だったか？ | 判断はまかせるが、行くなら 気を引き締めてかからないとな。

Sheet ThreePlayerCoopSkillDataMessag
A1: ID | B1: English | C1: Vietnamese | D1: Note
A2: 9726.001_ | B2: 2 | D2: 2
A3: 9727_ | B3: True | D3: True
A4: 9727.001_ | B4: 0 | D4: 0
A5: 9728_ | B5: 70 | D5: 70
A6: 9729_ | B6: Grand Cross | C6: Thánh Giá Thần Long | D6: グランドクロス
A7: 9730_ | B7: Causes special damage [Light+Shadow/8 hits] to all enemies near the target, ignoring elemental resistance. (Cyclone/Luminaire/Charge) | C7: Gây sát thương đặc biệt [Quang+Hắc Ám/8 đòn] lên kẻ địch gần mục tiêu, bỏ qua mọi kháng nguyên tố. (Cuồng Phong/Tỏa Sáng/Xung Kích) | D7: 大いなる力を解放して、属性耐性を無視する 特殊攻撃［天&冥/8ヒット］が対象中心に発生する。 回転斬りとシャイニングとダッシュ斬りによる連携。
A8: 9731_ | B8: Galactic Force | C8: Thiên Hà Lực | D8: ギャラクシー
A9: 9732_ | B9: Unlocks the infinite power of the cosmos, causing special damage [Null] to all enemies. (Meteo/Cure/Vanish) | C9: Mở khóa sức mạnh vô tận của vũ trụ, gây sát thương đặc biệt [Vô hệ] lên toàn bộ kẻ địch. (Thiên Thạch/Trị Liệu/Tàng Hình) | D9: 宇宙にある無限の力を解き放つことで 特殊攻撃［無］が敵全体に発生する。 メテオとケアルとバニッシュによる連携。
A10: 9733_ | B10: Peerless Power | C10: Tuyệt Kỹ Vô Song | D10: アンライバルド
